Workbook
Name Produtos: Table_1[[#All],[Produtos]]
Name Produtos: Table_1[[#All],[Produtos]]
Name Produtos: Table_1[[#All],[Produtos]]

Sheet Vendas 2024
A1: Mês | B1: Data | C1: Produto | D1: QT | E1: Cliente | F1: Vendedor | G1: Custo Un | H1: Valor gasto | I1: Valor uni venda | J1: Valor da venda | K1: Tipo de venda | L1: Valor CNPJ | M1: Lucro | N1: Forma de pagam | O1: % Lucro | P1: Recebido loja
A2: 1 | B2: 45313 | C2: Cabo Kingo Iphone 1M | D2: 1 | E2: Lázaro | F2: Rafael | G2: 7 | H2: 7 | I2: 15 | J2: 15 | K2: CPF | L2: 0.53333333 | M2: 8 | P2: Transferido
A3: 1 | B3: 45313 | C3: Mini jogo de luz c/c | D3: 1 | E3: Shopee | F3: Leonardo | G3: 37 | H3: 37 | I3: 55.5 | J3: 55.5 | K3: Shopee | L3: 0.33333333 | M3: 18.5 | P3: Transferido
A4: 1 | B4: 45314 | C4: Mini jogo de luz c/c | D4: 1 | E4: Mayra blayner | F4: Leonardo | G4: 37 | H4: 37 | I4: 60 | J4: 60 | K4: CPF | L4: 0.38333333 | M4: 23 | P4: Transferido
A5: 1 | B5: 45315 | C5: Case Iphone Caixa | D5: 1 | E5: Aleatorio | F5: Rafael | G5: 18 | H5: 18 | I5: 30 | J5: 30 | K5: CPF | L5: 0.4 | M5: 12 | P5: Transferido
A6: 1 | B6: 45316 | C6: Case Iphone Caixa | D6: 1 | E6: Aleatorio | F6: Rafael | G6: 18 | H6: 18 | I6: 20 | J6: 20 | K6: CPF | L6: 0.1 | M6: 2 | P6: Transferido
A7: 1 | B7: 45317 | C7: Powebank hmaster 20k | D7: 1 | E7: Aleatorio | F7: Rafael | G7: 80 | H7: 80 | I7: 140 | J7: 140 | K7: CPF | L7: 0.42857143 | M7: 60 | P7: Transferido
A8: 1 | B8: 45318 | C8: Raquete mata mosquito | D8: 1 | E8: Projeçao | F8: Leonardo | G8: 14 | H8: 14 | I8: 30 | J8: 30 | K8: CNPJ | L8: 0.53333333 | M8: 16 | P8: Transferido
A9: 1 | B9: 45318 | C9: Raquete mata mosquito | D9: 1 | E9: Projeçao | F9: Leonardo | G9: 14 | H9: 14 | I9: 30 | J9: 30 | K9: CNPJ | L9: 0.53333333 | M9: 16 | P9: Transferido
A10: 1 | B10: 45318 | C10: Raquete mata mosquito | D10: 1 | E10: Projeçao | F10: Leonardo | G10: 14 | H10: 14 | I10: 30 | J10: 30 | K10: CNPJ | L10: 0.53333333 | M10: 16 | P10: Transferido
A11: 1 | B11: 45318 | C11: Raquete mata mosquito | D11: 1 | E11: Projeçao | F11: Leonardo | G11: 14 | H11: 14 | I11: 30 | J11: 30 | K11: CNPJ | L11: 0.53333333 | M11: 16 | P11: Transferido
A12: 1 | B12: 45318 | C12: Case Iphone Caixa | D12: 1 | E12: Aleatorio | F12: Rafael | G12: 18 | H12: 18 | I12: 20 | J12: 20 | K12: CPF | L12: 0.1 | M12: 2 | P12: Transferido
A13: 1 | B13: 45318 | C13: Luminária astronauta | D13: 1 | E13: Aleatorio | F13: Rafael | G13: 75 | H13: 75 | I13: 150 | J13: 150 | K13: CPF | L13: 0.5 | M13: 75 | P13: Transferido
... A40: 1 | B40: 45322 | C40: Smartwatch i7 pro Max | D40: 1 | E40: Amigo higor | F40: Higor | G40: 60 | H40: 60 | I40: 70 | J40: 70 | K40: CPF | L40: 0.14285714 | M40: 10 | P40: Transferido
B41: 45322 | C41: Cabo Spartan v8 | D41: 1 | E41: Trabalho | F41: Leonardo | G41: 4.5 | H41: 4.5 | I41: 10 | J41: 10 | K41: CPF | L41: 0.55 | M41: 5.5 | P41: Transferido
A42: 2 | B42: 45324 | C42: tela mosquito leo | D42: 1 | E42: Deborah | F42: Leonardo | G42: 12 | H42: 12 | I42: 20 | J42: 20 | K42: CPF | L42: 0.4 | M42: 8 | P42: Transferido
A43: 2 | B43: 45325 | C43: Mini jogo de luz c/c | D43: 1 | E43: Aleatorio | F43: Leonardo | G43: 37 | H43: 37 | I43: 85 | J43: 85 | K43: CPF | L43: 0.56470588 | M43: 48 | P43: Transferido
A44: 2 | B44: 45325 | C44: Cabo kingo tc 1m | D44: 1 | E44: Aleatorio | F44: Rafael | G44: 7 | H44: 7 | I44: 12 | J44: 12 | K44: CPF | L44: 0.41666667 | M44: 5 | P44: Transferido
A45: 2 | B45: 45325 | C45: Powebank kv12047 10k | D45: 1 | E45: Aleatorio | F45: Rafael | G45: 55 | H45: 55 | I45: 80 | J45: 80 | K45: CPF | L45: 0.3125 | M45: 25 | P45: Transferido
A46: 2 | B46: 45327 | C46: Relógio inteligente KL201 Black | D46: 1 | E46: Aleatorio | F46: Higor | G46: 32.45 | H46: 32.45 | I46: 100 | J46: 100 | K46: CPF | L46: 0.6755 | M46: 67.55 | P46: Transferido
A47: 2 | B47: 45327 | C47: Powebank kv12047 10k | D47: 1 | E47: Aleatorio | F47: Higor | G47: 55 | H47: 55 | I47: 70 | J47: 70 | K47: CPF | L47: 0.21428571 | M47: 15 | P47: Transferido
A48: 2 | B48: 45327 | C48: Cabo Spartan v8 | D48: 1 | E48: Aleatorio | F48: Higor | G48: 4.5 | H48: 4.5 | I48: 8 | J48: 8 | K48: CPF | L48: 0.4375 | M48: 3.5 | P48: Transferido
A49: 2 | B49: 45329 | C49: pilha AAA cartela | D49: 1 | E49: Aleatorio | F49: Higor | G49: 1.2 | H49: 1.2 | I49: 5 | J49: 5 | K49: CPF | L49: 0.76 | M49: 3.8 | P49: Transferido
A50: 2 | B50: 45329 | C50: Cheirinho Hungria | D50: 1 | E50: Shopee CPF | F50: Leonardo | G50: 7.5 | H50: 7.5 | I50: 10.6 | J50: 10.6 | K50: Shopee | L50: 0.29245283 | M50: 3.1 | P50: Transferido
A51: 2 | B51: 45329 | C51: Garrafa Stanley 600lm | D51: 1 | E51: Shopee CPF | F51: Leonardo | G51: 35 | H51: 35 | I51: 63.3 | J51: 63.3 | K51: Shopee | L51: 0.44707741 | M51: 28.3 | P51: Transferido
A52: 2 | B52: 45329 | C52: Cheirinho Hungria | D52: 1 | E52: Shopee CPF | F52: Leonardo | G52: 7.5 | H52: 7.5 | I52: 10.6 | J52: 10.6 | K52: Shopee | L52: 0.29245283 | M52: 3.1 | P52: Transferido
A53: 2 | B53: 45329 | C53: Cheirinho Hungria | D53: 1 | E53: Shopee CPF | F53: Leonardo | G53: 7.5 | H53: 7.5 | I53: 10.6 | J53: 10.6 | K53: Shopee | L53: 0.29245283 | M53: 3.1 | P53: Transferido
A54: 2 | B54: 45329 | C54: Mini máquina de costura | D54: 1 | E54: Shopee | F54: Leonardo | G54: 7.5 | H54: 7.5 | I54: 16.89 | J54: 16.89 | K54: Shopee | L54: 0.55595027 | M54: 9.39 | P54: Transferido
A55: 2 | B55: 45329 | C55: Carregador iphone 20w | D55: 1 | E55: Beatriz almeida sales | F55: Leonardo | G55: 0 | H55: 0 | I55: 45 | J55: 45 | K55: CPF | L55: 1 | M55: 45 | P55: Transferido
A56: 2 | B56: 45329 | C56: Fone pmcell FO-15 | D56: 1 | E56: Shopee | F56: Leonardo | G56: 9 | H56: 9 | I56: 12 | J56: 12 | K56: CNPJ | L56: 0.25 | M56: 3 | P56: Transferido
A57: 2 | B57: 45329 | C57: pilha AAA cartela | D57: 1 | E57: Marcio | F57: Leonardo | G57: 1.2 | H57: 1.2 | I57: 5 | J57: 5 | K57: CPF | L57: 0.76 | M57: 3.8 | P57: Transferido
A58: 2 | B58: 45329 | C58: pilha AAA cartela | D58: 1 | E58: Marcio | F58: Leonardo | G58: 1.2 | H58: 1.2 | I58: 5 | J58: 5 | K58: CPF | L58: 0.76 | M58: 3.8 | P58: Transferido
A59: 2 | B59: 45329 | C59: pilha AA cartela | D59: 1 | E59: Marcio | F59: Leonardo | G59: 1.2 | H59: 1.2 | I59: 5 | J59: 5 | K59: CPF | L59: 0.76 | M59: 3.8 | P59: Transferido
A60: 2 | B60: 45329 | C60: pilha AA cartela | D60: 1 | E60: Marcio | F60: Leonardo | G60: 1.2 | H60: 1.2 | I60: 5 | J60: 5 | K60: CPF | L60: 0.76 | M60: 3.8 | P60: Transferido
A61: 2 | B61: 45329 | C61: Pendrive AL 16gb | D61: 1 | E61: Marcio | F61: Leonardo | G61: 13.5 | H61: 13.5 | I61: 25 | J61: 25 | K61: CPF | L61: 0.46 | M61: 11.5 | P61: Transferido
A62: 2 | B62: 45329 | C62: Suporte celular veicular ventosa bmg02 | D62: 1 | E62: Matheus | F62: Leonardo | G62: 10 | H62: 10 | I62: 25 | J62: 25 | K62: CPF | L62: 0.6 | M62: 15 | P62: Transferido
A63: 2 | B63: 45329 | C63: Carregador veicular inova tc | D63: 1 | E63: Matheus | F63: Leonardo | G63: 11 | H63: 11 | I63: 25 | J63: 25 | K63: CPF | L63: 0.56 | M63: 14 | P63: Transferido
A64: 2 | B64: 45330 | C64: Suporte magnético veicular barra | D64: 1 | E64: Aleatorio | F64: Higor | G64: 6 | H64: 6 | I64: 8 | J64: 8 | K64: CPF | L64: 0.25 | M64: 2 | P64: Transferido
A65: 2 | B65: 45330 | C65: Adaptador wifi 2.5g | D65: 1 | E65: Marcio | F65: Leonardo | G65: 11 | H65: 11 | I65: 25 | J65: 25 | K65: CPF | L65: 0.56 | M65: 14 | P65: Transferido
A66: 2 | B66: 45330 | C66: Adaptador wifi 2.5g antena | D66: 1 | E66: Marcio | F66: Leonardo | G66: 12 | H66: 12 | I66: 30 | J66: 30 | K66: CPF | L66: 0.6 | M66: 18 | P66: Transferido
A67: 2 | B67: 45330 | C67: Mouse wireless recarregável led rgb 2.4 ghz sem fio | D67: 1 | E67: Aleatorio | F67: Leonardo | G67: 18 | H67: 18 | I67: 35 | J67: 35 | K67: CPF | L67: 0.48571429 | M67: 17 | P67: Transferido
... A102: 2 | B102: 45339 | C102: Jogo de chaves peq. | D102: 1 | E102: Aleatorio | F102: Rafael | G102: 3.5 | H102: 3.5 | I102: 10 | J102: 10 | K102: CPF | L102: 0.65 | M102: 6.5 | P102: Transferido
A103: 2 | B103: 45339 | C103: Xtreme 3 | D103: 1 | E103: Aleatorio | F103: Rafael | G103: 0 | H103: 0 | I103: 165 | J103: 165 | K103: CPF | L103: 1 | M103: 165 | P103: Transferido
A104: 2 | B104: 45339 | C104: Suporte veicular ventosa it-blue | D104: 1 | E104: Aleatorio | F104: Rafael | G104: 11 | H104: 11 | I104: 15 | J104: 15 | K104: CPF | L104: 0.26666667 | M104: 4 | P104: Transferido
A105: 2 | B105: 45339 | C105: Mini massageador | D105: 1 | E105: Aleatorio | F105: Rafael | G105: 8 | H105: 8 | I105: 15 | J105: 15 | K105: CPF | L105: 0.46666667 | M105: 7 | P105: Transferido
A106: 2 | B106: 45339 | C106: Copo Stanley com som | D106: 1 | E106: Aleatorio | F106: Rafael | G106: 65 | H106: 65 | I106: 96.35 | J106: 96.35 | K106: CPF | L106: 0.32537623 | M106: 31.35 | P106: Transferido
A107: 2 | B107: 45339 | C107: Pelicula 3D | D107: 1 | E107: Aleatorio | F107: Rafael | G107: 3 | H107: 3 | I107: 15 | J107: 15 | K107: CPF | L107: 0.8 | M107: 12 | P107: Transferido
A108: 2 | B108: 45341 | C108: Fone iphone hmaster ej-56 | D108: 1 | E108: jazin | F108: Rafael | G108: 12 | H108: 12 | I108: 25 | J108: 25 | K108: CPF | L108: 0.52 | M108: 13 | P108: Transferido
A109: 2 | B109: 45342 | C109: Pelicula 3D | D109: 1 | E109: Renatinha | F109: Leonardo | G109: 3 | H109: 3 | I109: 10 | J109: 10 | K109: CPF | L109: 0.7 | M109: 7 | P109: Transferido
A110: 2 | B110: 45342 | C110: Pelicula 3D | D110: 1 | E110: Renatinha | F110: Leonardo | G110: 3 | H110: 3 | I110: 10 | J110: 10 | K110: CPF | L110: 0.7 | M110: 7 | P110: Transferido
A111: 2 | B111: 45342 | C111: Pelicula 3D | D111: 1 | E111: Renatinha | F111: Leonardo | G111: 3 | H111: 3 | I111: 10 | J111: 10 | K111: CPF | L111: 0.7 | M111: 7 | P111: Transferido
A112: 2 | B112: 45342 | C112: Carregador iphone 20w | D112: 1 | E112: Renatinha | F112: Leonardo | G112: 0 | H112: 0 | I112: 45 | J112: 45 | K112: CPF | L112: 1 | M112: 45 | P112: Transferido
A113: 2 | B113: 45342 | C113: Case Iphone transparente | D113: 1 | E113: Renatinha | F113: Leonardo | G113: 5 | H113: 5 | I113: 10 | J113: 10 | K113: CPF | L113: 0.5 | M113: 5 | P113: Transferido
A114: 2 | B114: 45342 | C114: Case Iphone Caixa | D114: 1 | E114: Renatinha | F114: Leonardo | G114: 18 | H114: 18 | I114: 30 | J114: 30 | K114: CPF | L114: 0.4 | M114: 12 | P114: Transferido
A115: 2 | B115: 45342 | C115: Cabo colorido iphone 1m | D115: 1 | E115: Aleatorio | F115: Leonardo | G115: 2.5 | H115: 2.5 | I115: 10 | J115: 10 | K115: CPF | L115: 0.75 | M115: 7.5 | P115: Transferido
A116: 2 | B116: 45342 | C116: Pelicula 3D | D116: 1 | E116: Aleatorio | F116: Leonardo | G116: 3 | H116: 3 | I116: 10 | J116: 10 | K116: CPF | L116: 0.7 | M116: 7 | P116: Transferido
A117: 2 | B117: 45344 | C117: Capa a prova d'água | D117: 1 | E117: Aleatorio | F117: Leonardo | G117: 3.5 | H117: 3.5 | I117: 10 | J117: 10 | K117: CPF | L117: 0.65 | M117: 6.5 | P117: Transferido
A118: 2 | B118: 45344 | C118: Capa a prova d'água | D118: 1 | E118: Aleatorio | F118: Leonardo | G118: 3.5 | H118: 3.5 | I118: 10 | J118: 10 | K118: CPF | L118: 0.65 | M118: 6.5 | P118: Transferido
A119: 2 | B119: 45345 | C119: Copo Stanley com som | D119: 1 | E119: Sarah | F119: Leonardo | G119: 65 | H119: 65 | I119: 98 | J119: 98 | K119: CPF | L119: 0.33673469 | M119: 33 | P119: Transferido
A120: 2 | B120: 45346 | C120: Xerox Preta | D120: 7 | E120: Aleatorio | F120: Leonardo | G120: 0.05 | H120: 0.35 | I120: 0.5 | J120: 3.5 | K120: CPF | L120: 0.9 | M120: 3.15 | P120: Transferido
A121: 2 | B121: 45346 | C121: Xerox Preta | D121: 25 | E121: Aleatorio | F121: Leonardo | G121: 0.05 | H121: 1.25 | I121: 1 | J121: 25 | K121: CPF | L121: 0.95 | M121: 23.75 | P121: Transferido
A122: 2 | B122: 45346 | C122: Serviço aleatorio | D122: 1 | E122: Aleatorio | F122: Leonardo | G122: 0 | H122: 0 | I122: 10 | J122: 10 | K122: CPF | L122: 1 | M122: 10 | P122: Transferido
A123: 2 | B123: 45346 | C123: Mochila escolar universitária unissex com estojo | D123: 1 | E123: Aleatorio | F123: Rafael | G123: 31.99 | H123: 31.99 | I123: 50 | J123: 50 | K123: CPF | L123: 0.3602 | M123: 18.01 | P123: Transferido
A124: 2 | B124: 45346 | C124: Mochila escolar universitária unissex com estojo | D124: 1 | E124: Aleatorio | F124: Rafael | G124: 31.99 | H124: 31.99 | I124: 50 | J124: 50 | K124: CPF | L124: 0.3602 | M124: 18.01 | P124: Transferido
... A129: 2 | B129: 45349 | C129: Cabo kingo tc 1m | D129: 1 | E129: Aleatorio | F129: Leonardo | G129: 7 | H129: 7 | I129: 20 | J129: 20 | K129: CPF | L129: 0.65 | M129: 13 | P129: Transferido
A130: 2 | B130: 45349 | C130: Regua tomada | D130: 1 | E130: Aleatorio | F130: Rafael | G130: 26 | H130: 26 | I130: 50 | J130: 50 | K130: CPF | L130: 0.48 | M130: 24 | O130: 50 | P130: Ainda não
A131: 2 | B131: 45350 | C131: Cadeado alarme | D131: 1 | E131: mkd | F131: Leonardo | G131: 0 | H131: 0 | I131: 70 | J131: 70 | K131: CPF | L131: 1 | M131: 70 | P131: Transferido
A132: 2 | B132: 45350 | C132: Pelicula 3D | D132: 1 | E132: Samara | F132: Leonardo | G132: 3 | H132: 3 | I132: 10 | J132: 10 | K132: CPF | L132: 0.7 | M132: 7 | O132: 10 | P132: Ainda não
A133: 2 | B133: 45350 | C133: Raquete mata mosquito | D133: 1 | E133: andre | F133: Leonardo | G133: 14 | H133: 14 | I133: 30 | J133: 30 | K133: CPF | L133: 0.53333333 | M133: 16 | P133: Transferido
A134: 2 | B134: 45350 | C134: Xerox Preta | D134: 6 | E134: Aleatorio | F134: Leonardo | G134: 0.05 | H134: 0.3 | I134: 1 | J134: 6 | K134: CPF | L134: 0.95 | M134: 5.7 | P134: Transferido
A135: 3 | B135: 45352 | C135: Controle Pc | D135: 1 | E135: Aleatorio | F135: Rafael | G135: 20 | H135: 20 | I135: 35 | J135: 35 | K135: CPF | L135: 0.42857143 | M135: 15 | P135: Transferido
A136: 3 | B136: 45352 | C136: Pelicularelogio 49mm | D136: 1 | E136: Aleatorio | F136: Rafael | G136: 6 | H136: 6 | I136: 15 | J136: 15 | K136: CPF | L136: 0.6 | M136: 9 | O136: 15 | P136: Ainda não
A137: 3 | B137: 45352 | C137: Garrafa 3 in 1 colorida | D137: 1 | E137: Aleatorio | F137: Rafael | G137: 22 | H137: 22 | I137: 40 | J137: 40 | K137: CPF | L137: 0.45 | M137: 18 | O137: 40 | P137: Ainda não
A138: 3 | B138: 45352 | C138: Cabo colorido iphone 1m | D138: 1 | E138: Aleatorio | F138: Rafael | G138: 2.5 | H138: 2.5 | I138: 10 | J138: 10 | K138: CPF | L138: 0.75 | M138: 7.5 | O138: 10 | P138: Ainda não
A139: 3 | B139: 45352 | C139: Capinha | D139: 1 | E139: Aleatorio | F139: Rafael | G139: 3 | H139: 3 | I139: 10 | J139: 10 | K139: CPF | L139: 0.7 | M139: 7 | P139: Transferido
A140: 3 | B140: 45352 | C140: Xerox Preta | D140: 3 | E140: Aleatorio | F140: Higor | G140: 0.05 | H140: 0.15 | I140: 1 | J140: 3 | K140: CPF | L140: 0.95 | M140: 2.85 | P140: Transferido
A141: 3 | B141: 45352 | C141: faca | D141: 1 | E141: Aleatorio | F141: Rafael | G141: 35 | H141: 35 | I141: 50 | J141: 50 | K141: CPF | L141: 0.3 | M141: 15 | O141: 50 | P141: Ainda não
A142: 3 | B142: 45355 | C142: Xerox Preta | D142: 1 | E142: Aleatorio | F142: Leonardo | G142: 0.05 | H142: 0.05 | I142: 1 | J142: 1 | K142: CPF | L142: 0.95 | M142: 0.95 | P142: Transferido
A143: 3 | B143: 45355 | C143: Relógio Inteligente Bluetooth 4.0 Smartwatch D20 1.3" 150mah | D143: 1 | E143: policia | F143: Leonardo | G143: 27.9 | H143: 27.9 | I143: 50 | J143: 50 | K143: CPF | L143: 0.442 | M143: 22.1 | P143: Transferido
A144: 3 | B144: 45356 | C144: Carregador Cabeça Spartan - Cw-178 | D144: 1 | E144: giovanni | F144: Leonardo | G144: 12 | H144: 12 | I144: 25 | J144: 25 | K144: CPF | L144: 0.52 | M144: 13 | O144: 25 | P144: Ainda não
A145: 3 | B145: 45357 | C145: Impressao Preta | D145: 2 | E145: magdar | F145: Leonardo | G145: 0.07 | H145: 0.14 | I145: 1 | J145: 2 | K145: CPF | L145: 0.93 | M145: 1.86 | P145: Transferido
A146: 3 | B146: 45358 | C146: Pelicula 3D | D146: 1 | E146: Aleatorio | F146: Leonardo | G146: 3 | H146: 3 | I146: 15 | J146: 15 | K146: CPF | L146: 0.8 | M146: 12 | P146: Transferido
A147: 3 | B147: 45358 | C147: Capinha | D147: 1 | E147: primo | F147: Rafael | G147: 3 | H147: 3 | I147: 10 | J147: 10 | K147: CPF | L147: 0.7 | M147: 7 | P147: Transferido
A148: 3 | B148: 45358 | C148: Fone Bluetooth Sem Fios P9 | D148: 1 | E148: primo | F148: Rafael | G148: 18.74 | H148: 18.74 | I148: 50 | J148: 50 | K148: CPF | L148: 0.6252 | M148: 31.26 | P148: Transferido
A149: 3 | B149: 45358 | C149: Mini liquidificado | D149: 1 | E149: Aleatorio | F149: Leonardo | G149: 25 | H149: 25 | I149: 49.31 | J149: 49.31 | K149: CNPJ | L149: 0.49300345 | M149: 24.31 | P149: Transferido
A150: 3 | B150: 45358 | C150: Blindagem | D150: 1 | E150: jorlan | F150: Leonardo | G150: 0 | H150: 0 | I150: 30 | J150: 30 | K150: CPF | L150: 1 | M150: 30 | P150: Transferido
A151: 3 | B151: 45358 | C151: Game Pop It | D151: 1 | E151: Sah | F151: Leonardo | G151: 27 | H151: 27 | I151: 40 | J151: 40 | K151: CPF | L151: 0.325 | M151: 13 | P151: Transferido
A152: 3 | B152: 45359 | C152: Cabo Colorido Tipo C 1M | D152: 1 | E152: Aleatorio | F152: Rafael | G152: 2.5 | H152: 2.5 | I152: 10 | J152: 10 | K152: CPF | L152: 0.75 | M152: 7.5 | P152: Transferido
A153: 3 | B153: 45359 | C153: Powebank Kv12047 10K | D153: 1 | E153: Aleatorio | F153: Rafael | G153: 55 | H153: 55 | I153: 80 | J153: 80 | K153: CPF | L153: 0.3125 | M153: 25 | O153: 80 | P153: Ainda não
A154: 3 | B154: 45360 | C154: Lanterna T9 | D154: 1 | E154: Aleatorio | F154: Rafael | G154: 37 | H154: 37 | I154: 60 | J154: 60 | K154: CPF | L154: 0.38333333 | M154: 23 | P154: Transferido
A155: 3 | B155: 45360 | C155: Chave de rodas | D155: 1 | E155: Aleatorio | F155: Rafael | G155: 28 | H155: 28 | I155: 50 | J155: 50 | K155: CPF | L155: 0.44 | M155: 22 | P155: Transferido
A156: 3 | B156: 45360 | C156: Cabo Kingo Iphone 1M | D156: 1 | E156: Aleatorio | F156: Rafael | G156: 7 | H156: 7 | I156: 20 | J156: 20 | K156: CPF | L156: 0.65 | M156: 13 | P156: Transferido
A157: 3 | B157: 45360 | C157: Controle ps2 | D157: 1 | E157: Aleatorio | F157: Rafael | G157: 20 | H157: 20 | I157: 40 | J157: 40 | K157: CPF | L157: 0.5 | M157: 20 | P157: Transferido
A158: 3 | B158: 45362 | C158: Garrafa 3 In 1 Colorida | D158: 1 | E158: jacqueline | F158: Leonardo | G158: 22 | H158: 22 | I158: 35 | J158: 35 | K158: CPF | L158: 0.37142857 | M158: 13 | P158: Transferido
A159: 3 | B159: 45362 | C159: Mini liquidificado | D159: 1 | E159: LOJA | F159: Leonardo | G159: 25 | H159: 25 | I159: 50 | J159: 50 | K159: CPF | L159: 0.5 | M159: 25 | P159: Transferido
A160: 3 | B160: 45362 | C160: Xerox Preta | D160: 1 | E160: Aleatorio | F160: Leonardo | G160: 0.05 | H160: 0.05 | I160: 1 | J160: 1 | K160: CPF | L160: 0.95 | M160: 0.95 | P160: Transferido
A161: 3 | B161: 45363 | C161: Impressao Preta | D161: 1 | E161: Aleatorio | F161: Leonardo | G161: 0.07 | H161: 0.07 | I161: 1 | J161: 1 | K161: CPF | L161: 0.93 | M161: 0.93 | P161: Transferido
A162: 3 | B162: 45364 | C162: Cabo Kingo Iphone 1M | D162: 1 | E162: Aleatorio | F162: Leonardo | G162: 7 | H162: 7 | I162: 15 | J162: 15 | K162: CPF | L162: 0.53333333 | M162: 8 | P162: Transferido
A163: 3 | B163: 45364 | C163: Pelicula 3D | D163: 1 | E163: Aleatorio | F163: Leonardo | G163: 3 | H163: 3 | I163: 15 | J163: 15 | K163: CPF | L163: 0.8 | M163: 12 | P163: Transferido
A164: 3 | B164: 45364 | C164: Bolsa Multifuncional Masculina De Peito | D164: 1 | E164: Aleatorio | F164: Leonardo | G164: 13 | H164: 13 | I164: 25 | J164: 25 | K164: CPF | L164: 0.48 | M164: 12 | P164: Transferido
...

Sheet Vendas 2025
A1: Mês | B1: Data | C1: Produto | D1: QT | E1: Cliente | F1: Vendedor | G1: Custo Un | H1: Valor gasto | I1: Valor uni venda | J1: Valor da venda | K1: Tipo de venda | L1: Valor CNPJ | M1: Lucro | N1: Forma de pagam | O1: % Lucro | P1: Recebido loja
A2: 1 | B2: 45659 | C2: Fonte 12v | D2: 1 | E2: hugo Som | F2: Fisica | G2: 10 | H2: 10 | I2: 15 | J2: 15 | K2: cpf | L2: 0.33333333 | M2: 5 | P2: Transferido
A3: 1 | B3: 45659 | C3: impressao preta | D3: 1 | E3: senhor loja | F3: Fisica | G3: 0.07 | H3: 0.07 | I3: 1 | J3: 1 | K3: cpf | L3: 0.93 | M3: 0.93 | P3: Transferido
A4: 1 | B4: 45659 | C4: Serviço Aleatorio | D4: 1 | E4: Aleatorio | F4: Fisica | G4: 0 | H4: 0 | I4: 10 | J4: 10 | K4: cpf | L4: 1 | M4: 10 | P4: Transferido
A5: 1 | B5: 45659 | C5: adaptador bluetooth | D5: 1 | E5: cliente israel | F5: Fisica | G5: 5 | H5: 5 | I5: 20 | J5: 20 | K5: cpf | L5: 0.75 | M5: 15 | P5: Transferido
A6: 1 | B6: 45659 | C6: Controle wireless gamepad alto-4w | D6: 1 | E6: cliente israel | F6: Fisica | G6: 63 | H6: 63 | I6: 110 | J6: 110 | K6: cpf | L6: 0.42727273 | M6: 47 | P6: Transferido
A7: 1 | B7: 45660 | C7: impressao preta | D7: 5 | E7: Aleatorio | F7: Fisica | G7: 0.07 | H7: 0.35 | I7: 1 | J7: 5 | K7: cpf | L7: 0.93 | M7: 4.65 | P7: Transferido
A8: 1 | B8: 45660 | C8: pelicula 3d | D8: 1 | E8: Aleatorio | F8: Fisica | G8: 3 | H8: 3 | I8: 15 | J8: 15 | K8: cpf | L8: 0.8 | M8: 12 | P8: Transferido
A9: 1 | B9: 45660 | C9: Serviço Aleatorio | D9: 1 | E9: Aleatorio | F9: Fisica | G9: 0 | H9: 0 | I9: 29 | J9: 29 | K9: cpf | L9: 1 | M9: 29 | P9: Transferido
A10: 1 | B10: 45660 | C10: pelicula 3d | D10: 2 | E10: Aleatorio | F10: Fisica | G10: 3 | H10: 6 | I10: 15 | J10: 30 | K10: cpf | L10: 0.8 | M10: 24 | P10: Transferido
A11: 1 | B11: 45660 | C11: capinha | D11: 2 | E11: Aleatorio | F11: Fisica | G11: 3 | H11: 6 | I11: 15 | J11: 30 | K11: cpf | L11: 0.8 | M11: 24 | P11: Transferido
A12: 1 | B12: 45661 | C12: luvinha de dedo | D12: 2 | E12: Aleatorio | F12: Fisica | G12: 0 | H12: 0 | I12: 5 | J12: 10 | K12: cpf | L12: 1 | M12: 10 | P12: Transferido
A13: 1 | B13: 45663 | C13: impressao preta | D13: 2 | E13: Cliente Impressão João Pedro | F13: Fisica | G13: 0.07 | H13: 0.14 | I13: 1 | J13: 2 | K13: cpf | L13: 0.93 | M13: 1.86 | P13: Transferido
A14: 1 | B14: 45663 | C14: Formatação | D14: 1 | E14: Cliente Pc Ronei | F14: Fisica | G14: 0 | H14: 0 | I14: 60 | J14: 60 | K14: cpf | L14: 1 | M14: 60 | P14: Transferido
A15: 1 | B15: 45663 | C15: impressao preta | D15: 2 | E15: Cliente mateus impressao | F15: Fisica | G15: 0.07 | H15: 0.14 | I15: 1 | J15: 2 | K15: cpf | L15: 0.93 | M15: 1.86 | P15: Transferido
A16: 1 | B16: 45663 | C16: Serviço Aleatorio | D16: 1 | E16: Aleatorio | F16: Fisica | G16: 0 | H16: 0 | I16: 5 | J16: 5 | K16: cpf | L16: 1 | M16: 5 | P16: Transferido
A17: 1 | B17: 45664 | C17: impressao preta | D17: 3 | E17: Aleatorio | F17: Fisica | G17: 0.07 | H17: 0.21 | I17: 1 | J17: 3 | K17: cpf | L17: 0.93 | M17: 2.79 | P17: Transferido
A18: 1 | B18: 45664 | C18: impressao preta | D18: 1 | E18: hugo Som | F18: Fisica | G18: 0.07 | H18: 0.07 | I18: 1 | J18: 1 | K18: cpf | L18: 0.93 | M18: 0.93 | P18: Transferido
A19: 1 | B19: 45664 | C19: chip com recarga | D19: 2 | E19: Aleatorio | F19: Fisica | G19: 0 | H19: 0 | I19: 30 | J19: 60 | K19: cpf | L19: 1 | M19: 60 | P19: Transferido
A20: 1 | B20: 45664 | C20: manutençao | D20: 1 | E20: Aleatorio | F20: luiz | G20: 0 | H20: 0 | I20: 37.5 | J20: 37.5 | K20: cpf | L20: 1 | M20: 37.5 | P20: Transferido
A21: 1 | B21: 45664 | C21: Serviço Aleatorio | D21: 1 | E21: Aleatorio | F21: luiz | G21: 0 | H21: 0 | I21: 150 | J21: 150 | K21: cpf | L21: 0.35 | M21: 150 | P21: Transferido
A22: 1 | B22: 45664 | C22: Pendrive 16gb AL-U-16 | D22: 1 | E22: luiz | F22: Fisica | G22: 13 | H22: 13 | I22: 20 | J22: 20 | K22: cpf | L22: 0.73333333 | M22: 7 | P22: Transferido
A23: 1 | B23: 45664 | C23: PILHA FLEX AAA | D23: 1 | E23: Aleatorio | F23: Fisica | G23: 4 | H23: 4 | I23: 15 | J23: 15 | K23: cpf | L23: 0.93 | M23: 11 | P23: Transferido
A24: 1 | B24: 45665 | C24: impressao preta | D24: 5 | E24: hugo Som | F24: Fisica | G24: 0.07 | H24: 0.35 | I24: 1 | J24: 5 | K24: cpf | L24: 1 | M24: 4.65 | P24: Transferido
A25: 1 | B25: 45665 | C25: pelicula 3d | D25: 1 | E25: Aleatorio | F25: Fisica | G25: 3 | H25: 3 | I25: 15 | J25: 15 | K25: cpf | L25: 0.8 | M25: 12 | P25: Transferido
A26: 1 | B26: 45665 | C26: Cabo auxiliar p2 LE-804 | D26: 1 | E26: RELOGIO | F26: Fisica | G26: 2.5 | H26: 2.5 | I26: 10 | J26: 10 | L26: 0.75 | M26: 7.5 | P26: Transferido
A27: 1 | B27: 45666 | C27: impressao preta | D27: 1 | E27: senhor | F27: Fisica | G27: 0.07 | H27: 0.07 | I27: 1 | J27: 1 | K27: cpf | L27: 0.93 | M27: 0.93 | P27: Transferido
A28: 1 | B28: 45666 | C28: luvinha de dedo | D28: 2 | E28: Aleatorio | F28: Fisica | G28: 0 | H28: 0 | I28: 5 | J28: 10 | K28: cpf | L28: 1 | M28: 10 | P28: Transferido
A29: 1 | B29: 45667 | C29: Carregador tipo c 4.1 LE-497 | D29: 1 | E29: Aleatorio | F29: Fisica | G29: 10 | H29: 10 | I29: 30 | J29: 30 | K29: cpf | L29: 0.66666667 | M29: 20 | P29: Transferido
A30: 1 | B30: 45668 | C30: Cabo Kingo Iphone 1M | D30: 1 | E30: fernando | F30: Fisica | G30: 7 | H30: 7 | I30: 20 | J30: 20 | K30: cpf | L30: 0.65 | M30: 13 | P30: Transferido
A31: 1 | B31: 45671 | C31: impressao preta | D31: 5 | E31: hugo Som | F31: Fisica | G31: 0.07 | H31: 0.35 | I31: 1 | J31: 5 | K31: cpf | L31: 0.93 | M31: 4.65 | P31: Transferido
A32: 1 | B32: 45671 | C32: impressao preta | D32: 1 | E32: Aleatorio | F32: Fisica | G32: 0.07 | H32: 0.07 | I32: 1 | J32: 1 | K32: cpf | L32: 0.93 | M32: 0.93 | P32: Transferido
A33: 1 | B33: 45671 | C33: Bateria 2032 | D33: 1 | E33: Aleatorio | F33: Fisica | G33: 1 | H33: 1 | I33: 5 | J33: 5 | K33: cpf | L33: 0.8 | M33: 4 | P33: Transferido
A34: 1 | B34: 45672 | C34: impressao preta | D34: 2 | E34: Aleatorio | F34: Fisica | G34: 0.07 | H34: 0.14 | I34: 1 | J34: 2 | K34: cpf | L34: 0.93 | M34: 1.86 | P34: Transferido
A35: 1 | B35: 45672 | C35: impressao preta | D35: 9 | E35: Aleatorio | F35: Fisica | G35: 0.07 | H35: 0.63 | I35: 1 | J35: 9 | K35: cpf | L35: 0.93 | M35: 8.37 | P35: Transferido
A36: 1 | B36: 45672 | C36: Fonte notebook grasep | D36: 1 | E36: Diretora higor | F36: Fisica | G36: 32 | H36: 32 | I36: 70 | J36: 70 | K36: cpf | L36: 0.54285714 | M36: 38 | P36: Transferido
A37: 1 | B37: 45672 | C37: Envelope A4 | D37: 1 | E37: Aleatorio | F37: Fisica | G37: 0.3955 | H37: 0.3955 | I37: 1 | J37: 1 | K37: cpf | L37: 0.6045 | M37: 0.6045 | P37: Transferido
A38: 1 | B38: 45672 | C38: Escova magica | D38: 2 | E38: leandro | F38: Fisica | G38: 25 | H38: 50 | I38: 50 | J38: 100 | K38: cpf | L38: 0.5 | M38: 50 | P38: Transferido
A39: 1 | B39: 45672 | C39: manutençao | D39: 1 | E39: Diretora higor | F39: luiz | G39: 0 | H39: 0 | I39: 50 | J39: 50 | K39: cpf | L39: 1 | M39: 50 | P39: Transferido
A40: 1 | B40: 45672 | C40: Suporte Moto Le-030D | D40: 1 | E40: Aleatorio | F40: Fisica | G40: 16 | H40: 16 | I40: 35 | J40: 35 | K40: cpf | L40: 0.54285714 | M40: 19 | P40: Transferido
A41: 1 | B41: 45672 | C41: Serviço Aleatorio | D41: 1 | E41: Aleatorio | F41: Fisica | G41: 0 | H41: 0 | I41: 57.5 | J41: 57.5 | K41: cpf | L41: 1 | M41: 57.5 | P41: Transferido
A42: 1 | B42: 45674 | C42: Mouse com fio exbom MD-9 | D42: 1 | E42: naiane | F42: Fisica | G42: 5.5 | H42: 5.5 | I42: 15 | J42: 15 | K42: cpf | L42: 0.63333333 | M42: 9.5 | P42: Transferido
A43: 1 | B43: 45674 | C43: Formatação | D43: 1 | E43: naiane | F43: Fisica | G43: 0 | H43: 0 | I43: 50 | J43: 50 | K43: cpf | L43: 1 | M43: 50 | P43: Transferido
A44: 1 | B44: 45674 | C44: Lanterna Chaveiro Recarregável | D44: 1 | E44: Magdar | F44: Fisica | G44: 10 | H44: 10 | I44: 20 | J44: 20 | K44: cpf | L44: 0.5 | M44: 10 | P44: Transferido
A45: 1 | B45: 45674 | C45: Jogo C 2 Canecas Vidro Chopp 480Ml | D45: 1 | E45: remedio | F45: Fisica | G45: 19 | H45: 19 | I45: 25 | J45: 25 | K45: cpf | L45: 0.24 | M45: 6 | P45: Transferido
A46: 1 | B46: 45674 | C46: caixa de som kts-1576 | D46: 1 | E46: max | F46: Fisica | G46: 60 | H46: 60 | I46: 90 | J46: 90 | K46: cpf | L46: 0.33333333 | M46: 30 | P46: Transferido
A47: 1 | B47: 45675 | C47: PILHA SULYC AAA | D47: 1 | E47: andre | F47: Fisica | G47: 2.5 | H47: 2.5 | I47: 10 | J47: 10 | K47: cpf | L47: 0.75 | M47: 7.5 | P47: Transferido
A48: 1 | B48: 45675 | C48: Miniteclado Tv Box | D48: 1 | E48: andre | F48: Fisica | G48: 19 | H48: 19 | I48: 30 | J48: 30 | K48: cpf | L48: 0.36666667 | M48: 11 | P48: Transferido
A49: 1 | B49: 45675 | C49: Cabo Kingo Iphone 2M Leo | D49: 1 | E49: Aleatorio | F49: Fisica | G49: 10 | H49: 10 | I49: 25 | J49: 25 | K49: cpf | L49: 0.6 | M49: 15 | P49: Transferido
A50: 1 | B50: 45675 | C50: manutençao | D50: 1 | E50: andre | F50: Fisica | G50: 0 | H50: 0 | I50: 37 | J50: 37 | K50: cpf | L50: 1 | M50: 37 | P50: Transferido
A51: 1 | B51: 45675 | C51: lamapada 40w | D51: 1 | E51: Karol G | F51: Fisica | G51: 15 | H51: 15 | I51: 50 | J51: 50 | K51: cpf | L51: 0.7 | M51: 35 | N51: 50 | P51: Transferido
A52: 1 | B52: 45675 | C52: Lâmpada Led 9W | D52: 1 | E52: Karol G | F52: Fisica | G52: 4.5 | H52: 4.5 | I52: 15 | J52: 15 | K52: cpf | L52: 0.7 | M52: 10.5 | N52: 15 | P52: Transferido
A53: 1 | B53: 45677 | C53: pelicula 3d | D53: 1 | E53: Aleatorio | F53: Fisica | G53: 3 | H53: 3 | I53: 15 | J53: 15 | K53: cpf | L53: 0.8 | M53: 12 | P53: Transferido
A54: 1 | B54: 45678 | C54: impressao preta | D54: 2 | E54: Aleatorio | F54: Fisica | G54: 0.07 | H54: 0.14 | I54: 1 | J54: 2 | K54: cpf | L54: 0.93 | M54: 1.86 | P54: Transferido
A55: 1 | B55: 45680 | C55: impressao preta | D55: 12 | E55: Aleatorio | F55: Fisica | G55: 0.07 | H55: 0.84 | I55: 1 | J55: 12 | K55: cpf | L55: 0.93 | M55: 11.16 | P55: Transferido
A56: 1 | B56: 45680 | C56: Envelope A4 | D56: 1 | E56: Aleatorio | F56: Fisica | G56: 0.3955 | H56: 0.3955 | I56: 2 | J56: 2 | K56: cpf | L56: 0.80225 | M56: 1.6045 | P56: Transferido
A57: 1 | B57: 45680 | C57: Manutençao | D57: 1 | E57: Aleatorio | F57: Fisica | G57: 0 | H57: 0 | I57: 61.75 | J57: 61.75 | K57: cpf | L57: 1 | M57: 61.75 | P57: Transferido
A58: 1 | B58: 45680 | C58: Manutençao | D58: 1 | E58: Aleatorio | F58: Fisica | G58: 0 | H58: 0 | I58: 20 | J58: 20 | K58: cpf | L58: 1 | M58: 20 | P58: Transferido
A59: 1 | B59: 45680 | C59: Carregador completo tipoc LE-285CC | D59: 1 | E59: Aleatorio | F59: Fisica | G59: 11 | H59: 11 | I59: 30 | J59: 30 | K59: cpf | L59: 0.63333333 | M59: 19 | P59: Transferido
A60: 1 | B60: 45680 | C60: Máquina De Cabelo Dragão | D60: 1 | E60: hugo Som | F60: Fisica | G60: 18 | H60: 18 | I60: 20 | J60: 20 | K60: cpf | L60: 0.1 | M60: 2 | P60: Transferido
A61: 1 | B61: 45680 | C61: Fonte tv box 5v | D61: 1 | E61: Aleatorio | F61: Fisica | G61: 7 | H61: 7 | I61: 25 | J61: 25 | K61: cpf | L61: 0.72 | M61: 18 | P61: Transferido
A62: 1 | B62: 45681 | C62: chip com recarga | D62: 1 | E62: Aleatorio | F62: Fisica | G62: 18 | H62: 18 | I62: 30 | J62: 30 | K62: cpf | L62: 0.4 | M62: 12 | P62: Transferido
A63: 1 | B63: 45681 | C63: impressao preta | D63: 1 | E63: Aleatorio | F63: Fisica | G63: 0.07 | H63: 0.07 | I63: 1 | J63: 1 | K63: cpf | L63: 0.93 | M63: 0.93 | P63: Transferido
A64: 1 | B64: 45681 | C64: chip com recarga | D64: 1 | E64: serrat | F64: Fisica | G64: 18 | H64: 18 | I64: 30 | J64: 30 | K64: cpf | L64: 0.6 | M64: 12 | P64: Transferido
A65: 1 | B65: 45682 | C65: manutençao | D65: 1 | E65: Aleatorio | F65: luiz | G65: 0 | H65: 0 | I65: 35 | J65: 35 | K65: cpf | L65: 0.4 | M65: 35 | P65: Transferido
A66: 1 | B66: 45684 | C66: impressao preta | D66: 15 | E66: Aleatorio | F66: luiz | G66: 0.07 | H66: 1.05 | I66: 1 | J66: 15 | K66: cpf | L66: 1 | M66: 13.95 | P66: Transferido
A67: 1 | B67: 45684 | C67: ring light | D67: 1 | E67: Karol G | F67: Fisica | G67: 50 | H67: 50 | I67: 70 | J67: 70 | K67: cpf | L67: 0.93 | M67: 20 | N67: 70 | P67: Transferido
A68: 1 | B68: 45684 | C68: Cabeça carregador 3.1a ka-5601 | D68: 1 | E68: Karol G | F68: Fisica | G68: 6 | H68: 6 | I68: 15 | J68: 15 | K68: cpf | L68: 0.28571429 | M68: 9 | N68: 15 | P68: Transferido
A69: 1 | B69: 45684 | C69: impressao preta | D69: 15 | E69: Aleatorio | F69: Fisica | G69: 0.07 | H69: 1.05 | I69: 1 | J69: 15 | K69: cpf | L69: 0.93 | M69: 13.95 | P69: Transferido
A70: 1 | B70: 45684 | C70: Pendrive 16gb AL-U-16 | D70: 1 | E70: Aleatorio | F70: Fisica | G70: 13 | H70: 13 | I70: 30 | J70: 30 | K70: cpf | L70: 0.56666667 | M70: 17 | P70: Transferido
A71: 1 | B71: 45684 | C71: Serviço Aleatorio | D71: 1 | E71: Aleatorio | F71: Fisica | G71: 0 | H71: 0 | I71: 10 | J71: 10 | K71: cpf | L71: 1 | M71: 10 | P71: Transferido
A72: 1 | B72: 45684 | C72: Adaptador Wifi 2.5G | D72: 1 | E72: Aleatorio | F72: Fisica | G72: 11 | H72: 11 | I72: 30 | J72: 30 | K72: cpf | L72: 0.63333333 | M72: 19 | P72: Transferido
A73: 1 | B73: 45684 | C73: Computadores | D73: 1 | E73: Aleatorio | F73: Fisica | G73: 0 | H73: 0 | I73: 600 | J73: 600 | K73: cpf | L73: 1 | M73: 600 | P73: Transferido
A74: 1 | B74: 45685 | C74: chip com recarga | D74: 1 | E74: RELOGIO | F74: Fisica | G74: 18 | H74: 18 | I74: 25 | J74: 25 | K74: cpf | L74: 0.28 | M74: 7 | P74: Transferido
A75: 1 | B75: 45686 | C75: Fone de ouvido gamr q0008 | D75: 1 | E75: Tauan | F75: Fisica | G75: 20 | H75: 20 | I75: 60 | J75: 60 | K75: cpf | L75: 0.66666667 | M75: 40 | O75: 60 | P75: Aguardando
A76: 1 | B76: 45686 | C76: Formatação | D76: 1 | E76: Tauan | F76: Fisica | G76: 0 | H76: 0 | I76: 55 | J76: 55 | K76: cpf | L76: 1 | M76: 55 | O76: 55 | P76: Aguardando
A77: 1 | B77: 45686 | C77: Memoria | D77: 1 | E77: Tauan | F77: Fisica | G77: 0 | H77: 0 | I77: 50 | J77: 50 | K77: cpf | L77: 1 | M77: 50 | O77: 50 | P77: Aguardando
A78: 1 | B78: 45687 | C78: impressao preta | D78: 1 | E78: senhora feira | F78: Fisica | G78: 0.07 | H78: 0.07 | I78: 1 | J78: 1 | K78: cpf | L78: 0.93 | M78: 0.93 | P78: Transferido
A79: 1 | B79: 45687 | C79: Serviço Aleatorio | D79: 1 | E79: Cliente tabela | F79: Fisica | G79: 0 | H79: 0 | I79: 5 | J79: 5 | K79: cpf | L79: 0.68 | M79: 5 | P79: Transferido
A80: 1 | B80: 45687 | C80: fita dupla face | D80: 1 | E80: Karol G | F80: Fisica | G80: 5 | H80: 5 | I80: 10 | J80: 10 | K80: cpf | L80: 1 | M80: 5 | O80: 10 | P80: Transferido
A81: 1 | B81: 45688 | C81: impressao preta | D81: 1 | E81: loja senhor | F81: Fisica | G81: 0.07 | H81: 0.07 | I81: 1 | J81: 1 | K81: cpf | L81: 0.93 | M81: 0.93 | P81: Transferido
A82: 1 | B82: 45688 | C82: manutençao | D82: 1 | E82: Aleatorio | F82: Fisica | G82: 0 | H82: 0 | I82: 50 | J82: 50 | K82: cpf | L82: 1 | M82: 50 | P82: Transferido
A83: 1 | B83: 45688 | C83: Fone Fon30024 Inova | D83: 1 | E83: Aleatorio | F83: luiz | G83: 8 | H83: 8 | I83: 25 | J83: 25 | K83: cpf | L83: 0.5 | M83: 17 | P83: Transferido
A84: 1 | B84: 45688 | C84: luvinha de dedo | D84: 4 | E84: Aleatorio | F84: Fisica | G84: 0 | H84: 0 | I84: 5 | J84: 20 | K84: cpf | L84: 1 | M84: 20 | P84: Transferido
A85: 2 | B85: 45691 | C85: Cabo Kingo Tc 1M | D85: 1 | E85: Aleatorio | F85: Fisica | G85: 7 | H85: 7 | I85: 20 | J85: 20 | K85: cpf | L85: 0.65 | M85: 13 | P85: Transferido
A86: 2 | B86: 45691 | C86: Suporte Veicular Retrovisor B-Max | D86: 1 | E86: marcelo pai | F86: Fisica | G86: 11 | H86: 11 | I86: 30 | J86: 30 | K86: cpf | L86: 0.63333333 | M86: 19 | P86: Transferido
A87: 2 | B87: 45691 | C87: Fone Simples | D87: 1 | E87: Aleatorio | F87: Fisica | G87: 0 | H87: 0 | I87: 5 | J87: 5 | K87: cpf | L87: 1 | M87: 5 | P87: Transferido
A88: 2 | B88: 45691 | C88: Fonte notebook grasep | D88: 1 | E88: cliente viviane | F88: Fisica | G88: 30 | H88: 30 | I88: 70 | J88: 70 | K88: cpf | L88: 0.57142857 | M88: 40 | P88: Transferido
A89: 2 | B89: 45691 | C89: Serviço Aleatorio | D89: 1 | E89: cliente viviane | F89: luiz | G89: 0 | H89: 0 | I89: 50 | J89: 50 | K89: cpf | L89: 1 | M89: 50 | P89: Transferido
A90: 2 | B90: 45691 | C90: manutençao | D90: 1 | E90: Aleatorio | F90: luiz | G90: 0 | H90: 0 | I90: 45 | J90: 45 | K90: cpf | L90: 1 | M90: 45 | P90: Transferido
A91: 2 | B91: 45691 | C91: SSD 220gb | D91: 1 | E91: cliente viviane | F91: Fisica | G91: 0 | H91: 0 | I91: 250 | J91: 250 | K91: cpf | L91: 1 | M91: 250 | P91: Transferido
A92: 2 | B92: 45692 | C92: Fonte notebook grasep | D92: 1 | E92: Aleatorio | F92: Fisica | G92: 38 | H92: 38 | I92: 68 | J92: 68 | K92: cpf | L92: 0.44117647 | M92: 30 | P92: Transferido
A93: 2 | B93: 45692 | C93: Computadores | D93: 1 | E93: Senhor relogio | F93: Fisica | G93: 0 | H93: 0 | I93: 140 | J93: 140 | K93: cpf | L93: 1 | M93: 140 | P93: Transferido
A94: 2 | B94: 45692 | C94: chip recarregado | D94: 1 | E94: Karol G | F94: Fisica | G94: 18.5 | H94: 18.5 | I94: 30 | J94: 30 | K94: cpf | L94: 0.38333333 | M94: 11.5 | O94: 30 | P94: Ainda não
A95: 2 | B95: 45693 | C95: chip recarregado | D95: 1 | E95: Aleatorio | F95: Fisica | G95: 18.5 | H95: 18.5 | I95: 30 | J95: 30 | K95: cpf | L95: 0.38333333 | M95: 11.5 | P95: Transferido
A96: 2 | B96: 45693 | C96: Fone m10 | D96: 1 | E96: Aleatorio | F96: Fisica | G96: 18 | H96: 18 | I96: 20 | J96: 20 | K96: cpf | L96: 0.1 | M96: 2 | P96: Transferido
A97: 2 | B97: 45693 | C97: Fone Pmcell Fo-11 | D97: 1 | E97: Aleatorio | F97: Fisica | G97: 3.5 | H97: 3.5 | I97: 45 | J97: 45 | K97: cpf | L97: 0.92222222 | M97: 41.5 | P97: Transferido
A98: 2 | B98: 45694 | C98: capinha | D98: 3 | E98: marcellin | F98: Fisica | G98: 6 | H98: 18 | I98: 15 | J98: 45 | K98: cpf | L98: 0.6 | M98: 27 | P98: Transferido
A99: 2 | B99: 45694 | C99: Cabo Kingo Iphone 1M | D99: 1 | E99: marcellin | F99: Fisica | G99: 7 | H99: 7 | I99: 15 | J99: 15 | K99: cpf | L99: 0.53333333 | M99: 8 | P99: Transferido
A100: 2 | B100: 45694 | C100: Fonte pc 200w | D100: 1 | E100: Aleatorio | F100: Fisica | G100: 60 | H100: 60 | I100: 110 | J100: 110 | K100: cpf | L100: 0.45454545 | M100: 50 | P100: Transferido
...

Sheet Vendas 2026
A1: Mês | B1: Data | C1: Produto | D1: QT | E1: Cliente | F1: Vendedor | G1: Custo Un | H1: Valor gasto | I1: Valor uni venda | J1: entrada | K1: Valor da venda | L1: Lucro | M1: Coluna2 | N1: Recebido loja | O1: Coluna1 | S1: valor anuncio | T1: valor desocnto | U1: valor recebido | V1: Valor da taxa | W1: valor a pagar | X1: lucro
A2: =IF(Table_246[[#This Row],[Data]]="","",MONTH(Table_246[[#This Row],[Data]])) -> 1 | B2: 46024 | C2: Carregador Completo Iphone 20W | D2: 1 | E2: elza | F2: Fisica | G2: 12 | H2: =Table_246[[#This Row],[QT]]*Table_246[[#This Row],[Custo Un]] -> 12 | I2: 30 | J2: =I2*D2 -> 30 | K2: =I2*D2 -> 30 | L2: =Table_246[[#This Row],[Valor da venda]]-Table_246[[#This Row],[Valor gasto]] -> 18 | M2: =IFERROR(L2/K2, 0) -> 0.6 | N2: Transferido | O2: =IF([1]!Table_246[[#This Row],[Coluna2]]>0.5, "🔥 Excelente", IF([1]!Table_246[[#This Row],[Coluna2]]>0.4, "👍 Bom", "⚠️ Baixo")) -> 🔥 Excelente | R2: 600 | S2: 725 | T2: 0.25 | U2: =S2-(S2*T2)-4 -> 539.75 | V2: =S2*25% -> 181.25 | W2: 490 | X2: =U2-W2 -> 49.75
A3: =IF(Table_246[[#This Row],[Data]]="","",MONTH(Table_246[[#This Row],[Data]])) -> 1 | B3: 46027 | C3: Pelicula 3D | D3: 1 | E3: vall | F3: Fisica | G3: =IFERROR(VLOOKUP(C3,PROD!$A$2:$E$1204,5,0),"0") -> 3 | H3: =Table_246[[#This Row],[QT]]*Table_246[[#This Row],[Custo Un]] -> 3 | I3: 15 | J3: =I3*D3 -> 15 | K3: =I3*D3 -> 15 | L3: =Table_246[[#This Row],[Valor da venda]]-Table_246[[#This Row],[Valor gasto]] -> 12 | M3: =IFERROR(L3/K3, 0) -> 0.8 | N3: Transferido | O3: =IF([1]!Table_246[[#This Row],[Coluna2]]>0.5, "🔥 Excelente", IF([1]!Table_246[[#This Row],[Coluna2]]>0.4, "👍 Bom", "⚠️ Baixo")) -> 🔥 Excelente | R3: 800 | S3: 830 | T3: 0.25 | U3: =S3-(S3*T3)-4 -> 618.5 | V3: =S3*25% -> 207.5 | W3: 550 | X3: =U3-W3 -> 68.5
A4: =IF(Table_246[[#This Row],[Data]]="","",MONTH(Table_246[[#This Row],[Data]])) -> 1 | B4: 46027 | C4: Cheirinho | D4: 2 | E4: 26010470HA378U | F4: Shopee | G4: 7.5 | H4: =Table_246[[#This Row],[QT]]*Table_246[[#This Row],[Custo Un]] -> 15 | I4: 28.1 | J4: =I4*D4 -> 56.2 | K4: =I4*D4 -> 56.2 | L4: =Table_246[[#This Row],[Valor da venda]]-Table_246[[#This Row],[Valor gasto]] -> 41.2 | M4: =IFERROR(L4/K4, 0) -> 0.73309609 | N4: Transferido | O4: =IF([1]!Table_246[[#This Row],[Coluna2]]>0.5, "🔥 Excelente", IF([1]!Table_246[[#This Row],[Coluna2]]>0.4, "👍 Bom", "⚠️ Baixo")) -> 🔥 Excelente | R4: 900 | S4: 800 | T4: 0.25 | U4: =S4-(S4*T4)-4 -> 596 | V4: =S4*25% -> 200 | W4: 510 | X4: =U4-W4 -> 86
A5: =IF(Table_246[[#This Row],[Data]]="","",MONTH(Table_246[[#This Row],[Data]])) -> 1 | B5: 46027 | C5: Nterruptor De Controle Remoto | D5: 1 | E5: 2601057PDHKMGS | F5: Shopee | G5: 15 | H5: =Table_246[[#This Row],[QT]]*Table_246[[#This Row],[Custo Un]] -> 15 | I5: 41.6 | J5: =I5*D5 -> 41.6 | K5: =I5*D5 -> 41.6 | L5: =Table_246[[#This Row],[Valor da venda]]-Table_246[[#This Row],[Valor gasto]] -> 26.6 | M5: =IFERROR(L5/K5, 0) -> 0.63942308 | N5: Transferido | O5: =IF([1]!Table_246[[#This Row],[Coluna2]]>0.5, "🔥 Excelente", IF([1]!Table_246[[#This Row],[Coluna2]]>0.4, "👍 Bom", "⚠️ Baixo")) -> 🔥 Excelente | R5: 1000 | S5: 1000 | T5: 0.25 | U5: =S5-(S5*T5)-4 -> 746 | V5: =S5*25% -> 250 | W5: 700 | X5: =U5-W5 -> 46
A6: =IF(Table_246[[#This Row],[Data]]="","",MONTH(Table_246[[#This Row],[Data]])) -> 1 | B6: 46027 | C6: Desentupidor | D6: 1 | E6: 26010322KX6CM7 | F6: Shopee | G6: 12 | H6: =Table_246[[#This Row],[QT]]*Table_246[[#This Row],[Custo Un]] -> 12 | I6: 14.99 | J6: =I6*D6 -> 14.99 | K6: =I6*D6 -> 14.99 | L6: =Table_246[[#This Row],[Valor da venda]]-Table_246[[#This Row],[Valor gasto]] -> 2.99 | M6: =IFERROR(L6/K6, 0) -> 0.19946631 | N6: Transferido | O6: =IF([1]!Table_246[[#This Row],[Coluna2]]>0.5, "🔥 Excelente", IF([1]!Table_246[[#This Row],[Coluna2]]>0.4, "👍 Bom", "⚠️ Baixo")) -> ⚠️ Baixo | S6: 36 | T6: 0.25 | U6: =S6-(S6*T6)-4 -> 23 | V6: =S6*25% -> 9 | X6: =U6-W6 -> 23
A7: =IF(Table_246[[#This Row],[Data]]="","",MONTH(Table_246[[#This Row],[Data]])) -> 1 | B7: 46027 | C7: Desentupidor | D7: 1 | E7: 26010321EYMMGF | F7: Shopee | G7: 12 | H7: =Table_246[[#This Row],[QT]]*Table_246[[#This Row],[Custo Un]] -> 12 | I7: 14.99 | J7: =I7*D7 -> 14.99 | K7: =I7*D7 -> 14.99 | L7: =Table_246[[#This Row],[Valor da venda]]-Table_246[[#This Row],[Valor gasto]] -> 2.99 | M7: =IFERROR(L7/K7, 0) -> 0.19946631 | N7: Transferido | O7: =IF([1]!Table_246[[#This Row],[Coluna2]]>0.5, "🔥 Excelente", IF([1]!Table_246[[#This Row],[Coluna2]]>0.4, "👍 Bom", "⚠️ Baixo")) -> ⚠️ Baixo | R7: 520 | S7: 520 | T7: 0.23 | U7: =S7-(S7*T7)-4 -> 396.4 | V7: =S7*25% -> 130 | W7: 350 | X7: =U7-W7 -> 46.4
A8: =IF(Table_246[[#This Row],[Data]]="","",MONTH(Table_246[[#This Row],[Data]])) -> 1 | B8: 46027 | C8: Case 2.5 Hd | D8: 1 | E8: 26010330Y0QYCC | F8: Shopee | G8: 19 | H8: =Table_246[[#This Row],[QT]]*Table_246[[#This Row],[Custo Un]] -> 19 | I8: 34.75 | J8: =I8*D8 -> 34.75 | K8: =I8*D8 -> 34.75 | L8: =Table_246[[#This Row],[Valor da venda]]-Table_246[[#This Row],[Valor gasto]] -> 15.75 | M8: =IFERROR(L8/K8, 0) -> 0.45323741 | N8: Transferido | O8: =IF([1]!Table_246[[#This Row],[Coluna2]]>0.5, "🔥 Excelente", IF([1]!Table_246[[#This Row],[Coluna2]]>0.4, "👍 Bom", "⚠️ Baixo")) -> 👍 Bom | S8: 820 | T8: 0.21 | U8: =S8-(S8*T8)-4 -> 643.8 | V8: =S8*25% -> 205 | W8: 550 | X8: =U8-W8 -> 93.8
A9: =IF(Table_246[[#This Row],[Data]]="","",MONTH(Table_246[[#This Row],[Data]])) -> 1 | B9: 46027 | C9: Pelicula 3D | D9: 1 | E9: vall | F9: Fisica | G9: 6 | H9: =Table_246[[#This Row],[QT]]*Table_246[[#This Row],[Custo Un]] -> 6 | I9: 15 | J9: =I9*D9 -> 15 | K9: =I9*D9 -> 15 | L9: =Table_246[[#This Row],[Valor da venda]]-Table_246[[#This Row],[Valor gasto]] -> 9 | M9: =IFERROR(L9/K9, 0) -> 0.6 | N9: Transferido | O9: =IF([1]!Table_246[[#This Row],[Coluna2]]>0.5, "🔥 Excelente", IF([1]!Table_246[[#This Row],[Coluna2]]>0.4, "👍 Bom", "⚠️ Baixo")) -> 🔥 Excelente | R9: usina | S9: 800 | T9: 0.23 | U9: =S9-(S9*T9)-4 -> 612 | V9: =S9*25% -> 200 | W9: 570 | X9: =U9-W9 -> 42
A10: =IF(Table_246[[#This Row],[Data]]="","",MONTH(Table_246[[#This Row],[Data]])) -> 1 | B10: 46028 | C10: Pelicula 3D | D10: 1 | E10: boneca | F10: Fisica | G10: =IFERROR(VLOOKUP(C10,PROD!$A$2:$E$1204,5,0),"0") -> 3 | H10: =Table_246[[#This Row],[QT]]*Table_246[[#This Row],[Custo Un]] -> 3 | I10: 15 | J10: =I10*D10 -> 15 | K10: =I10*D10 -> 15 | L10: =Table_246[[#This Row],[Valor da venda]]-Table_246[[#This Row],[Valor gasto]] -> 12 | M10: =IFERROR(L10/K10, 0) -> 0.8 | N10: Transferido | O10: =IF([1]!Table_246[[#This Row],[Coluna2]]>0.5, "🔥 Excelente", IF([1]!Table_246[[#This Row],[Coluna2]]>0.4, "👍 Bom", "⚠️ Baixo")) -> 🔥 Excelente | S10: 10 | T10: 0.23 | U10: =S10-(S10*T10)-4 -> 3.7 | V10: =S10*25% -> 2.5 | X10: =U10-W10 -> 3.7
A11: =IF(Table_246[[#This Row],[Data]]="","",MONTH(Table_246[[#This Row],[Data]])) -> 1 | B11: 46028 | C11: Restauraçao Dados | D11: 1 | E11: Eliane | F11: Fisica | G11: =IFERROR(VLOOKUP(C11,PROD!$A$2:$E$1204,5,0),"0") -> 0 | H11: =Table_246[[#This Row],[QT]]*Table_246[[#This Row],[Custo Un]] -> 0 | I11: 100 | J11: =I11*D11 -> 100 | K11: =I11*D11 -> 100 | L11: =Table_246[[#This Row],[Valor da venda]]-Table_246[[#This Row],[Valor gasto]] -> 100 | M11: =IFERROR(L11/K11, 0) -> 1 | N11: Transferido | O11: =IF([1]!Table_246[[#This Row],[Coluna2]]>0.5, "🔥 Excelente", IF([1]!Table_246[[#This Row],[Coluna2]]>0.4, "👍 Bom", "⚠️ Baixo")) -> 🔥 Excelente | S11: 12 | T11: 0.23 | U11: =S11-(S11*T11)-4 -> 5.24 | V11: =S11*25% -> 3 | X11: =U11-W11 -> 5.24
A12: =IF(Table_246[[#This Row],[Data]]="","",MONTH(Table_246[[#This Row],[Data]])) -> 1 | B12: 46029 | C12: Gravação De Musica | D12: 1 | E12: aleatorio | F12: Fisica | G12: =IFERROR(VLOOKUP(C12,PROD!$A$2:$E$1204,5,0),"0") -> 0 | H12: =Table_246[[#This Row],[QT]]*Table_246[[#This Row],[Custo Un]] -> 0 | I12: 15 | J12: =I12*D12 -> 15 | K12: =I12*D12 -> 15 | L12: =Table_246[[#This Row],[Valor da venda]]-Table_246[[#This Row],[Valor gasto]] -> 15 | M12: =IFERROR(L12/K12, 0) -> 1 | N12: Transferido | O12: =IF([1]!Table_246[[#This Row],[Coluna2]]>0.5, "🔥 Excelente", IF([1]!Table_246[[#This Row],[Coluna2]]>0.4, "👍 Bom", "⚠️ Baixo")) -> 🔥 Excelente | S12: 20 | T12: 0.23 | U12: =S12-(S12*T12)-4 -> 11.4 | V12: =S12*25% -> 5 | X12: =U12-W12 -> 11.4
A13: =IF(Table_246[[#This Row],[Data]]="","",MONTH(Table_246[[#This Row],[Data]])) -> 1 | B13: 46029 | C13: Boneco Lego Kit | D13: 1 | E13: aleatorio | F13: Fisica | G13: 11 | H13: =Table_246[[#This Row],[QT]]*Table_246[[#This Row],[Custo Un]] -> 11 | I13: 20 | J13: =I13*D13 -> 20 | K13: =I13*D13 -> 20 | L13: =Table_246[[#This Row],[Valor da venda]]-Table_246[[#This Row],[Valor gasto]] -> 9 | M13: =IFERROR(L13/K13, 0) -> 0.45 | N13: Transferido | O13: =IF([1]!Table_246[[#This Row],[Coluna2]]>0.5, "🔥 Excelente", IF([1]!Table_246[[#This Row],[Coluna2]]>0.4, "👍 Bom", "⚠️ Baixo")) -> 👍 Bom | T13: 0.23 | U13: =S13-(S13*T13)-4 -> -4 | V13: =S13*25% -> 0 | X13: =U13-W13 -> -4
A14: =IF(Table_246[[#This Row],[Data]]="","",MONTH(Table_246[[#This Row],[Data]])) -> 1 | B14: 46034 | C14: Impressao Preta | D14: 1 | E14: sonia | F14: Fisica | G14: =IFERROR(VLOOKUP(C14,PROD!$A$2:$E$1204,5,0),"0") -> 0.07 | H14: =Table_246[[#This Row],[QT]]*Table_246[[#This Row],[Custo Un]] -> 0.07 | I14: 1 | J14: =I14*D14 -> 1 | K14: =I14*D14 -> 1 | L14: =Table_246[[#This Row],[Valor da venda]]-Table_246[[#This Row],[Valor gasto]] -> 0.93 | M14: =IFERROR(L14/K14, 0) -> 0.93 | N14: Transferido | O14: =IF([1]!Table_246[[#This Row],[Coluna2]]>0.5, "🔥 Excelente", IF([1]!Table_246[[#This Row],[Coluna2]]>0.4, "👍 Bom", "⚠️ Baixo")) -> 🔥 Excelente | T14: 0.23 | U14: =S14-(S14*T14)-4 -> -4 | V14: =S14*25% -> 0 | X14: =U14-W14 -> -4
A15: =IF(Table_246[[#This Row],[Data]]="","",MONTH(Table_246[[#This Row],[Data]])) -> 1 | B15: 46034 | C15: Durex | D15: 1 | E15: cacheados | F15: Fisica | G15: =IFERROR(VLOOKUP(C15,PROD!$A$2:$E$1204,5,0),"0") -> 2.5 | H15: =Table_246[[#This Row],[QT]]*Table_246[[#This Row],[Custo Un]] -> 2.5 | I15: 7 | J15: =I15*D15 -> 7 | K15: =I15*D15 -> 7 | L15: =Table_246[[#This Row],[Valor da venda]]-Table_246[[#This Row],[Valor gasto]] -> 4.5 | M15: =IFERROR(L15/K15, 0) -> 0.64285714 | N15: Transferido | O15: =IF([1]!Table_246[[#This Row],[Coluna2]]>0.5, "🔥 Excelente", IF([1]!Table_246[[#This Row],[Coluna2]]>0.4, "👍 Bom", "⚠️ Baixo")) -> 🔥 Excelente
A16: =IF(Table_246[[#This Row],[Data]]="","",MONTH(Table_246[[#This Row],[Data]])) -> 1 | B16: 46034 | C16: Moeba | D16: 1 | E16: samuel | F16: Fisica | G16: 5 | H16: =Table_246[[#This Row],[QT]]*Table_246[[#This Row],[Custo Un]] -> 5 | I16: 10 | J16: =I16*D16 -> 10 | K16: =I16*D16 -> 10 | L16: =Table_246[[#This Row],[Valor da venda]]-Table_246[[#This Row],[Valor gasto]] -> 5 | M16: =IFERROR(L16/K16, 0) -> 0.5 | N16: Transferido | O16: =IF([1]!Table_246[[#This Row],[Coluna2]]>0.5, "🔥 Excelente", IF([1]!Table_246[[#This Row],[Coluna2]]>0.4, "👍 Bom", "⚠️ Baixo")) -> 👍 Bom
A17: =IF(Table_246[[#This Row],[Data]]="","",MONTH(Table_246[[#This Row],[Data]])) -> 1 | B17: 46034 | C17: Impressao Preta | D17: 4 | E17: aleatorio | F17: Fisica | G17: =IFERROR(VLOOKUP(C17,PROD!$A$2:$E$1204,5,0),"0") -> 0.07 | H17: =Table_246[[#This Row],[QT]]*Table_246[[#This Row],[Custo Un]] -> 0.28 | I17: 1 | J17: =I17*D17 -> 4 | K17: =I17*D17 -> 4 | L17: =Table_246[[#This Row],[Valor da venda]]-Table_246[[#This Row],[Valor gasto]] -> 3.72 | M17: =IFERROR(L17/K17, 0) -> 0.93 | N17: Transferido | O17: =IF([1]!Table_246[[#This Row],[Coluna2]]>0.5, "🔥 Excelente", IF([1]!Table_246[[#This Row],[Coluna2]]>0.4, "👍 Bom", "⚠️ Baixo")) -> 🔥 Excelente
A18: =IF(Table_246[[#This Row],[Data]]="","",MONTH(Table_246[[#This Row],[Data]])) -> 1 | B18: 46034 | C18: Cheirinho Para Carro | D18: 2 | E18: 260113UN53PDB3 | F18: Shopee | G18: 7.5 | H18: =Table_246[[#This Row],[QT]]*Table_246[[#This Row],[Custo Un]] -> 15 | I18: 14.05 | J18: =I18*D18 -> 28.1 | K18: =I18*D18 -> 28.1 | L18: =Table_246[[#This Row],[Valor da venda]]-Table_246[[#This Row],[Valor gasto]] -> 13.1 | M18: =IFERROR(L18/K18, 0) -> 0.46619217 | N18: Transferido | O18: =IF([1]!Table_246[[#This Row],[Coluna2]]>0.5, "🔥 Excelente", IF([1]!Table_246[[#This Row],[Coluna2]]>0.4, "👍 Bom", "⚠️ Baixo")) -> 👍 Bom
A19: =IF(Table_246[[#This Row],[Data]]="","",MONTH(Table_246[[#This Row],[Data]])) -> 1 | B19: 46034 | C19: Pen Drive Com 10 Jogos Para Ps2 | D19: 1 | E19: 1732942733137053663 | F19: Tiktok | G19: =IFERROR(VLOOKUP(C19,PROD!$A$2:$E$1204,5,0),"0") -> 0 | H19: =Table_246[[#This Row],[QT]]*Table_246[[#This Row],[Custo Un]] -> 0 | I19: 100.32 | J19: =I19*D19 -> 100.32 | K19: =I19*D19 -> 100.32 | L19: =Table_246[[#This Row],[Valor da venda]]-Table_246[[#This Row],[Valor gasto]] -> 100.32 | M19: =IFERROR(L19/K19, 0) -> 1 | N19: Transferido | O19: =IF([1]!Table_246[[#This Row],[Coluna2]]>0.5, "🔥 Excelente", IF([1]!Table_246[[#This Row],[Coluna2]]>0.4, "👍 Bom", "⚠️ Baixo")) -> 🔥 Excelente
A20: =IF(Table_246[[#This Row],[Data]]="","",MONTH(Table_246[[#This Row],[Data]])) -> 1 | B20: 46035 | C20: Impressao Preta | D20: 1 | E20: samuel | F20: Fisica | G20: =IFERROR(VLOOKUP(C20,PROD!$A$2:$E$1204,5,0),"0") -> 0.07 | H20: =Table_246[[#This Row],[QT]]*Table_246[[#This Row],[Custo Un]] -> 0.07 | I20: 1 | J20: =I20*D20 -> 1 | K20: =I20*D20 -> 1 | L20: =Table_246[[#This Row],[Valor da venda]]-Table_246[[#This Row],[Valor gasto]] -> 0.93 | M20: =IFERROR(L20/K20, 0) -> 0.93 | N20: Transferido | O20: =IF([1]!Table_246[[#This Row],[Coluna2]]>0.5, "🔥 Excelente", IF([1]!Table_246[[#This Row],[Coluna2]]>0.4, "👍 Bom", "⚠️ Baixo")) -> 🔥 Excelente
A21: =IF(Table_246[[#This Row],[Data]]="","",MONTH(Table_246[[#This Row],[Data]])) -> 1 | B21: 46035 | C21: Impressao Preta | D21: 4 | E21: eliane | F21: Fisica | G21: =IFERROR(VLOOKUP(C21,PROD!$A$2:$E$1204,5,0),"0") -> 0.07 | H21: =Table_246[[#This Row],[QT]]*Table_246[[#This Row],[Custo Un]] -> 0.28 | I21: 1 | J21: =I21*D21 -> 4 | K21: =I21*D21 -> 4 | L21: =Table_246[[#This Row],[Valor da venda]]-Table_246[[#This Row],[Valor gasto]] -> 3.72 | M21: =IFERROR(L21/K21, 0) -> 0.93 | N21: Transferido | O21: =IF([1]!Table_246[[#This Row],[Coluna2]]>0.5, "🔥 Excelente", IF([1]!Table_246[[#This Row],[Coluna2]]>0.4, "👍 Bom", "⚠️ Baixo")) -> 🔥 Excelente
A22: =IF(Table_246[[#This Row],[Data]]="","",MONTH(Table_246[[#This Row],[Data]])) -> 1 | B22: 46036 | C22: Protetor Documento | D22: 1 | E22: 26011533GTJVCC | F22: Shopee | G22: 3 | H22: =Table_246[[#This Row],[QT]]*Table_246[[#This Row],[Custo Un]] -> 3 | I22: 4.54 | J22: =I22*D22 -> 4.54 | K22: =I22*D22 -> 4.54 | L22: =Table_246[[#This Row],[Valor da venda]]-Table_246[[#This Row],[Valor gasto]] -> 1.54 | M22: =IFERROR(L22/K22, 0) -> 0.33920705 | N22: Transferido | O22: =IF([1]!Table_246[[#This Row],[Coluna2]]>0.5, "🔥 Excelente", IF([1]!Table_246[[#This Row],[Coluna2]]>0.4, "👍 Bom", "⚠️ Baixo")) -> ⚠️ Baixo
A23: =IF(Table_246[[#This Row],[Data]]="","",MONTH(Table_246[[#This Row],[Data]])) -> 1 | B23: 46036 | C23: Kit Maçarico | D23: 1 | E23: 260115363HXRNS | F23: Shopee | G23: 25 | H23: =Table_246[[#This Row],[QT]]*Table_246[[#This Row],[Custo Un]] -> 25 | I23: 52.99 | J23: =I23*D23 -> 52.99 | K23: =I23*D23 -> 52.99 | L23: =Table_246[[#This Row],[Valor da venda]]-Table_246[[#This Row],[Valor gasto]] -> 27.99 | M23: =IFERROR(L23/K23, 0) -> 0.52821287 | N23: Transferido | O23: =IF([1]!Table_246[[#This Row],[Coluna2]]>0.5, "🔥 Excelente", IF([1]!Table_246[[#This Row],[Coluna2]]>0.4, "👍 Bom", "⚠️ Baixo")) -> 🔥 Excelente
A24: =IF(Table_246[[#This Row],[Data]]="","",MONTH(Table_246[[#This Row],[Data]])) -> 1 | B24: 46037 | C24: Pelicula 3D | D24: 1 | E24: aleatorio | F24: Fisica | G24: =IFERROR(VLOOKUP(C24,PROD!$A$2:$E$1204,5,0),"0") -> 3 | H24: =Table_246[[#This Row],[QT]]*Table_246[[#This Row],[Custo Un]] -> 3 | I24: 10 | J24: =I24*D24 -> 10 | K24: =I24*D24 -> 10 | L24: =Table_246[[#This Row],[Valor da venda]]-Table_246[[#This Row],[Valor gasto]] -> 7 | M24: =IFERROR(L24/K24, 0) -> 0.7 | N24: Transferido | O24: =IF([1]!Table_246[[#This Row],[Coluna2]]>0.5, "🔥 Excelente", IF([1]!Table_246[[#This Row],[Coluna2]]>0.4, "👍 Bom", "⚠️ Baixo")) -> 🔥 Excelente
A25: =IF(Table_246[[#This Row],[Data]]="","",MONTH(Table_246[[#This Row],[Data]])) -> 1 | B25: 46037 | C25: Lixa De Unha | D25: 2 | E25: aleatorio | F25: Fisica | G25: =IFERROR(VLOOKUP(C25,PROD!$A$2:$E$1204,5,0),"0") -> 0 | H25: =Table_246[[#This Row],[QT]]*Table_246[[#This Row],[Custo Un]] -> 0 | I25: 0.5 | J25: =I25*D25 -> 1 | K25: =I25*D25 -> 1 | L25: =Table_246[[#This Row],[Valor da venda]]-Table_246[[#This Row],[Valor gasto]] -> 1 | M25: =IFERROR(L25/K25, 0) -> 1 | N25: Transferido | O25: =IF([1]!Table_246[[#This Row],[Coluna2]]>0.5, "🔥 Excelente", IF([1]!Table_246[[#This Row],[Coluna2]]>0.4, "👍 Bom", "⚠️ Baixo")) -> 🔥 Excelente
A26: =IF(Table_246[[#This Row],[Data]]="","",MONTH(Table_246[[#This Row],[Data]])) -> 1 | B26: 46037 | C26: Pelicula 3D | D26: 1 | E26: aleatorio | F26: Fisica | G26: =IFERROR(VLOOKUP(C26,PROD!$A$2:$E$1204,5,0),"0") -> 3 | H26: =Table_246[[#This Row],[QT]]*Table_246[[#This Row],[Custo Un]] -> 3 | I26: 10 | J26: =I26*D26 -> 10 | K26: =I26*D26 -> 10 | L26: =Table_246[[#This Row],[Valor da venda]]-Table_246[[#This Row],[Valor gasto]] -> 7 | M26: =IFERROR(L26/K26, 0) -> 0.7 | N26: Transferido | O26: =IF([1]!Table_246[[#This Row],[Coluna2]]>0.5, "🔥 Excelente", IF([1]!Table_246[[#This Row],[Coluna2]]>0.4, "👍 Bom", "⚠️ Baixo")) -> 🔥 Excelente
A27: =IF(Table_246[[#This Row],[Data]]="","",MONTH(Table_246[[#This Row],[Data]])) -> 1 | B27: 46038 | C27: Chip Sem Recarga | D27: 1 | E27: aleatorio | F27: Fisica | G27: 11 | H27: =Table_246[[#This Row],[QT]]*Table_246[[#This Row],[Custo Un]] -> 11 | I27: 20 | J27: =I27*D27 -> 20 | K27: =I27*D27 -> 20 | L27: =Table_246[[#This Row],[Valor da venda]]-Table_246[[#This Row],[Valor gasto]] -> 9 | M27: =IFERROR(L27/K27, 0) -> 0.45 | N27: Transferido | O27: =IF([1]!Table_246[[#This Row],[Coluna2]]>0.5, "🔥 Excelente", IF([1]!Table_246[[#This Row],[Coluna2]]>0.4, "👍 Bom", "⚠️ Baixo")) -> 👍 Bom
A28: =IF(Table_246[[#This Row],[Data]]="","",MONTH(Table_246[[#This Row],[Data]])) -> 1 | B28: 46038 | C28: Brinquedo Arminha | D28: 1 | E28: daniel | F28: Fisica | G28: 12 | H28: =Table_246[[#This Row],[QT]]*Table_246[[#This Row],[Custo Un]] -> 12 | I28: 25 | J28: =I28*D28 -> 25 | K28: =I28*D28 -> 25 | L28: =Table_246[[#This Row],[Valor da venda]]-Table_246[[#This Row],[Valor gasto]] -> 13 | M28: =IFERROR(L28/K28, 0) -> 0.52 | N28: Transferido | O28: =IF([1]!Table_246[[#This Row],[Coluna2]]>0.5, "🔥 Excelente", IF([1]!Table_246[[#This Row],[Coluna2]]>0.4, "👍 Bom", "⚠️ Baixo")) -> 🔥 Excelente
A29: =IF(Table_246[[#This Row],[Data]]="","",MONTH(Table_246[[#This Row],[Data]])) -> 1 | B29: 46041 | C29: Impressao Preta | D29: 2 | E29: aleatorio | F29: Fisica | G29: =IFERROR(VLOOKUP(C29,PROD!$A$2:$E$1204,5,0),"0") -> 0.07 | H29: =Table_246[[#This Row],[QT]]*Table_246[[#This Row],[Custo Un]] -> 0.14 | I29: 1 | J29: =I29*D29 -> 2 | K29: =I29*D29 -> 2 | L29: =Table_246[[#This Row],[Valor da venda]]-Table_246[[#This Row],[Valor gasto]] -> 1.86 | M29: =IFERROR(L29/K29, 0) -> 0.93 | N29: Transferido | O29: =IF([1]!Table_246[[#This Row],[Coluna2]]>0.5, "🔥 Excelente", IF([1]!Table_246[[#This Row],[Coluna2]]>0.4, "👍 Bom", "⚠️ Baixo")) -> 🔥 Excelente
A30: =IF(Table_246[[#This Row],[Data]]="","",MONTH(Table_246[[#This Row],[Data]])) -> 1 | B30: 46041 | C30: Caixa De Som Pc | D30: 1 | E30: aleatorio | F30: Fisica | G30: 15 | H30: =Table_246[[#This Row],[QT]]*Table_246[[#This Row],[Custo Un]] -> 15 | I30: 25 | J30: =I30*D30 -> 25 | K30: =I30*D30 -> 25 | L30: =Table_246[[#This Row],[Valor da venda]]-Table_246[[#This Row],[Valor gasto]] -> 10 | M30: =IFERROR(L30/K30, 0) -> 0.4 | N30: Transferido | O30: =IF([1]!Table_246[[#This Row],[Coluna2]]>0.5, "🔥 Excelente", IF([1]!Table_246[[#This Row],[Coluna2]]>0.4, "👍 Bom", "⚠️ Baixo")) -> ⚠️ Baixo
A31: =IF(Table_246[[#This Row],[Data]]="","",MONTH(Table_246[[#This Row],[Data]])) -> 1 | B31: 46041 | C31: Bolinha De Gel | D31: 1 | E31: aleatorio | F31: Fisica | G31: 2.5 | H31: =Table_246[[#This Row],[QT]]*Table_246[[#This Row],[Custo Un]] -> 2.5 | I31: 5 | J31: =I31*D31 -> 5 | K31: =I31*D31 -> 5 | L31: =Table_246[[#This Row],[Valor da venda]]-Table_246[[#This Row],[Valor gasto]] -> 2.5 | M31: =IFERROR(L31/K31, 0) -> 0.5 | N31: Transferido | O31: =IF([1]!Table_246[[#This Row],[Coluna2]]>0.5, "🔥 Excelente", IF([1]!Table_246[[#This Row],[Coluna2]]>0.4, "👍 Bom", "⚠️ Baixo")) -> 👍 Bom
A32: =IF(Table_246[[#This Row],[Data]]="","",MONTH(Table_246[[#This Row],[Data]])) -> 1 | B32: 46041 | C32: Serviço Aleatorio | D32: 1 | E32: aleatorio | F32: Fisica | G32: =IFERROR(VLOOKUP(C32,PROD!$A$2:$E$1204,5,0),"0") -> 0 | H32: =Table_246[[#This Row],[QT]]*Table_246[[#This Row],[Custo Un]] -> 0 | I32: 30 | J32: =I32*D32 -> 30 | K32: =I32*D32 -> 30 | L32: =Table_246[[#This Row],[Valor da venda]]-Table_246[[#This Row],[Valor gasto]] -> 30 | M32: =IFERROR(L32/K32, 0) -> 1 | N32: Transferido | O32: =IF([1]!Table_246[[#This Row],[Coluna2]]>0.5, "🔥 Excelente", IF([1]!Table_246[[#This Row],[Coluna2]]>0.4, "👍 Bom", "⚠️ Baixo")) -> 🔥 Excelente
A33: =IF(Table_246[[#This Row],[Data]]="","",MONTH(Table_246[[#This Row],[Data]])) -> 1 | B33: 46039 | C33: Impressao Preta | D33: 8 | E33: aleatorio | F33: Fisica | G33: =IFERROR(VLOOKUP(C33,PROD!$A$2:$E$1204,5,0),"0") -> 0.07 | H33: =Table_246[[#This Row],[QT]]*Table_246[[#This Row],[Custo Un]] -> 0.56 | I33: 1 | J33: =I33*D33 -> 8 | K33: =I33*D33 -> 8 | L33: =Table_246[[#This Row],[Valor da venda]]-Table_246[[#This Row],[Valor gasto]] -> 7.44 | M33: =IFERROR(L33/K33, 0) -> 0.93 | N33: Transferido | O33: =IF([1]!Table_246[[#This Row],[Coluna2]]>0.5, "🔥 Excelente", IF([1]!Table_246[[#This Row],[Coluna2]]>0.4, "👍 Bom", "⚠️ Baixo")) -> 🔥 Excelente
A34: =IF(Table_246[[#This Row],[Data]]="","",MONTH(Table_246[[#This Row],[Data]])) -> 1 | B34: 46041 | C34: Bleybleyd | D34: 1 | E34: aleatorio | F34: Fisica | G34: 25 | H34: =Table_246[[#This Row],[QT]]*Table_246[[#This Row],[Custo Un]] -> 25 | I34: 50 | J34: =I34*D34 -> 50 | K34: =I34*D34 -> 50 | L34: =Table_246[[#This Row],[Valor da venda]]-Table_246[[#This Row],[Valor gasto]] -> 25 | M34: =IFERROR(L34/K34, 0) -> 0.5 | N34: Transferido | O34: =IF([1]!Table_246[[#This Row],[Coluna2]]>0.5, "🔥 Excelente", IF([1]!Table_246[[#This Row],[Coluna2]]>0.4, "👍 Bom", "⚠️ Baixo")) -> 👍 Bom
A35: =IF(Table_246[[#This Row],[Data]]="","",MONTH(Table_246[[#This Row],[Data]])) -> 1 | B35: 46039 | C35: Fone P9 | D35: 1 | E35: brinquedo | F35: Fisica | G35: 20 | H35: =Table_246[[#This Row],[QT]]*Table_246[[#This Row],[Custo Un]] -> 20 | I35: 40 | J35: =I35*D35 -> 40 | K35: =I35*D35 -> 40 | L35: =Table_246[[#This Row],[Valor da venda]]-Table_246[[#This Row],[Valor gasto]] -> 20 | M35: =IFERROR(L35/K35, 0) -> 0.5 | N35: Transferido | O35: =IF([1]!Table_246[[#This Row],[Coluna2]]>0.5, "🔥 Excelente", IF([1]!Table_246[[#This Row],[Coluna2]]>0.4, "👍 Bom", "⚠️ Baixo")) -> 👍 Bom
A36: =IF(Table_246[[#This Row],[Data]]="","",MONTH(Table_246[[#This Row],[Data]])) -> 1 | B36: 46042 | C36: Moeba | D36: 1 | E36: remedio | F36: Fisica | G36: 5 | H36: =Table_246[[#This Row],[QT]]*Table_246[[#This Row],[Custo Un]] -> 5 | I36: 10 | J36: =I36*D36 -> 10 | K36: =I36*D36 -> 10 | L36: =Table_246[[#This Row],[Valor da venda]]-Table_246[[#This Row],[Valor gasto]] -> 5 | M36: =IFERROR(L36/K36, 0) -> 0.5 | N36: Transferido | O36: =IF([1]!Table_246[[#This Row],[Coluna2]]>0.5, "🔥 Excelente", IF([1]!Table_246[[#This Row],[Coluna2]]>0.4, "👍 Bom", "⚠️ Baixo")) -> 👍 Bom
A37: =IF(Table_246[[#This Row],[Data]]="","",MONTH(Table_246[[#This Row],[Data]])) -> 1 | B37: 46042 | C37: Cabo Colorido | D37: 1 | E37: aleatorio | F37: Fisica | G37: 5 | H37: =Table_246[[#This Row],[QT]]*Table_246[[#This Row],[Custo Un]] -> 5 | I37: 10 | J37: =I37*D37 -> 10 | K37: =I37*D37 -> 10 | L37: =Table_246[[#This Row],[Valor da venda]]-Table_246[[#This Row],[Valor gasto]] -> 5 | M37: =IFERROR(L37/K37, 0) -> 0.5 | N37: Transferido | O37: =IF([1]!Table_246[[#This Row],[Coluna2]]>0.5, "🔥 Excelente", IF([1]!Table_246[[#This Row],[Coluna2]]>0.4, "👍 Bom", "⚠️ Baixo")) -> 👍 Bom
A38: =IF(Table_246[[#This Row],[Data]]="","",MONTH(Table_246[[#This Row],[Data]])) -> 1 | B38: 46042 | C38: Cabo Iphone 20W | D38: 1 | E38: ruiva | F38: Fisica | G38: =IFERROR(VLOOKUP(C38,PROD!$A$2:$E$1204,5,0),"0") -> 6 | H38: =Table_246[[#This Row],[QT]]*Table_246[[#This Row],[Custo Un]] -> 6 | I38: 20 | J38: =I38*D38 -> 20 | K38: =I38*D38 -> 20 | L38: =Table_246[[#This Row],[Valor da venda]]-Table_246[[#This Row],[Valor gasto]] -> 14 | M38: =IFERROR(L38/K38, 0) -> 0.7 | N38: Transferido | O38: =IF([1]!Table_246[[#This Row],[Coluna2]]>0.5, "🔥 Excelente", IF([1]!Table_246[[#This Row],[Coluna2]]>0.4, "👍 Bom", "⚠️ Baixo")) -> 🔥 Excelente
A39: =IF(Table_246[[#This Row],[Data]]="","",MONTH(Table_246[[#This Row],[Data]])) -> 1 | B39: 46042 | C39: Capinha Iphone | D39: 1 | E39: ruiva | F39: Fisica | G39: 6.5 | H39: =Table_246[[#This Row],[QT]]*Table_246[[#This Row],[Custo Un]] -> 6.5 | I39: 15 | J39: =I39*D39 -> 15 | K39: =I39*D39 -> 15 | L39: =Table_246[[#This Row],[Valor da venda]]-Table_246[[#This Row],[Valor gasto]] -> 8.5 | M39: =IFERROR(L39/K39, 0) -> 0.56666667 | N39: Transferido | O39: =IF([1]!Table_246[[#This Row],[Coluna2]]>0.5, "🔥 Excelente", IF([1]!Table_246[[#This Row],[Coluna2]]>0.4, "👍 Bom", "⚠️ Baixo")) -> 🔥 Excelente
A40: =IF(Table_246[[#This Row],[Data]]="","",MONTH(Table_246[[#This Row],[Data]])) -> 1 | B40: 46042 | C40: Cabo De Força - 3 Pinos | D40: 1 | E40: aleatorio | F40: Fisica | G40: =IFERROR(VLOOKUP(C40,PROD!$A$2:$E$1204,5,0),"0") -> 6 | H40: =Table_246[[#This Row],[QT]]*Table_246[[#This Row],[Custo Un]] -> 6 | I40: 10 | J40: =I40*D40 -> 10 | K40: =I40*D40 -> 10 | L40: =Table_246[[#This Row],[Valor da venda]]-Table_246[[#This Row],[Valor gasto]] -> 4 | M40: =IFERROR(L40/K40, 0) -> 0.4 | N40: Transferido | O40: =IF([1]!Table_246[[#This Row],[Coluna2]]>0.5, "🔥 Excelente", IF([1]!Table_246[[#This Row],[Coluna2]]>0.4, "👍 Bom", "⚠️ Baixo")) -> ⚠️ Baixo
A41: =IF(Table_246[[#This Row],[Data]]="","",MONTH(Table_246[[#This Row],[Data]])) -> 1 | B41: 46042 | C41: Arminha De Agua | D41: 2 | E41: vall | F41: Fisica | G41: 5 | H41: =Table_246[[#This Row],[QT]]*Table_246[[#This Row],[Custo Un]] -> 10 | I41: 10 | J41: =I41*D41 -> 20 | K41: =I41*D41 -> 20 | L41: =Table_246[[#This Row],[Valor da venda]]-Table_246[[#This Row],[Valor gasto]] -> 10 | M41: =IFERROR(L41/K41, 0) -> 0.5 | N41: Transferido | O41: =IF([1]!Table_246[[#This Row],[Coluna2]]>0.5, "🔥 Excelente", IF([1]!Table_246[[#This Row],[Coluna2]]>0.4, "👍 Bom", "⚠️ Baixo")) -> 👍 Bom
A42: =IF(Table_246[[#This Row],[Data]]="","",MONTH(Table_246[[#This Row],[Data]])) -> 1 | B42: 46042 | C42: Opl 16 Mb | D42: 1 | E42: aleatorio | F42: Fisica | G42: 18 | H42: =Table_246[[#This Row],[QT]]*Table_246[[#This Row],[Custo Un]] -> 18 | I42: 35 | J42: =I42*D42 -> 35 | K42: =I42*D42 -> 35 | L42: =Table_246[[#This Row],[Valor da venda]]-Table_246[[#This Row],[Valor gasto]] -> 17 | M42: =IFERROR(L42/K42, 0) -> 0.48571429 | N42: Transferido | O42: =IF([1]!Table_246[[#This Row],[Coluna2]]>0.5, "🔥 Excelente", IF([1]!Table_246[[#This Row],[Coluna2]]>0.4, "👍 Bom", "⚠️ Baixo")) -> 👍 Bom
A43: =IF(Table_246[[#This Row],[Data]]="","",MONTH(Table_246[[#This Row],[Data]])) -> 1 | B43: 46042 | C43: Pendrive 32 | D43: 1 | E43: aleatorio | F43: Fisica | G43: 25 | H43: =Table_246[[#This Row],[QT]]*Table_246[[#This Row],[Custo Un]] -> 25 | I43: 60 | J43: =I43*D43 -> 60 | K43: =I43*D43 -> 60 | L43: =Table_246[[#This Row],[Valor da venda]]-Table_246[[#This Row],[Valor gasto]] -> 35 | M43: =IFERROR(L43/K43, 0) -> 0.58333333 | N43: Transferido | O43: =IF([1]!Table_246[[#This Row],[Coluna2]]>0.5, "🔥 Excelente", IF([1]!Table_246[[#This Row],[Coluna2]]>0.4, "👍 Bom", "⚠️ Baixo")) -> 🔥 Excelente
A44: =IF(Table_246[[#This Row],[Data]]="","",MONTH(Table_246[[#This Row],[Data]])) -> 1 | B44: 46043 | C44: Cabo De Força - 3 Pinos | D44: 1 | E44: thuane | F44: Fisica | G44: 5 | H44: =Table_246[[#This Row],[QT]]*Table_246[[#This Row],[Custo Un]] -> 5 | I44: 10 | J44: =I44*D44 -> 10 | K44: =I44*D44 -> 10 | L44: =Table_246[[#This Row],[Valor da venda]]-Table_246[[#This Row],[Valor gasto]] -> 5 | M44: =IFERROR(L44/K44, 0) -> 0.5 | N44: Transferido | O44: =IF([1]!Table_246[[#This Row],[Coluna2]]>0.5, "🔥 Excelente", IF([1]!Table_246[[#This Row],[Coluna2]]>0.4, "👍 Bom", "⚠️ Baixo")) -> 👍 Bom
A45: =IF(Table_246[[#This Row],[Data]]="","",MONTH(Table_246[[#This Row],[Data]])) -> 1 | B45: 46043 | C45: Conversor Vga Para Hdmi | D45: 1 | E45: thuane | F45: Fisica | G45: 20 | H45: =Table_246[[#This Row],[QT]]*Table_246[[#This Row],[Custo Un]] -> 20 | I45: 30 | J45: =I45*D45 -> 30 | K45: =I45*D45 -> 30 | L45: =Table_246[[#This Row],[Valor da venda]]-Table_246[[#This Row],[Valor gasto]] -> 10 | M45: =IFERROR(L45/K45, 0) -> 0.33333333 | N45: Transferido | O45: =IF([1]!Table_246[[#This Row],[Coluna2]]>0.5, "🔥 Excelente", IF([1]!Table_246[[#This Row],[Coluna2]]>0.4, "👍 Bom", "⚠️ Baixo")) -> ⚠️ Baixo
A46: =IF(Table_246[[#This Row],[Data]]="","",MONTH(Table_246[[#This Row],[Data]])) -> 1 | B46: 46043 | C46: Mouse Sem Fio | D46: 1 | E46: thuane | F46: Fisica | G46: 18 | H46: =Table_246[[#This Row],[QT]]*Table_246[[#This Row],[Custo Un]] -> 18 | I46: 30 | J46: =I46*D46 -> 30 | K46: =I46*D46 -> 30 | L46: =Table_246[[#This Row],[Valor da venda]]-Table_246[[#This Row],[Valor gasto]] -> 12 | M46: =IFERROR(L46/K46, 0) -> 0.4 | N46: Transferido | O46: =IF([1]!Table_246[[#This Row],[Coluna2]]>0.5, "🔥 Excelente", IF([1]!Table_246[[#This Row],[Coluna2]]>0.4, "👍 Bom", "⚠️ Baixo")) -> ⚠️ Baixo
A47: =IF(Table_246[[#This Row],[Data]]="","",MONTH(Table_246[[#This Row],[Data]])) -> 1 | B47: 46043 | C47: Cheirinho Para Carro | D47: 1 | E47: 260120HKJW21F6 | F47: Shopee | G47: 7.5 | H47: =Table_246[[#This Row],[QT]]*Table_246[[#This Row],[Custo Un]] -> 7.5 | I47: 11.2 | J47: =I47*D47 -> 11.2 | K47: =I47*D47 -> 11.2 | L47: =Table_246[[#This Row],[Valor da venda]]-Table_246[[#This Row],[Valor gasto]] -> 3.7 | M47: =IFERROR(L47/K47, 0) -> 0.33035714 | N47: Transferido | O47: =IF([1]!Table_246[[#This Row],[Coluna2]]>0.5, "🔥 Excelente", IF([1]!Table_246[[#This Row],[Coluna2]]>0.4, "👍 Bom", "⚠️ Baixo")) -> ⚠️ Baixo
A48: =IF(Table_246[[#This Row],[Data]]="","",MONTH(Table_246[[#This Row],[Data]])) -> 1 | B48: 46043 | C48: Tweeter Evok 400 | D48: 1 | E48: 260120HW0K4N7G | F48: Shopee | G48: 0 | H48: =Table_246[[#This Row],[QT]]*Table_246[[#This Row],[Custo Un]] -> 0 | I48: 45.84 | J48: =I48*D48 -> 45.84 | K48: =I48*D48 -> 45.84 | L48: =Table_246[[#This Row],[Valor da venda]]-Table_246[[#This Row],[Valor gasto]] -> 45.84 | M48: =IFERROR(L48/K48, 0) -> 1 | N48: Transferido | O48: =IF([1]!Table_246[[#This Row],[Coluna2]]>0.5, "🔥 Excelente", IF([1]!Table_246[[#This Row],[Coluna2]]>0.4, "👍 Bom", "⚠️ Baixo")) -> 🔥 Excelente
A49: =IF(Table_246[[#This Row],[Data]]="","",MONTH(Table_246[[#This Row],[Data]])) -> 1 | B49: 46043 | C49: Kit 10 Jogos Ps2 | D49: 1 | E49: 582149843775227 | F49: Tiktok | G49: 7 | H49: =Table_246[[#This Row],[QT]]*Table_246[[#This Row],[Custo Un]] -> 7 | I49: 55.2 | J49: =I49*D49 -> 55.2 | K49: =I49*D49 -> 55.2 | L49: =Table_246[[#This Row],[Valor da venda]]-Table_246[[#This Row],[Valor gasto]] -> 48.2 | M49: =IFERROR(L49/K49, 0) -> 0.87318841 | N49: Transferido | O49: =IF([1]!Table_246[[#This Row],[Coluna2]]>0.5, "🔥 Excelente", IF([1]!Table_246[[#This Row],[Coluna2]]>0.4, "👍 Bom", "⚠️ Baixo")) -> 🔥 Excelente
A50: =IF(Table_246[[#This Row],[Data]]="","",MONTH(Table_246[[#This Row],[Data]])) -> 1 | B50: 46044 | C50: Impressao Preta | D50: 12 | E50: sonia | F50: Fisica | G50: =IFERROR(VLOOKUP(C50,PROD!$A$2:$E$1204,5,0),"0") -> 0.07 | H50: =Table_246[[#This Row],[QT]]*Table_246[[#This Row],[Custo Un]] -> 0.84 | I50: 1 | J50: =I50*D50 -> 12 | K50: =I50*D50 -> 12 | L50: =Table_246[[#This Row],[Valor da venda]]-Table_246[[#This Row],[Valor gasto]] -> 11.16 | M50: =IFERROR(L50/K50, 0) -> 0.93 | N50: Transferido | O50: =IF([1]!Table_246[[#This Row],[Coluna2]]>0.5, "🔥 Excelente", IF([1]!Table_246[[#This Row],[Coluna2]]>0.4, "👍 Bom", "⚠️ Baixo")) -> 🔥 Excelente
A51: =IF(Table_246[[#This Row],[Data]]="","",MONTH(Table_246[[#This Row],[Data]])) -> 1 | B51: 46044 | C51: Impressao Preta | D51: 2 | E51: BONECA | F51: Fisica | G51: =IFERROR(VLOOKUP(C51,PROD!$A$2:$E$1204,5,0),"0") -> 0.07 | H51: =Table_246[[#This Row],[QT]]*Table_246[[#This Row],[Custo Un]] -> 0.14 | I51: 1 | J51: =I51*D51 -> 2 | K51: =I51*D51 -> 2 | L51: =Table_246[[#This Row],[Valor da venda]]-Table_246[[#This Row],[Valor gasto]] -> 1.86 | M51: =IFERROR(L51/K51, 0) -> 0.93 | N51: Transferido | O51: =IF([1]!Table_246[[#This Row],[Coluna2]]>0.5, "🔥 Excelente", IF([1]!Table_246[[#This Row],[Coluna2]]>0.4, "👍 Bom", "⚠️ Baixo")) -> 🔥 Excelente
A52: =IF(Table_246[[#This Row],[Data]]="","",MONTH(Table_246[[#This Row],[Data]])) -> 1 | B52: 46044 | C52: Chaveiro | D52: 1 | E52: aysha | F52: Fisica | G52: =IFERROR(VLOOKUP(C52,PROD!$A$2:$E$1204,5,0),"0") -> 0 | H52: =Table_246[[#This Row],[QT]]*Table_246[[#This Row],[Custo Un]] -> 0 | I52: 3 | J52: =I52*D52 -> 3 | K52: =I52*D52 -> 3 | L52: =Table_246[[#This Row],[Valor da venda]]-Table_246[[#This Row],[Valor gasto]] -> 3 | M52: =IFERROR(L52/K52, 0) -> 1 | N52: Transferido | O52: =IF([1]!Table_246[[#This Row],[Coluna2]]>0.5, "🔥 Excelente", IF([1]!Table_246[[#This Row],[Coluna2]]>0.4, "👍 Bom", "⚠️ Baixo")) -> 🔥 Excelente
A53: =IF(Table_246[[#This Row],[Data]]="","",MONTH(Table_246[[#This Row],[Data]])) -> 1 | B53: 46045 | C53: Formatação | D53: 1 | E53: alexandre | F53: Fisica | G53: =IFERROR(VLOOKUP(#REF!,PROD!$A$2:$E$1204,5,0),"0") -> 0 | H53: =Table_246[[#This Row],[QT]]*Table_246[[#This Row],[Custo Un]] -> 0 | I53: 70 | J53: =I53*D53 -> 70 | K53: =I53*D53 -> 70 | L53: =Table_246[[#This Row],[Valor da venda]]-Table_246[[#This Row],[Valor gasto]] -> 70 | M53: =IFERROR(L53/K53, 0) -> 1 | N53: Transferido | O53: =IF([1]!Table_246[[#This Row],[Coluna2]]>0.5, "🔥 Excelente", IF([1]!Table_246[[#This Row],[Coluna2]]>0.4, "👍 Bom", "⚠️ Baixo")) -> 🔥 Excelente
A54: =IF(Table_246[[#This Row],[Data]]="","",MONTH(Table_246[[#This Row],[Data]])) -> 1 | B54: 46045 | C54: Serviço Aleatorio | D54: 1 | E54: Eliane | F54: Fisica | G54: =IFERROR(VLOOKUP(C53,PROD!$A$2:$E$1204,5,0),"0") -> 0 | H54: =Table_246[[#This Row],[QT]]*Table_246[[#This Row],[Custo Un]] -> 0 | I54: 50 | J54: =I54*D54 -> 50 | K54: =I54*D54 -> 50 | L54: =Table_246[[#This Row],[Valor da venda]]-Table_246[[#This Row],[Valor gasto]] -> 50 | M54: =IFERROR(L54/K54, 0) -> 1 | N54: Transferido | O54: =IF([1]!Table_246[[#This Row],[Coluna2]]>0.5, "🔥 Excelente", IF([1]!Table_246[[#This Row],[Coluna2]]>0.4, "👍 Bom", "⚠️ Baixo")) -> 🔥 Excelente
A55: =IF(Table_246[[#This Row],[Data]]="","",MONTH(Table_246[[#This Row],[Data]])) -> 1 | B55: 46046 | C55: Uno | D55: 1 | E55: manu | F55: Fisica | G55: 5 | H55: =Table_246[[#This Row],[QT]]*Table_246[[#This Row],[Custo Un]] -> 5 | I55: 10 | J55: =I55*D55 -> 10 | K55: =I55*D55 -> 10 | L55: =Table_246[[#This Row],[Valor da venda]]-Table_246[[#This Row],[Valor gasto]] -> 5 | M55: =IFERROR(L55/K55, 0) -> 0.5 | N55: Transferido | O55: =IF([1]!Table_246[[#This Row],[Coluna2]]>0.5, "🔥 Excelente", IF([1]!Table_246[[#This Row],[Coluna2]]>0.4, "👍 Bom", "⚠️ Baixo")) -> 👍 Bom
A56: =IF(Table_246[[#This Row],[Data]]="","",MONTH(Table_246[[#This Row],[Data]])) -> 1 | B56: 46046 | C56: Impressao Preta | D56: 5 | E56: relogio | F56: Fisica | G56: =IFERROR(VLOOKUP(C56,PROD!$A$2:$E$1204,5,0),"0") -> 0.07 | H56: =Table_246[[#This Row],[QT]]*Table_246[[#This Row],[Custo Un]] -> 0.35 | I56: 1 | J56: =I56*D56 -> 5 | K56: =I56*D56 -> 5 | L56: =Table_246[[#This Row],[Valor da venda]]-Table_246[[#This Row],[Valor gasto]] -> 4.65 | M56: =IFERROR(L56/K56, 0) -> 0.93 | N56: Transferido | O56: =IF([1]!Table_246[[#This Row],[Coluna2]]>0.5, "🔥 Excelente", IF([1]!Table_246[[#This Row],[Coluna2]]>0.4, "👍 Bom", "⚠️ Baixo")) -> 🔥 Excelente
A57: =IF(Table_246[[#This Row],[Data]]="","",MONTH(Table_246[[#This Row],[Data]])) -> 1 | B57: 46048 | C57: Jogo Ps2 Shopee | D57: 1 | E57: 26012501R0305B | F57: Shopee | G57: 0.7 | H57: =Table_246[[#This Row],[QT]]*Table_246[[#This Row],[Custo Un]] -> 0.7 | I57: 6.26 | J57: =I57*D57 -> 6.26 | K57: =I57*D57 -> 6.26 | L57: =Table_246[[#This Row],[Valor da venda]]-Table_246[[#This Row],[Valor gasto]] -> 5.56 | M57: =IFERROR(L57/K57, 0) -> 0.88817891 | N57: Transferido | O57: =IF([1]!Table_246[[#This Row],[Coluna2]]>0.5, "🔥 Excelente", IF([1]!Table_246[[#This Row],[Coluna2]]>0.4, "👍 Bom", "⚠️ Baixo")) -> 🔥 Excelente
A58: =IF(Table_246[[#This Row],[Data]]="","",MONTH(Table_246[[#This Row],[Data]])) -> 1 | B58: 46048 | C58: Coleção_4_Jogos_Ben_10_Ps2 | D58: 1 | E58: 260125W10MYBA6 | F58: Shopee | G58: =0.7*4 -> 2.8 | H58: =Table_246[[#This Row],[QT]]*Table_246[[#This Row],[Custo Un]] -> 2.8 | I58: 6.26 | J58: =I58*D58 -> 6.26 | K58: =I58*D58 -> 6.26 | L58: =Table_246[[#This Row],[Valor da venda]]-Table_246[[#This Row],[Valor gasto]] -> 3.46 | M58: =IFERROR(L58/K58, 0) -> 0.55271565 | N58: Transferido | O58: =IF([1]!Table_246[[#This Row],[Coluna2]]>0.5, "🔥 Excelente", IF([1]!Table_246[[#This Row],[Coluna2]]>0.4, "👍 Bom", "⚠️ Baixo")) -> 🔥 Excelente
A59: =IF(Table_246[[#This Row],[Data]]="","",MONTH(Table_246[[#This Row],[Data]])) -> 1 | B59: 46048 | C59: Kit Com 10 Mini Fusível | D59: 1 | E59: 260123QKXEPFNT | F59: Shopee | G59: 4.5 | H59: =Table_246[[#This Row],[QT]]*Table_246[[#This Row],[Custo Un]] -> 4.5 | I59: 17.06 | J59: =I59*D59 -> 17.06 | K59: =I59*D59 -> 17.06 | L59: =Table_246[[#This Row],[Valor da venda]]-Table_246[[#This Row],[Valor gasto]] -> 12.56 | M59: =IFERROR(L59/K59, 0) -> 0.73622509 | N59: Transferido | O59: =IF([1]!Table_246[[#This Row],[Coluna2]]>0.5, "🔥 Excelente", IF([1]!Table_246[[#This Row],[Coluna2]]>0.4, "👍 Bom", "⚠️ Baixo")) -> 🔥 Excelente
A60: =IF(Table_246[[#This Row],[Data]]="","",MONTH(Table_246[[#This Row],[Data]])) -> 1 | B60: 46048 | C60: Kit 10 Jogos Ps2 | D60: 1 | E60: 2601262EWM7HSQ | F60: Shopee | G60: 7 | H60: =Table_246[[#This Row],[QT]]*Table_246[[#This Row],[Custo Un]] -> 7 | I60: 45.39 | J60: =I60*D60 -> 45.39 | K60: =I60*D60 -> 45.39 | L60: =Table_246[[#This Row],[Valor da venda]]-Table_246[[#This Row],[Valor gasto]] -> 38.39 | M60: =IFERROR(L60/K60, 0) -> 0.84578101 | N60: Transferido | O60: =IF([1]!Table_246[[#This Row],[Coluna2]]>0.5, "🔥 Excelente", IF([1]!Table_246[[#This Row],[Coluna2]]>0.4, "👍 Bom", "⚠️ Baixo")) -> 🔥 Excelente
A61: =IF(Table_246[[#This Row],[Data]]="","",MONTH(Table_246[[#This Row],[Data]])) -> 1 | B61: 46048 | C61: Jogo Ps2 Shopee | D61: 1 | E61: 26012643AWWXYN | F61: Shopee | G61: 0.7 | H61: =Table_246[[#This Row],[QT]]*Table_246[[#This Row],[Custo Un]] -> 0.7 | I61: 8.31 | J61: =I61*D61 -> 8.31 | K61: =I61*D61 -> 8.31 | L61: =Table_246[[#This Row],[Valor da venda]]-Table_246[[#This Row],[Valor gasto]] -> 7.61 | M61: =IFERROR(L61/K61, 0) -> 0.91576414 | N61: Transferido | O61: =IF([1]!Table_246[[#This Row],[Coluna2]]>0.5, "🔥 Excelente", IF([1]!Table_246[[#This Row],[Coluna2]]>0.4, "👍 Bom", "⚠️ Baixo")) -> 🔥 Excelente
A62: =IF(Table_246[[#This Row],[Data]]="","",MONTH(Table_246[[#This Row],[Data]])) -> 1 | B62: 46048 | C62: Unitv V10 | D62: 1 | E62: luiz | F62: Fisica | G62: 275 | H62: =Table_246[[#This Row],[QT]]*Table_246[[#This Row],[Custo Un]] -> 275 | I62: 360 | J62: =I62*D62 -> 360 | K62: =I62*D62 -> 360 | L62: =Table_246[[#This Row],[Valor da venda]]-Table_246[[#This Row],[Valor gasto]] -> 85 | M62: =IFERROR(L62/K62, 0) -> 0.23611111 | N62: Transferido | O62: =IF([1]!Table_246[[#This Row],[Coluna2]]>0.5, "🔥 Excelente", IF([1]!Table_246[[#This Row],[Coluna2]]>0.4, "👍 Bom", "⚠️ Baixo")) -> ⚠️ Baixo
A63: =IF(Table_246[[#This Row],[Data]]="","",MONTH(Table_246[[#This Row],[Data]])) -> 1 | B63: 46049 | C63: Jogo Ps2 Shopee | D63: 1 | E63: 26012877ASXSW2 | F63: Shopee | G63: =IFERROR(VLOOKUP(C63,PROD!$A$2:$E$1204,5,0),"0") -> 0.7 | H63: =Table_246[[#This Row],[QT]]*Table_246[[#This Row],[Custo Un]] -> 0.7 | I63: 7.02 | J63: =I63*D63 -> 7.02 | K63: =I63*D63 -> 7.02 | L63: =Table_246[[#This Row],[Valor da venda]]-Table_246[[#This Row],[Valor gasto]] -> 6.32 | M63: =IFERROR(L63/K63, 0) -> 0.9002849 | N63: Transferido | O63: =IF([1]!Table_246[[#This Row],[Coluna2]]>0.5, "🔥 Excelente", IF([1]!Table_246[[#This Row],[Coluna2]]>0.4, "👍 Bom", "⚠️ Baixo")) -> 🔥 Excelente
A64: =IF(Table_246[[#This Row],[Data]]="","",MONTH(Table_246[[#This Row],[Data]])) -> 1 | B64: 46049 | C64: Jogo Ps2 Shopee | D64: 1 | E64: 26012879CE069S | F64: Shopee | G64: =IFERROR(VLOOKUP(C64,PROD!$A$2:$E$1204,5,0),"0") -> 0.7 | H64: =Table_246[[#This Row],[QT]]*Table_246[[#This Row],[Custo Un]] -> 0.7 | I64: 7.02 | J64: =I64*D64 -> 7.02 | K64: =I64*D64 -> 7.02 | L64: =Table_246[[#This Row],[Valor da venda]]-Table_246[[#This Row],[Valor gasto]] -> 6.32 | M64: =IFERROR(L64/K64, 0) -> 0.9002849 | N64: Transferido | O64: =IF([1]!Table_246[[#This Row],[Coluna2]]>0.5, "🔥 Excelente", IF([1]!Table_246[[#This Row],[Coluna2]]>0.4, "👍 Bom", "⚠️ Baixo")) -> 🔥 Excelente
A65: =IF(Table_246[[#This Row],[Data]]="","",MONTH(Table_246[[#This Row],[Data]])) -> 1 | B65: 46050 | C65: Cheirinho Para Carro | D65: 1 | E65: 2601287HCSF395 | F65: Shopee | G65: =IFERROR(VLOOKUP(C65,PROD!$A$2:$E$1204,5,0),"0") -> 7.5 | H65: =Table_246[[#This Row],[QT]]*Table_246[[#This Row],[Custo Un]] -> 7.5 | I65: 14.04 | J65: =I65*D65 -> 14.04 | K65: =I65*D65 -> 14.04 | L65: =Table_246[[#This Row],[Valor da venda]]-Table_246[[#This Row],[Valor gasto]] -> 6.54 | M65: =IFERROR(L65/K65, 0) -> 0.46581197 | N65: Transferido | O65: =IF([1]!Table_246[[#This Row],[Coluna2]]>0.5, "🔥 Excelente", IF([1]!Table_246[[#This Row],[Coluna2]]>0.4, "👍 Bom", "⚠️ Baixo")) -> 👍 Bom
A66: =IF(Table_246[[#This Row],[Data]]="","",MONTH(Table_246[[#This Row],[Data]])) -> 1 | B66: 46050 | C66: Jogo Ps2 Shopee | D66: 1 | E66: 2601288URC8VEF | F66: Shopee | G66: =IFERROR(VLOOKUP(C66,PROD!$A$2:$E$1204,5,0),"0") -> 0.7 | H66: =Table_246[[#This Row],[QT]]*Table_246[[#This Row],[Custo Un]] -> 0.7 | I66: 7.02 | J66: =I66*D66 -> 7.02 | K66: =I66*D66 -> 7.02 | L66: =Table_246[[#This Row],[Valor da venda]]-Table_246[[#This Row],[Valor gasto]] -> 6.32 | M66: =IFERROR(L66/K66, 0) -> 0.9002849 | N66: Transferido | O66: =IF([1]!Table_246[[#This Row],[Coluna2]]>0.5, "🔥 Excelente", IF([1]!Table_246[[#This Row],[Coluna2]]>0.4, "👍 Bom", "⚠️ Baixo")) -> 🔥 Excelente
A67: =IF(Table_246[[#This Row],[Data]]="","",MONTH(Table_246[[#This Row],[Data]])) -> 1 | B67: 46049 | C67: Capinha Simples | D67: 2 | E67: remdio | F67: Fisica | G67: 5 | H67: =Table_246[[#This Row],[QT]]*Table_246[[#This Row],[Custo Un]] -> 10 | I67: 10 | J67: =I67*D67 -> 20 | K67: =I67*D67 -> 20 | L67: =Table_246[[#This Row],[Valor da venda]]-Table_246[[#This Row],[Valor gasto]] -> 10 | M67: =IFERROR(L67/K67, 0) -> 0.5 | N67: Transferido | O67: =IF([1]!Table_246[[#This Row],[Coluna2]]>0.5, "🔥 Excelente", IF([1]!Table_246[[#This Row],[Coluna2]]>0.4, "👍 Bom", "⚠️ Baixo")) -> 👍 Bom
A68: =IF(Table_246[[#This Row],[Data]]="","",MONTH(Table_246[[#This Row],[Data]])) -> 1 | B68: 46051 | C68: Cartao Micro Sd 16Gb | D68: 1 | E68: aleatorio | F68: Fisica | G68: 14 | H68: =Table_246[[#This Row],[QT]]*Table_246[[#This Row],[Custo Un]] -> 14 | I68: 40 | J68: =I68*D68 -> 40 | K68: =I68*D68 -> 40 | L68: =Table_246[[#This Row],[Valor da venda]]-Table_246[[#This Row],[Valor gasto]] -> 26 | M68: =IFERROR(L68/K68, 0) -> 0.65 | N68: Transferido | O68: =IF([1]!Table_246[[#This Row],[Coluna2]]>0.5, "🔥 Excelente", IF([1]!Table_246[[#This Row],[Coluna2]]>0.4, "👍 Bom", "⚠️ Baixo")) -> 🔥 Excelente
A69: =IF(Table_246[[#This Row],[Data]]="","",MONTH(Table_246[[#This Row],[Data]])) -> 1 | B69: 46051 | C69: Pelicula 3D | D69: 1 | E69: aleatorio | F69: Fisica | G69: =IFERROR(VLOOKUP(C69,PROD!$A$2:$E$1204,5,0),"0") -> 3 | H69: =Table_246[[#This Row],[QT]]*Table_246[[#This Row],[Custo Un]] -> 3 | I69: 15 | J69: =I69*D69 -> 15 | K69: =I69*D69 -> 15 | L69: =Table_246[[#This Row],[Valor da venda]]-Table_246[[#This Row],[Valor gasto]] -> 12 | M69: =IFERROR(L69/K69, 0) -> 0.8 | N69: Transferido | O69: =IF([1]!Table_246[[#This Row],[Coluna2]]>0.5, "🔥 Excelente", IF([1]!Table_246[[#This Row],[Coluna2]]>0.4, "👍 Bom", "⚠️ Baixo")) -> 🔥 Excelente
A70: =IF(Table_246[[#This Row],[Data]]="","",MONTH(Table_246[[#This Row],[Data]])) -> 1 | B70: 46051 | C70: Kit 10 Jogos Ps2 | D70: 1 | E70: 260131E6UQ7MER | F70: Shopee | G70: =IFERROR(VLOOKUP(C70,PROD!$A$2:$E$1204,5,0),"0") -> 0 | H70: =Table_246[[#This Row],[QT]]*Table_246[[#This Row],[Custo Un]] -> 0 | I70: 45.39 | J70: =I70*D70 -> 45.39 | K70: =I70*D70 -> 45.39 | L70: =Table_246[[#This Row],[Valor da venda]]-Table_246[[#This Row],[Valor gasto]] -> 45.39 | M70: =IFERROR(L70/K70, 0) -> 1 | N70: Transferido | O70: =IF([1]!Table_246[[#This Row],[Coluna2]]>0.5, "🔥 Excelente", IF([1]!Table_246[[#This Row],[Coluna2]]>0.4, "👍 Bom", "⚠️ Baixo")) -> 🔥 Excelente
A71: =IF(Table_246[[#This Row],[Data]]="","",MONTH(Table_246[[#This Row],[Data]])) -> 1 | B71: 46052 | C71: Impressao Preta | D71: 1 | E71: aleatorio | F71: Fisica | G71: =IFERROR(VLOOKUP(C71,PROD!$A$2:$E$1204,5,0),"0") -> 0.07 | H71: =Table_246[[#This Row],[QT]]*Table_246[[#This Row],[Custo Un]] -> 0.07 | I71: 1 | J71: =I71*D71 -> 1 | K71: =I71*D71 -> 1 | L71: =Table_246[[#This Row],[Valor da venda]]-Table_246[[#This Row],[Valor gasto]] -> 0.93 | M71: =IFERROR(L71/K71, 0) -> 0.93 | N71: Transferido | O71: =IF([1]!Table_246[[#This Row],[Coluna2]]>0.5, "🔥 Excelente", IF([1]!Table_246[[#This Row],[Coluna2]]>0.4, "👍 Bom", "⚠️ Baixo")) -> 🔥 Excelente
A72: =IF(Table_246[[#This Row],[Data]]="","",MONTH(Table_246[[#This Row],[Data]])) -> 1 | B72: 46052 | C72: Kit 10 Jogos Ps2 | D72: 1 | E72: 582355031501800714 | F72: Tiktok | G72: =IFERROR(VLOOKUP(C72,PROD!$A$2:$E$1204,5,0),"0") -> 0 | H72: =Table_246[[#This Row],[QT]]*Table_246[[#This Row],[Custo Un]] -> 0 | I72: 55.2 | J72: =I72*D72 -> 55.2 | K72: =I72*D72 -> 55.2 | L72: =Table_246[[#This Row],[Valor da venda]]-Table_246[[#This Row],[Valor gasto]] -> 55.2 | M72: =IFERROR(L72/K72, 0) -> 1 | N72: Transferido | O72: =IF([1]!Table_246[[#This Row],[Coluna2]]>0.5, "🔥 Excelente", IF([1]!Table_246[[#This Row],[Coluna2]]>0.4, "👍 Bom", "⚠️ Baixo")) -> 🔥 Excelente
A73: =IF(Table_246[[#This Row],[Data]]="","",MONTH(Table_246[[#This Row],[Data]])) -> 1 | B73: 46053 | C73: Suporte Veicular | D73: 1 | E73: gian | F73: Fisica | G73: 12 | H73: =Table_246[[#This Row],[QT]]*Table_246[[#This Row],[Custo Un]] -> 12 | I73: 20 | J73: =I73*D73 -> 20 | K73: =I73*D73 -> 20 | L73: =Table_246[[#This Row],[Valor da venda]]-Table_246[[#This Row],[Valor gasto]] -> 8 | M73: =IFERROR(L73/K73, 0) -> 0.4 | N73: Transferido | O73: =IF([1]!Table_246[[#This Row],[Coluna2]]>0.5, "🔥 Excelente", IF([1]!Table_246[[#This Row],[Coluna2]]>0.4, "👍 Bom", "⚠️ Baixo")) -> ⚠️ Baixo
A74: =IF(Table_246[[#This Row],[Data]]="","",MONTH(Table_246[[#This Row],[Data]])) -> 1 | B74: 46053 | C74: Cabo Iphone 20W | D74: 1 | E74: gian | F74: Fisica | G74: 5 | H74: =Table_246[[#This Row],[QT]]*Table_246[[#This Row],[Custo Un]] -> 5 | I74: 30 | J74: =I74*D74 -> 30 | K74: =I74*D74 -> 30 | L74: =Table_246[[#This Row],[Valor da venda]]-Table_246[[#This Row],[Valor gasto]] -> 25 | M74: =IFERROR(L74/K74, 0) -> 0.83333333 | N74: Transferido | O74: =IF([1]!Table_246[[#This Row],[Coluna2]]>0.5, "🔥 Excelente", IF([1]!Table_246[[#This Row],[Coluna2]]>0.4, "👍 Bom", "⚠️ Baixo")) -> 🔥 Excelente
A75: =IF(Table_246[[#This Row],[Data]]="","",MONTH(Table_246[[#This Row],[Data]])) -> 1 | B75: 46053 | C75: Lanterna | D75: 1 | E75: aleatorio | F75: Fisica | G75: =IFERROR(VLOOKUP(C75,PROD!$A$2:$E$1204,5,0),"0") -> 0 | H75: =Table_246[[#This Row],[QT]]*Table_246[[#This Row],[Custo Un]] -> 0 | I75: 10 | J75: =I75*D75 -> 10 | K75: =I75*D75 -> 10 | L75: =Table_246[[#This Row],[Valor da venda]]-Table_246[[#This Row],[Valor gasto]] -> 10 | M75: =IFERROR(L75/K75, 0) -> 1 | N75: Transferido | O75: =IF([1]!Table_246[[#This Row],[Coluna2]]>0.5, "🔥 Excelente", IF([1]!Table_246[[#This Row],[Coluna2]]>0.4, "👍 Bom", "⚠️ Baixo")) -> 🔥 Excelente
A76: =IF(Table_246[[#This Row],[Data]]="","",MONTH(Table_246[[#This Row],[Data]])) -> 2 | B76: 46054 | C76: Jogo Ps2 Shopee | D76: 3 | E76: 260202KGB8PW0S | F76: Shopee | G76: =IFERROR(VLOOKUP(C76,PROD!$A$2:$E$1204,5,0),"0") -> 0.7 | H76: =Table_246[[#This Row],[QT]]*Table_246[[#This Row],[Custo Un]] -> 2.1 | I76: 22.02 | J76: =I76*D76 -> 66.06 | K76: =I76*D76 -> 66.06 | L76: =Table_246[[#This Row],[Valor da venda]]-Table_246[[#This Row],[Valor gasto]] -> 63.96 | M76: =IFERROR(L76/K76, 0) -> 0.96821072 | N76: Transferido | O76: =IF([1]!Table_246[[#This Row],[Coluna2]]>0.5, "🔥 Excelente", IF([1]!Table_246[[#This Row],[Coluna2]]>0.4, "👍 Bom", "⚠️ Baixo")) -> 🔥 Excelente
A77: =IF(Table_246[[#This Row],[Data]]="","",MONTH(Table_246[[#This Row],[Data]])) -> 2 | B77: 46054 | C77: Jogo Ps2 Shopee | D77: 1 | E77: 260202KDJAYA04 | F77: Shopee | G77: =IFERROR(VLOOKUP(C77,PROD!$A$2:$E$1204,5,0),"0") -> 0.7 | H77: =Table_246[[#This Row],[QT]]*Table_246[[#This Row],[Custo Un]] -> 0.7 | I77: 7.02 | J77: =I77*D77 -> 7.02 | K77: =I77*D77 -> 7.02 | L77: =Table_246[[#This Row],[Valor da venda]]-Table_246[[#This Row],[Valor gasto]] -> 6.32 | M77: =IFERROR(L77/K77, 0) -> 0.9002849 | N77: Transferido | O77: =IF([1]!Table_246[[#This Row],[Coluna2]]>0.5, "🔥 Excelente", IF([1]!Table_246[[#This Row],[Coluna2]]>0.4, "👍 Bom", "⚠️ Baixo")) -> 🔥 Excelente
A78: =IF(Table_246[[#This Row],[Data]]="","",MONTH(Table_246[[#This Row],[Data]])) -> 2 | B78: 46054 | C78: Jogo Ps2 Shopee | D78: 1 | E78: 260202KB9XFY1F | F78: Shopee | G78: =IFERROR(VLOOKUP(C78,PROD!$A$2:$E$1204,5,0),"0") -> 0.7 | H78: =Table_246[[#This Row],[QT]]*Table_246[[#This Row],[Custo Un]] -> 0.7 | I78: 7.02 | J78: =I78*D78 -> 7.02 | K78: =I78*D78 -> 7.02 | L78: =Table_246[[#This Row],[Valor da venda]]-Table_246[[#This Row],[Valor gasto]] -> 6.32 | M78: =IFERROR(L78/K78, 0) -> 0.9002849 | N78: Transferido | O78: =IF([1]!Table_246[[#This Row],[Coluna2]]>0.5, "🔥 Excelente", IF([1]!Table_246[[#This Row],[Coluna2]]>0.4, "👍 Bom", "⚠️ Baixo")) -> 🔥 Excelente
A79: =IF(Table_246[[#This Row],[Data]]="","",MONTH(Table_246[[#This Row],[Data]])) -> 2 | B79: 46054 | C79: Jogo Ps2 Shopee | D79: 2 | E79: 260201HUCC9A14 | F79: Shopee | G79: =IFERROR(VLOOKUP(C79,PROD!$A$2:$E$1204,5,0),"0") -> 0.7 | H79: =Table_246[[#This Row],[QT]]*Table_246[[#This Row],[Custo Un]] -> 1.4 | I79: 14.99 | J79: =I79*D79 -> 29.98 | K79: =I79*D79 -> 29.98 | L79: =Table_246[[#This Row],[Valor da venda]]-Table_246[[#This Row],[Valor gasto]] -> 28.58 | M79: =IFERROR(L79/K79, 0) -> 0.9533022 | N79: Transferido | O79: =IF([1]!Table_246[[#This Row],[Coluna2]]>0.5, "🔥 Excelente", IF([1]!Table_246[[#This Row],[Coluna2]]>0.4, "👍 Bom", "⚠️ Baixo")) -> 🔥 Excelente
A80: =IF(Table_246[[#This Row],[Data]]="","",MONTH(Table_246[[#This Row],[Data]])) -> 2 | B80: 46055 | C80: Cheirinho Para Carro | D80: 1 | E80: 260130BPA5UXQ0 | F80: Shopee | G80: =IFERROR(VLOOKUP(C80,PROD!$A$2:$E$1204,5,0),"0") -> 7.5 | H80: =Table_246[[#This Row],[QT]]*Table_246[[#This Row],[Custo Un]] -> 7.5 | I80: 14.04 | J80: =I80*D80 -> 14.04 | K80: =I80*D80 -> 14.04 | L80: =Table_246[[#This Row],[Valor da venda]]-Table_246[[#This Row],[Valor gasto]] -> 6.54 | M80: =IFERROR(L80/K80, 0) -> 0.46581197 | N80: Transferido | O80: =IF([1]!Table_246[[#This Row],[Coluna2]]>0.5, "🔥 Excelente", IF([1]!Table_246[[#This Row],[Coluna2]]>0.4, "👍 Bom", "⚠️ Baixo")) -> 👍 Bom
A81: =IF(Table_246[[#This Row],[Data]]="","",MONTH(Table_246[[#This Row],[Data]])) -> 2 | B81: 46055 | C81: Jogos De Ps2 | D81: 2 | E81: aleatorio | F81: Fisica | G81: 1.4 | H81: =Table_246[[#This Row],[QT]]*Table_246[[#This Row],[Custo Un]] -> 2.8 | I81: 5 | J81: =I81*D81 -> 10 | K81: =I81*D81 -> 10 | L81: =Table_246[[#This Row],[Valor da venda]]-Table_246[[#This Row],[Valor gasto]] -> 7.2 | M81: =IFERROR(L81/K81, 0) -> 0.72 | N81: Transferido | O81: =IF([1]!Table_246[[#This Row],[Coluna2]]>0.5, "🔥 Excelente", IF([1]!Table_246[[#This Row],[Coluna2]]>0.4, "👍 Bom", "⚠️ Baixo")) -> 🔥 Excelente
A82: =IF(Table_246[[#This Row],[Data]]="","",MONTH(Table_246[[#This Row],[Data]])) -> 2 | B82: 46056 | C82: Pelicula 3D | D82: 1 | E82: aleatorio | F82: Fisica | G82: =IFERROR(VLOOKUP(C82,PROD!$A$2:$E$1204,5,0),"0") -> 3 | H82: =Table_246[[#This Row],[QT]]*Table_246[[#This Row],[Custo Un]] -> 3 | I82: 15 | J82: =I82*D82 -> 15 | K82: =I82*D82 -> 15 | L82: =Table_246[[#This Row],[Valor da venda]]-Table_246[[#This Row],[Valor gasto]] -> 12 | M82: =IFERROR(L82/K82, 0) -> 0.8 | N82: Transferido | O82: =IF([1]!Table_246[[#This Row],[Coluna2]]>0.5, "🔥 Excelente", IF([1]!Table_246[[#This Row],[Coluna2]]>0.4, "👍 Bom", "⚠️ Baixo")) -> 🔥 Excelente
A83: =IF(Table_246[[#This Row],[Data]]="","",MONTH(Table_246[[#This Row],[Data]])) -> 2 | B83: 46056 | C83: Desentupidor | D83: 1 | E83: 260203QVC1NHGG | F83: Shopee | G83: 12 | H83: =Table_246[[#This Row],[QT]]*Table_246[[#This Row],[Custo Un]] -> 12 | I83: 18.79 | J83: =I83*D83 -> 18.79 | K83: =I83*D83 -> 18.79 | L83: =Table_246[[#This Row],[Valor da venda]]-Table_246[[#This Row],[Valor gasto]] -> 6.79 | M83: =IFERROR(L83/K83, 0) -> 0.36136243 | N83: Transferido | O83: =IF([1]!Table_246[[#This Row],[Coluna2]]>0.5, "🔥 Excelente", IF([1]!Table_246[[#This Row],[Coluna2]]>0.4, "👍 Bom", "⚠️ Baixo")) -> ⚠️ Baixo
A84: =IF(Table_246[[#This Row],[Data]]="","",MONTH(Table_246[[#This Row],[Data]])) -> 2 | B84: 46056 | C84: Jogo Ps2 Shopee | D84: 1 | E84: 260203PK6Y0A25 | F84: Shopee | G84: =IFERROR(VLOOKUP(C84,PROD!$A$2:$E$1204,5,0),"0") -> 0.7 | H84: =Table_246[[#This Row],[QT]]*Table_246[[#This Row],[Custo Un]] -> 0.7 | I84: 7.02 | J84: =I84*D84 -> 7.02 | K84: =I84*D84 -> 7.02 | L84: =Table_246[[#This Row],[Valor da venda]]-Table_246[[#This Row],[Valor gasto]] -> 6.32 | M84: =IFERROR(L84/K84, 0) -> 0.9002849 | N84: Transferido | O84: =IF([1]!Table_246[[#This Row],[Coluna2]]>0.5, "🔥 Excelente", IF([1]!Table_246[[#This Row],[Coluna2]]>0.4, "👍 Bom", "⚠️ Baixo")) -> 🔥 Excelente
A85: =IF(Table_246[[#This Row],[Data]]="","",MONTH(Table_246[[#This Row],[Data]])) -> 2 | B85: 46056 | C85: Jogo Ps2 Shopee | D85: 1 | E85: 260203PRHGUC97 | F85: Shopee | G85: =IFERROR(VLOOKUP(C85,PROD!$A$2:$E$1204,5,0),"0") -> 0.7 | H85: =Table_246[[#This Row],[QT]]*Table_246[[#This Row],[Custo Un]] -> 0.7 | I85: 7.2 | J85: =I85*D85 -> 7.2 | K85: =I85*D85 -> 7.2 | L85: =Table_246[[#This Row],[Valor da venda]]-Table_246[[#This Row],[Valor gasto]] -> 6.5 | M85: =IFERROR(L85/K85, 0) -> 0.90277778 | N85: Transferido | O85: =IF([1]!Table_246[[#This Row],[Coluna2]]>0.5, "🔥 Excelente", IF([1]!Table_246[[#This Row],[Coluna2]]>0.4, "👍 Bom", "⚠️ Baixo")) -> 🔥 Excelente
A86: =IF(Table_246[[#This Row],[Data]]="","",MONTH(Table_246[[#This Row],[Data]])) -> 2 | B86: 46056 | C86: Cheirinho Para Carro | D86: 1 | E86: 260203Q3C34DNC | F86: Shopee | G86: =IFERROR(VLOOKUP(C86,PROD!$A$2:$E$1204,5,0),"0") -> 7.5 | H86: =Table_246[[#This Row],[QT]]*Table_246[[#This Row],[Custo Un]] -> 7.5 | I86: 14.99 | J86: =I86*D86 -> 14.99 | K86: =I86*D86 -> 14.99 | L86: =Table_246[[#This Row],[Valor da venda]]-Table_246[[#This Row],[Valor gasto]] -> 7.49 | M86: =IFERROR(L86/K86, 0) -> 0.49966644 | N86: Transferido | O86: =IF([1]!Table_246[[#This Row],[Coluna2]]>0.5, "🔥 Excelente", IF([1]!Table_246[[#This Row],[Coluna2]]>0.4, "👍 Bom", "⚠️ Baixo")) -> 👍 Bom
A87: =IF(Table_246[[#This Row],[Data]]="","",MONTH(Table_246[[#This Row],[Data]])) -> 2 | B87: 46056 | C87: Cheirinho Para Carro | D87: 1 | E87: 260203QJNTUWSC | F87: Shopee | G87: =IFERROR(VLOOKUP(C87,PROD!$A$2:$E$1204,5,0),"0") -> 7.5 | H87: =Table_246[[#This Row],[QT]]*Table_246[[#This Row],[Custo Un]] -> 7.5 | I87: 14.04 | J87: =I87*D87 -> 14.04 | K87: =I87*D87 -> 14.04 | L87: =Table_246[[#This Row],[Valor da venda]]-Table_246[[#This Row],[Valor gasto]] -> 6.54 | M87: =IFERROR(L87/K87, 0) -> 0.46581197 | N87: Transferido | O87: =IF([1]!Table_246[[#This Row],[Coluna2]]>0.5, "🔥 Excelente", IF([1]!Table_246[[#This Row],[Coluna2]]>0.4, "👍 Bom", "⚠️ Baixo")) -> 👍 Bom
A88: =IF(Table_246[[#This Row],[Data]]="","",MONTH(Table_246[[#This Row],[Data]])) -> 2 | B88: 46057 | C88: Cabo De Rede | D88: 1 | E88: aleatorio | F88: Fisica | G88: =IFERROR(VLOOKUP(C88,PROD!$A$2:$E$1204,5,0),"0") -> 0 | H88: =Table_246[[#This Row],[QT]]*Table_246[[#This Row],[Custo Un]] -> 0 | I88: 10 | J88: =I88*D88 -> 10 | K88: =I88*D88 -> 10 | L88: =Table_246[[#This Row],[Valor da venda]]-Table_246[[#This Row],[Valor gasto]] -> 10 | M88: =IFERROR(L88/K88, 0) -> 1 | N88: Transferido | O88: =IF([1]!Table_246[[#This Row],[Coluna2]]>0.5, "🔥 Excelente", IF([1]!Table_246[[#This Row],[Coluna2]]>0.4, "👍 Bom", "⚠️ Baixo")) -> 🔥 Excelente
A89: =IF(Table_246[[#This Row],[Data]]="","",MONTH(Table_246[[#This Row],[Data]])) -> 2 | B89: 46057 | C89: Desentupidor | D89: 1 | E89: 260205TXSABCRN | F89: Shopee | G89: 12.5 | H89: =Table_246[[#This Row],[QT]]*Table_246[[#This Row],[Custo Un]] -> 12.5 | I89: 18.79 | J89: =I89*D89 -> 18.79 | K89: =I89*D89 -> 18.79 | L89: =Table_246[[#This Row],[Valor da venda]]-Table_246[[#This Row],[Valor gasto]] -> 6.29 | M89: =IFERROR(L89/K89, 0) -> 0.33475253 | N89: Transferido | O89: =IF([1]!Table_246[[#This Row],[Coluna2]]>0.5, "🔥 Excelente", IF([1]!Table_246[[#This Row],[Coluna2]]>0.4, "👍 Bom", "⚠️ Baixo")) -> ⚠️ Baixo
A90: =IF(Table_246[[#This Row],[Data]]="","",MONTH(Table_246[[#This Row],[Data]])) -> 2 | B90: 46057 | C90: Jogo Ps2 Shopee | D90: 1 | E90: 260205TXVP1P5N | F90: Shopee | G90: =IFERROR(VLOOKUP(C90,PROD!$A$2:$E$1204,5,0),"0") -> 0.7 | H90: =Table_246[[#This Row],[QT]]*Table_246[[#This Row],[Custo Un]] -> 0.7 | I90: 7.02 | J90: =I90*D90 -> 7.02 | K90: =I90*D90 -> 7.02 | L90: =Table_246[[#This Row],[Valor da venda]]-Table_246[[#This Row],[Valor gasto]] -> 6.32 | M90: =IFERROR(L90/K90, 0) -> 0.9002849 | N90: Transferido | O90: =IF([1]!Table_246[[#This Row],[Coluna2]]>0.5, "🔥 Excelente", IF([1]!Table_246[[#This Row],[Coluna2]]>0.4, "👍 Bom", "⚠️ Baixo")) -> 🔥 Excelente
A91: =IF(Table_246[[#This Row],[Data]]="","",MONTH(Table_246[[#This Row],[Data]])) -> 2 | B91: 46057 | C91: Conversor Vga Para Hdmi | D91: 1 | E91: Clauberto | F91: Fisica | G91: 20 | H91: =Table_246[[#This Row],[QT]]*Table_246[[#This Row],[Custo Un]] -> 20 | I91: 30 | J91: =I91*D91 -> 30 | K91: =I91*D91 -> 30 | L91: =Table_246[[#This Row],[Valor da venda]]-Table_246[[#This Row],[Valor gasto]] -> 10 | M91: =IFERROR(L91/K91, 0) -> 0.33333333 | N91: Transferido | O91: =IF([1]!Table_246[[#This Row],[Coluna2]]>0.5, "🔥 Excelente", IF([1]!Table_246[[#This Row],[Coluna2]]>0.4, "👍 Bom", "⚠️ Baixo")) -> ⚠️ Baixo
A92: =IF(Table_246[[#This Row],[Data]]="","",MONTH(Table_246[[#This Row],[Data]])) -> 2 | B92: 46057 | C92: Cabo De Força - 3 Pinos | D92: 1 | E92: Clauberto | F92: Fisica | G92: 5 | H92: =Table_246[[#This Row],[QT]]*Table_246[[#This Row],[Custo Un]] -> 5 | I92: 10 | J92: =I92*D92 -> 10 | K92: =I92*D92 -> 10 | L92: =Table_246[[#This Row],[Valor da venda]]-Table_246[[#This Row],[Valor gasto]] -> 5 | M92: =IFERROR(L92/K92, 0) -> 0.5 | N92: Transferido | O92: =IF([1]!Table_246[[#This Row],[Coluna2]]>0.5, "🔥 Excelente", IF([1]!Table_246[[#This Row],[Coluna2]]>0.4, "👍 Bom", "⚠️ Baixo")) -> 👍 Bom
A93: =IF(Table_246[[#This Row],[Data]]="","",MONTH(Table_246[[#This Row],[Data]])) -> 2 | B93: 46057 | C93: Cabo Vga | D93: 1 | E93: Clauberto | F93: Fisica | G93: 5 | H93: =Table_246[[#This Row],[QT]]*Table_246[[#This Row],[Custo Un]] -> 5 | I93: 10 | J93: =I93*D93 -> 10 | K93: =I93*D93 -> 10 | L93: =Table_246[[#This Row],[Valor da venda]]-Table_246[[#This Row],[Valor gasto]] -> 5 | M93: =IFERROR(L93/K93, 0) -> 0.5 | N93: Transferido | O93: =IF([1]!Table_246[[#This Row],[Coluna2]]>0.5, "🔥 Excelente", IF([1]!Table_246[[#This Row],[Coluna2]]>0.4, "👍 Bom", "⚠️ Baixo")) -> 👍 Bom
A94: =IF(Table_246[[#This Row],[Data]]="","",MONTH(Table_246[[#This Row],[Data]])) -> 2 | B94: 46057 | C94: Jogo Ps2 Shopee | D94: 1 | E94: 260205UK2H546J | F94: Shopee | G94: =IFERROR(VLOOKUP(C94,PROD!$A$2:$E$1204,5,0),"0") -> 0.7 | H94: =Table_246[[#This Row],[QT]]*Table_246[[#This Row],[Custo Un]] -> 0.7 | I94: 7.02 | J94: =I94*D94 -> 7.02 | K94: =I94*D94 -> 7.02 | L94: =Table_246[[#This Row],[Valor da venda]]-Table_246[[#This Row],[Valor gasto]] -> 6.32 | M94: =IFERROR(L94/K94, 0) -> 0.9002849 | N94: Transferido | O94: =IF([1]!Table_246[[#This Row],[Coluna2]]>0.5, "🔥 Excelente", IF([1]!Table_246[[#This Row],[Coluna2]]>0.4, "👍 Bom", "⚠️ Baixo")) -> 🔥 Excelente
A95: =IF(Table_246[[#This Row],[Data]]="","",MONTH(Table_246[[#This Row],[Data]])) -> 2 | B95: 46058 | C95: Jogo Ps2 Shopee | D95: 1 | E95: 2602060TRY2SPR | F95: Shopee | G95: =IFERROR(VLOOKUP(C95,PROD!$A$2:$E$1204,5,0),"0") -> 0.7 | H95: =Table_246[[#This Row],[QT]]*Table_246[[#This Row],[Custo Un]] -> 0.7 | I95: 7.02 | J95: =I95*D95 -> 7.02 | K95: =I95*D95 -> 7.02 | L95: =Table_246[[#This Row],[Valor da venda]]-Table_246[[#This Row],[Valor gasto]] -> 6.32 | M95: =IFERROR(L95/K95, 0) -> 0.9002849 | N95: Transferido | O95: =IF([1]!Table_246[[#This Row],[Coluna2]]>0.5, "🔥 Excelente", IF([1]!Table_246[[#This Row],[Coluna2]]>0.4, "👍 Bom", "⚠️ Baixo")) -> 🔥 Excelente
A96: =IF(Table_246[[#This Row],[Data]]="","",MONTH(Table_246[[#This Row],[Data]])) -> 2 | B96: 46059 | C96: Jogo Ps2 Shopee | D96: 1 | E96: 26020619R29YC5 | F96: Shopee | G96: =IFERROR(VLOOKUP(C96,PROD!$A$2:$E$1204,5,0),"0") -> 0.7 | H96: =Table_246[[#This Row],[QT]]*Table_246[[#This Row],[Custo Un]] -> 0.7 | I96: 7.02 | J96: =I96*D96 -> 7.02 | K96: =I96*D96 -> 7.02 | L96: =Table_246[[#This Row],[Valor da venda]]-Table_246[[#This Row],[Valor gasto]] -> 6.32 | M96: =IFERROR(L96/K96, 0) -> 0.9002849 | N96: Transferido | O96: =IF([1]!Table_246[[#This Row],[Coluna2]]>0.5, "🔥 Excelente", IF([1]!Table_246[[#This Row],[Coluna2]]>0.4, "👍 Bom", "⚠️ Baixo")) -> 🔥 Excelente
A97: =IF(Table_246[[#This Row],[Data]]="","",MONTH(Table_246[[#This Row],[Data]])) -> 2 | B97: 46059 | C97: Jogo Ps2 Shopee | D97: 1 | E97: 2602061AFHRWQS | F97: Shopee | G97: =IFERROR(VLOOKUP(C97,PROD!$A$2:$E$1204,5,0),"0") -> 0.7 | H97: =Table_246[[#This Row],[QT]]*Table_246[[#This Row],[Custo Un]] -> 0.7 | I97: 7.02 | J97: =I97*D97 -> 7.02 | K97: =I97*D97 -> 7.02 | L97: =Table_246[[#This Row],[Valor da venda]]-Table_246[[#This Row],[Valor gasto]] -> 6.32 | M97: =IFERROR(L97/K97, 0) -> 0.9002849 | N97: Transferido | O97: =IF([1]!Table_246[[#This Row],[Coluna2]]>0.5, "🔥 Excelente", IF([1]!Table_246[[#This Row],[Coluna2]]>0.4, "👍 Bom", "⚠️ Baixo")) -> 🔥 Excelente
A98: =IF(Table_246[[#This Row],[Data]]="","",MONTH(Table_246[[#This Row],[Data]])) -> 2 | B98: 46059 | C98: Carregador lehmox tipo c | D98: 1 | E98: aleatorio | F98: Fisica | G98: 11 | H98: =Table_246[[#This Row],[QT]]*Table_246[[#This Row],[Custo Un]] -> 11 | I98: 35 | J98: =I98*D98 -> 35 | K98: =I98*D98 -> 35 | L98: =Table_246[[#This Row],[Valor da venda]]-Table_246[[#This Row],[Valor gasto]] -> 24 | M98: =IFERROR(L98/K98, 0) -> 0.68571429 | N98: Transferido | O98: =IF([1]!Table_246[[#This Row],[Coluna2]]>0.5, "🔥 Excelente", IF([1]!Table_246[[#This Row],[Coluna2]]>0.4, "👍 Bom", "⚠️ Baixo")) -> 🔥 Excelente
A99: =IF(Table_246[[#This Row],[Data]]="","",MONTH(Table_246[[#This Row],[Data]])) -> 2 | B99: 46059 | C99: Lanterna | D99: 1 | E99: aleatorio | F99: Fisica | G99: =IFERROR(VLOOKUP(C99,PROD!$A$2:$E$1204,5,0),"0") -> 0 | H99: =Table_246[[#This Row],[QT]]*Table_246[[#This Row],[Custo Un]] -> 0 | I99: 10 | J99: =I99*D99 -> 10 | K99: =I99*D99 -> 10 | L99: =Table_246[[#This Row],[Valor da venda]]-Table_246[[#This Row],[Valor gasto]] -> 10 | M99: =IFERROR(L99/K99, 0) -> 1 | N99: Transferido | O99: =IF([1]!Table_246[[#This Row],[Coluna2]]>0.5, "🔥 Excelente", IF([1]!Table_246[[#This Row],[Coluna2]]>0.4, "👍 Bom", "⚠️ Baixo")) -> 🔥 Excelente
A100: =IF(Table_246[[#This Row],[Data]]="","",MONTH(Table_246[[#This Row],[Data]])) -> 2 | B100: 46061 | C100: adaptador hdmi ps2 | D100: 1 | E100: aleatorio | F100: Fisica | G100: 20 | H100: =Table_246[[#This Row],[QT]]*Table_246[[#This Row],[Custo Un]] -> 20 | I100: 45 | J100: =I100*D100 -> 45 | K100: =I100*D100 -> 45 | L100: =Table_246[[#This Row],[Valor da venda]]-Table_246[[#This Row],[Valor gasto]] -> 25 | M100: =IFERROR(L100/K100, 0) -> 0.55555556 | N100: Transferido | O100: =IF([1]!Table_246[[#This Row],[Coluna2]]>0.5, "🔥 Excelente", IF([1]!Table_246[[#This Row],[Coluna2]]>0.4, "👍 Bom", "⚠️ Baixo")) -> 🔥 Excelente
...

Sheet PROD
A1: Produtos | B1: Compras | C1: Estoque | D1: Vendas | E1: valor | G1: MARCA | H1: MODELO | I1: Q
A2: Adaptador Bluetooth | B2: 1 | C2: =B2-D2 -> 1 | D2: =COUNTIF(Table_246[Produto],Table_1[[#This Row],[Produtos]]) -> 0 | E2: 5 | G2: IPHONE | H2: Iphone 14 PRO MAX | I2: 1
A3: Adaptador Ios P2 | B3: 1 | C3: =B3-D3 -> 1 | D3: =COUNTIF(Table_246[Produto],Table_1[[#This Row],[Produtos]]) -> 0 | E3: 5.9 | G3: IPHONE | H3: Iphone 15 | I3: 1
A4: Adaptador Micro Sd | B4: 1 | C4: =B4-D4 -> 1 | D4: =COUNTIF(Table_246[Produto],Table_1[[#This Row],[Produtos]]) -> 0 | E4: 3.5 | G4: IPHONE | H4: Iphone 15 PRO MAX | I4: 1
A5: Adaptador P2 - P10 | B5: 1 | C5: =B5-D5 -> 1 | D5: =COUNTIF(Table_246[Produto],Table_1[[#This Row],[Produtos]]) -> 0 | E5: 5 | G5: MOTOROLA | H5: G14 | I5: 2
A6: Adaptador P2 Tipo C | B6: 1 | C6: =B6-D6 -> 1 | D6: =COUNTIF(Table_246[Produto],Table_1[[#This Row],[Produtos]]) -> 0 | E6: 8 | G6: MOTOROLA | H6: MOTO edge 30 neo | I6: 2
A7: Adaptador P3X2 - P2 | B7: 1 | C7: =B7-D7 -> 1 | D7: =COUNTIF(Table_246[Produto],Table_1[[#This Row],[Produtos]]) -> 0 | E7: 5 | G7: MOTOROLA | H7: MOTO G30 | I7: 2
A8: Adaptador Rede - Usb | B8: 2 | C8: =B8-D8 -> 2 | D8: =COUNTIF(Table_246[Produto],Table_1[[#This Row],[Produtos]]) -> 0 | G8: SAMSUNG | H8: A10s | I8: 1
A9: Adaptador T | B9: 1 | C9: =B9-D9 -> 1 | D9: =COUNTIF(Table_246[Produto],Table_1[[#This Row],[Produtos]]) -> 0 | E9: 1.5 | G9: SAMSUNG | H9: A22 5g | I9: 3
A10: Adaptador Tipo C Para Usb | B10: 1 | C10: =B10-D10 -> 1 | D10: =COUNTIF(Table_246[Produto],Table_1[[#This Row],[Produtos]]) -> 0 | E10: 3.5 | G10: SAMSUNG | H10: m53 | I10: 1
A11: Adaptador Tomada 2 Entrada | B11: 1 | C11: =B11-D11 -> 1 | D11: =COUNTIF(Table_246[Produto],Table_1[[#This Row],[Produtos]]) -> 0 | E11: 9.9 | G11: XIAOMI | H11: mi 9a | I11: 1
A12: Adaptador V8 - Iphone | B12: 1 | C12: =B12-D12 -> 1 | D12: =COUNTIF(Table_246[Produto],Table_1[[#This Row],[Produtos]]) -> 0 | E12: 3.5 | G12: XIAOMI | H12: Note 10 | I12: 2
A13: Adaptador Vga Para Hdmi | B13: 1 | C13: =B13-D13 -> 1 | D13: =COUNTIF(Table_246[Produto],Table_1[[#This Row],[Produtos]]) -> 0 | E13: 15 | G13: XIAOMI | H13: Note 10 4g | I13: 3
A14: Adaptador Wifi 2.5G | B14: 1 | C14: =B14-D14 -> 1 | D14: =COUNTIF(Table_246[Produto],Table_1[[#This Row],[Produtos]]) -> 0 | E14: 11 | G14: XIAOMI | H14: Note 12s | I14: 1
A15: Adaptador Wifi 2.5G Antena | B15: 1 | C15: =B15-D15 -> 1 | D15: =COUNTIF(Table_246[Produto],Table_1[[#This Row],[Produtos]]) -> 0 | E15: 12 | G15: XIAOMI | H15: pc x3 | I15: 2
A16: Adaptador Wifi 2.5G Antena Ms | B16: 1 | C16: =B16-D16 -> 1 | D16: =COUNTIF(Table_246[Produto],Table_1[[#This Row],[Produtos]]) -> 0 | E16: 9 | G16: XIAOMI | H16: REDMI 12 | I16: 2
A17: Adaptador Wifi 6 | B17: 1 | C17: =B17-D17 -> 1 | D17: =COUNTIF(Table_246[Produto],Table_1[[#This Row],[Produtos]]) -> 0 | E17: 17.18 | G17: XIAOMI | H17: REDMI 12c | I17: 1
A18: Alicate Universal 8 Id-4762A | B18: 1 | C18: =B18-D18 -> 1 | D18: =COUNTIF(Table_246[Produto],Table_1[[#This Row],[Produtos]]) -> 0 | E18: 11 | G18: XIAOMI | H18: REDMI 12 pro 5g | I18: 1
A19: Arma De Hidrogel Ar15 | B19: 1 | C19: =B19-D19 -> 1 | D19: =COUNTIF(Table_246[Produto],Table_1[[#This Row],[Produtos]]) -> 0 | E19: 35 | G19: XIAOMI | H19: REDMI 13c | I19: 2
A20: Arminha De Agua | B20: 99 | C20: =B20-D20 -> 98 | D20: =COUNTIF(Table_246[Produto],Table_1[[#This Row],[Produtos]]) -> 1 | G20: MARCA | H20: MODELO | I20: Q
A21: Balança 10Kg | B21: 1 | C21: =B21-D21 -> 1 | D21: =COUNTIF(Table_246[Produto],Table_1[[#This Row],[Produtos]]) -> 0 | E21: 14 | G21: Privacidade
A22: Balança De Precisão Xm-50522 | B22: 1 | C22: =B22-D22 -> 1 | D22: =COUNTIF(Table_246[Produto],Table_1[[#This Row],[Produtos]]) -> 0 | E22: 16 | G22: IPHONE | H22: 7 / 8 PLUS | I22: 3
A23: Baralho C 2 Jogos Bar-69087 | B23: 1 | C23: =B23-D23 -> 1 | D23: =COUNTIF(Table_246[Produto],Table_1[[#This Row],[Produtos]]) -> 0 | E23: 1 | G23: IPHONE | H23: XR / 11 | I23: 2
A24: Bateria 23A | B24: 1 | C24: =B24-D24 -> 1 | D24: =COUNTIF(Table_246[Produto],Table_1[[#This Row],[Produtos]]) -> 0 | E24: =7.5/5 -> 1.5 | G24: IPHONE | H24: 12 | I24: 1
A25: Bateria 9V | B25: 1 | C25: =B25-D25 -> 1 | D25: =COUNTIF(Table_246[Produto],Table_1[[#This Row],[Produtos]]) -> 0 | E25: 4
A26: Bleybleyd | B26: 99 | C26: =B26-D26 -> 98 | D26: =COUNTIF(Table_246[Produto],Table_1[[#This Row],[Produtos]]) -> 1
A27: Bobbie Goods Caderno | B27: 1 | C27: =B27-D27 -> 1 | D27: =COUNTIF(Table_246[Produto],Table_1[[#This Row],[Produtos]]) -> 0 | E27: 13
A28: Bobbie Goods Card | B28: 1 | C28: =B28-D28 -> 1 | D28: =COUNTIF(Table_246[Produto],Table_1[[#This Row],[Produtos]]) -> 0 | E28: 2.5
A29: Bolinha De Gel | B29: 99 | C29: =B29-D29 -> 98 | D29: =COUNTIF(Table_246[Produto],Table_1[[#This Row],[Produtos]]) -> 1
A30: Boneco Lego | B30: 1 | C30: =B30-D30 -> 1 | D30: =COUNTIF(Table_246[Produto],Table_1[[#This Row],[Produtos]]) -> 0 | E30: 15
A31: Boneco Lego Kit | B31: 99 | C31: =B31-D31 -> 97 | D31: =COUNTIF(Table_246[Produto],Table_1[[#This Row],[Produtos]]) -> 2
A32: Brinquedo Arminha | B32: 99 | C32: =B32-D32 -> 98 | D32: =COUNTIF(Table_246[Produto],Table_1[[#This Row],[Produtos]]) -> 1
A33: Cabeça Carregador 3.1A Ka-5601 | B33: 1 | C33: =B33-D33 -> 1 | D33: =COUNTIF(Table_246[Produto],Table_1[[#This Row],[Produtos]]) -> 0 | E33: 6
A34: Cabo Auxiliar P2 H'Maston | B34: 1 | C34: =B34-D34 -> 1 | D34: =COUNTIF(Table_246[Produto],Table_1[[#This Row],[Produtos]]) -> 0 | E34: 3.5
A35: Cabo Auxiliar P2 Kingo | B35: 1 | C35: =B35-D35 -> 1 | D35: =COUNTIF(Table_246[Produto],Table_1[[#This Row],[Produtos]]) -> 0 | E35: 7
A36: Cabo Auxiliar P2 Le-804 | B36: 1 | C36: =B36-D36 -> 1 | D36: =COUNTIF(Table_246[Produto],Table_1[[#This Row],[Produtos]]) -> 0 | E36: 2.5
A37: Cabo Colorido | B37: 99 | C37: =B37-D37 -> 98 | D37: =COUNTIF(Table_246[Produto],Table_1[[#This Row],[Produtos]]) -> 1
A38: Cabo De Dados Tc Kapbom Kap 1Mtc | B38: 1 | C38: =B38-D38 -> 1 | D38: =COUNTIF(Table_246[Produto],Table_1[[#This Row],[Produtos]]) -> 0 | E38: 3.5
A39: Cabo De Dados V8 Kapbom Kap 1Mv8 | B39: 1 | C39: =B39-D39 -> 1 | D39: =COUNTIF(Table_246[Produto],Table_1[[#This Row],[Produtos]]) -> 0 | E39: 3.5
A40: Cabo De Força - 2 Pinos | B40: 1 | C40: =B40-D40 -> 1 | D40: =COUNTIF(Table_246[Produto],Table_1[[#This Row],[Produtos]]) -> 0
A41: Cabo De Força - 3 Pinos | B41: 3 | C41: =B41-D41 -> 0 | D41: =COUNTIF(Table_246[Produto],Table_1[[#This Row],[Produtos]]) -> 3 | E41: 6
A42: Cabo De Força - Pc | B42: 1 | C42: =B42-D42 -> 1 | D42: =COUNTIF(Table_246[Produto],Table_1[[#This Row],[Produtos]]) -> 0 | E42: 6
A43: Cabo De Rede | B43: 99 | C43: =B43-D43 -> 98 | D43: =COUNTIF(Table_246[Produto],Table_1[[#This Row],[Produtos]]) -> 1
A44: Cabo Displayport | B44: 1 | C44: =B44-D44 -> 1 | D44: =COUNTIF(Table_246[Produto],Table_1[[#This Row],[Produtos]]) -> 0 | E44: 10
A45: Cabo Hdmi 1,8/2M | B45: 1 | C45: =B45-D45 -> 1 | D45: =COUNTIF(Table_246[Produto],Table_1[[#This Row],[Produtos]]) -> 0 | E45: 6
A46: Cabo Hdmi 2M | B46: 1 | C46: =B46-D46 -> 1 | D46: =COUNTIF(Table_246[Produto],Table_1[[#This Row],[Produtos]]) -> 0 | E46: 6
A47: Cabo Hdmi 3M Multilaser | B47: 1 | C47: =B47-D47 -> 1 | D47: =COUNTIF(Table_246[Produto],Table_1[[#This Row],[Produtos]]) -> 0 | E47: 0
A48: Cabo Hdmi 4M | B48: 1 | C48: =B48-D48 -> 1 | D48: =COUNTIF(Table_246[Produto],Table_1[[#This Row],[Produtos]]) -> 0 | E48: 15
A49: Cabo Hmaster Tpc 4.8A | B49: 1 | C49: =B49-D49 -> 1 | D49: =COUNTIF(Table_246[Produto],Table_1[[#This Row],[Produtos]]) -> 0 | E49: 4
A50: Cabo H'Maston Hb01-1 | B50: 1 | C50: =B50-D50 -> 1 | D50: =COUNTIF(Table_246[Produto],Table_1[[#This Row],[Produtos]]) -> 0 | E50: 4.5
A51: Cabo Inova Tc Cbo-12223 | B51: 1 | C51: =B51-D51 -> 1 | D51: =COUNTIF(Table_246[Produto],Table_1[[#This Row],[Produtos]]) -> 0 | E51: 6
A52: Cabo Iphone 20W | B52: 3 | C52: =B52-D52 -> 1 | D52: =COUNTIF(Table_246[Produto],Table_1[[#This Row],[Produtos]]) -> 2 | E52: 6
A53: Cabo Iphone Caixa Branca | B53: 1 | C53: =B53-D53 -> 1 | D53: =COUNTIF(Table_246[Produto],Table_1[[#This Row],[Produtos]]) -> 0 | E53: 15
A54: Cabo Iphone Hb10-2 Iphone | B54: 1 | C54: =B54-D54 -> 1 | D54: =COUNTIF(Table_246[Produto],Table_1[[#This Row],[Produtos]]) -> 0 | E54: 5
A55: Cabo Iphone Hb10-3 Tipo C | B55: 1 | C55: =B55-D55 -> 1 | D55: =COUNTIF(Table_246[Produto],Table_1[[#This Row],[Produtos]]) -> 0 | E55: 5
... A72: Cabos Variados Saco Branco | B72: 1 | C72: =B72-D72 -> 1 | D72: =COUNTIF(Table_246[Produto],Table_1[[#This Row],[Produtos]]) -> 0 | E72: 5
A73: Caixa De Som Pc | B73: 99 | C73: =B73-D73 -> 98 | D73: =COUNTIF(Table_246[Produto],Table_1[[#This Row],[Produtos]]) -> 1
A74: Calculadora 12 Dígitos Crs8585 | B74: 1 | C74: =B74-D74 -> 1 | D74: =COUNTIF(Table_246[Produto],Table_1[[#This Row],[Produtos]]) -> 0 | E74: 23
A75: Calculadora Pequena | B75: 1 | C75: =B75-D75 -> 1 | D75: =COUNTIF(Table_246[Produto],Table_1[[#This Row],[Produtos]]) -> 0 | E75: 2.7
A76: Camera Ip Dupla | B76: 1 | C76: =B76-D76 -> 1 | D76: =COUNTIF(Table_246[Produto],Table_1[[#This Row],[Produtos]]) -> 0 | E76: =210.35/2 -> 105.175
A77: Caneta Depiladora | B77: 1 | C77: =B77-D77 -> 1 | D77: =COUNTIF(Table_246[Produto],Table_1[[#This Row],[Produtos]]) -> 0 | E77: 12.5
A78: Canivete Automático Knife | B78: 1 | C78: =B78-D78 -> 1 | D78: =COUNTIF(Table_246[Produto],Table_1[[#This Row],[Produtos]]) -> 0 | E78: 9
A79: Capa A Prova D'Água | B79: 1 | C79: =B79-D79 -> 1 | D79: =COUNTIF(Table_246[Produto],Table_1[[#This Row],[Produtos]]) -> 0 | E79: 3.5
A80: Capa Celular Simples | B80: 1 | C80: =B80-D80 -> 1 | D80: =COUNTIF(Table_246[Produto],Table_1[[#This Row],[Produtos]]) -> 0 | E80: 2
A81: Capa De Chuva | B81: 1 | C81: =B81-D81 -> 1 | D81: =COUNTIF(Table_246[Produto],Table_1[[#This Row],[Produtos]]) -> 0 | E81: 7
A82: Capinha | B82: 1 | C82: =B82-D82 -> 1 | D82: =COUNTIF(Table_246[Produto],Table_1[[#This Row],[Produtos]]) -> 0 | E82: 3
A83: Capinha Iphone | B83: 99 | C83: =B83-D83 -> 98 | D83: =COUNTIF(Table_246[Produto],Table_1[[#This Row],[Produtos]]) -> 1
A84: Capinha Simples | B84: 99 | C84: =B84-D84 -> 98 | D84: =COUNTIF(Table_246[Produto],Table_1[[#This Row],[Produtos]]) -> 1
A85: Card | B85: 1 | C85: =B85-D85 -> 1 | D85: =COUNTIF(Table_246[Produto],Table_1[[#This Row],[Produtos]]) -> 0 | E85: 0.4
A86: Card Caixa 50 | B86: 1 | C86: =B86-D86 -> 1 | D86: =COUNTIF(Table_246[Produto],Table_1[[#This Row],[Produtos]]) -> 0 | E86: 5
A87: Carregador Cabeça Spartan - Cw-178 | B87: 1 | C87: =B87-D87 -> 1 | D87: =COUNTIF(Table_246[Produto],Table_1[[#This Row],[Produtos]]) -> 0 | E87: 12
A88: Carregador Cabeça 20W | B88: 1 | C88: =B88-D88 -> 1 | D88: =COUNTIF(Table_246[Produto],Table_1[[#This Row],[Produtos]]) -> 0 | E88: 11
A89: Carregador Completo Iphone 20W | B89: 99 | C89: =B89-D89 -> 96 | D89: =COUNTIF(Table_246[Produto],Table_1[[#This Row],[Produtos]]) -> 3 | E89: 15
A90: Carregador Completo Lehmox Tipo C | B90: 1 | C90: =B90-D90 -> 1 | D90: =COUNTIF(Table_246[Produto],Table_1[[#This Row],[Produtos]]) -> 0 | E90: 11
A91: Carregador Completo Lehmox v8 | B91: 1 | C91: =B91-D91 -> 1 | D91: =COUNTIF(Table_246[Produto],Table_1[[#This Row],[Produtos]]) -> 0 | E91: 11
A92: Carregador Completo Lehmox iphone | B92: 1 | C92: =B92-D92 -> 1 | D92: =COUNTIF(Table_246[Produto],Table_1[[#This Row],[Produtos]]) -> 0 | E92: 11
A93: Jogos De Ps2 | B93: 999 | C93: =B93-D93 -> 990 | D93: =COUNTIF(Table_246[Produto],Table_1[[#This Row],[Produtos]]) -> 9 | E93: 0.7
A94: Jogo Ps2 tiktok | B94: 999 | C94: =B94-D94 -> 964 | D94: =COUNTIF(Table_246[Produto],Table_1[[#This Row],[Produtos]]) -> 35 | E94: 0.7
A95: Carregador Lehmox 5.1 Le-82 | B95: 1 | C95: =B95-D95 -> 1 | D95: =COUNTIF(Table_246[Produto],Table_1[[#This Row],[Produtos]]) -> 0 | E95: 10
A96: Carregador Spartan V8 Leo | B96: 1 | C96: =B96-D96 -> 1 | D96: =COUNTIF(Table_246[Produto],Table_1[[#This Row],[Produtos]]) -> 0 | E96: 10
... A108: Cartão De Memoria 32Gb | B108: 1 | C108: =B108-D108 -> 1 | D108: =COUNTIF(Table_246[Produto],Table_1[[#This Row],[Produtos]]) -> 0 | E108: 23.5
A109: Cartao Micro Sd 16Gb | B109: 99 | C109: =B109-D109 -> 97 | D109: =COUNTIF(Table_246[Produto],Table_1[[#This Row],[Produtos]]) -> 2
A110: Carteira Pequena | B110: 1 | C110: =B110-D110 -> 1 | D110: =COUNTIF(Table_246[Produto],Table_1[[#This Row],[Produtos]]) -> 0 | E110: 2.5
A111: Cartinha | B111: 1 | C111: =B111-D111 -> 1 | D111: =COUNTIF(Table_246[Produto],Table_1[[#This Row],[Produtos]]) -> 0 | E111: 1
A112: Cascata Led - Fios De Fada | B112: 1 | C112: =B112-D112 -> 1 | D112: =COUNTIF(Table_246[Produto],Table_1[[#This Row],[Produtos]]) -> 0 | E112: 12.88
A113: Case 2.5 Hd | B113: 99 | C113: =B113-D113 -> 98 | D113: =COUNTIF(Table_246[Produto],Table_1[[#This Row],[Produtos]]) -> 1
A114: Chave Allen - Canivete Ls-A08 | B114: 1 | C114: =B114-D114 -> 1 | D114: =COUNTIF(Table_246[Produto],Table_1[[#This Row],[Produtos]]) -> 0 | E114: 13
A115: Chave Para Bicicleta | B115: 1 | C115: =B115-D115 -> 1 | D115: =COUNTIF(Table_246[Produto],Table_1[[#This Row],[Produtos]]) -> 0 | E115: 3.5
A116: Chave Tork 8Pçs Lst08 | B116: 1 | C116: =B116-D116 -> 1 | D116: =COUNTIF(Table_246[Produto],Table_1[[#This Row],[Produtos]]) -> 0 | E116: 11.5
A117: Chaveiro | B117: 99 | C117: =B117-D117 -> 98 | D117: =COUNTIF(Table_246[Produto],Table_1[[#This Row],[Produtos]]) -> 1
A118: Cheirinho | B118: 99 | C118: =B118-D118 -> 98 | D118: =COUNTIF(Table_246[Produto],Table_1[[#This Row],[Produtos]]) -> 1
A119: Cheirinho Para Carro | B119: 7 | C119: =B119-D119 -> -14 | D119: =COUNTIF(Table_246[Produto],Table_1[[#This Row],[Produtos]]) -> 21 | E119: 7.5
A120: Chip Normal | B120: 1 | C120: =B120-D120 -> 1 | D120: =COUNTIF(Table_246[Produto],Table_1[[#This Row],[Produtos]]) -> 0 | E120: 10
A121: Chip Recarregado | B121: 1 | C121: =B121-D121 -> 1 | D121: =COUNTIF(Table_246[Produto],Table_1[[#This Row],[Produtos]]) -> 0 | E121: 17
A122: Chip Sem Recarga | B122: 99 | C122: =B122-D122 -> 97 | D122: =COUNTIF(Table_246[Produto],Table_1[[#This Row],[Produtos]]) -> 2
A123: Coleção_4_Jogos_Ben_10_Ps2 | B123: 99 | C123: =B123-D123 -> 98 | D123: =COUNTIF(Table_246[Produto],Table_1[[#This Row],[Produtos]]) -> 1
A124: Computadores | B124: 1 | C124: =B124-D124 -> 1 | D124: =COUNTIF(Table_246[Produto],Table_1[[#This Row],[Produtos]]) -> 0
A125: Conjunto De Chaves Allen 9Pçs Ls-4113 | B125: 1 | C125: =B125-D125 -> 1 | D125: =COUNTIF(Table_246[Produto],Table_1[[#This Row],[Produtos]]) -> 0 | E125: 15
A126: Controle Gamepad Com-7436 | B126: 1 | C126: =B126-D126 -> 1 | D126: =COUNTIF(Table_246[Produto],Table_1[[#This Row],[Produtos]]) -> 0 | E126: 17
A127: Controle Gamer Celular Ly84358 | B127: 1 | C127: =B127-D127 -> 1 | D127: =COUNTIF(Table_246[Produto],Table_1[[#This Row],[Produtos]]) -> 0 | E127: 15
...

Sheet Nota Fiscal
B3: ZM Store | G3: Número | H3: 385 | O3: ZM Store | T3: Número | U3: =H3 -> 385
B5: Endereço | C5: Feicenter box 64 Samambaia N | G5: Data | H5: =TODAY() -> 46216 | O5: Endereço | P5: Feicenter box 64 Samambaia N | T5: Data | U5: =TODAY() -> 46216
B6: Telefone | C6: (61) 98182-0906 | O6: Telefone | P6: (61) 98182-0906
B9: FICHA DE PEDIDO | O9: FICHA DE PEDIDO
B11: Cliente: | O11: Cliente: | P11: =C11 -> 0
B12: Telefone: | C12: 61 9368-7737 | O12: Telefone: | P12: =C12 -> 61 9368-7737
B13: E-mail: | O13: E-mail: | P13: =C13 -> 0
B14: Endereço: | O14: Endereço: | P14: =C14 -> 0
B15: Cidade: | C15: Brasília | E15: CEP: | H15: Vendedor: | I15: Leonardo Coutinho | O15: Cidade: | P15: =C15 -> Brasília | R15: CEP: | S15: =F15 -> 0 | U15: Vendedor: | V15: =I15 -> Leonardo Coutinho
B18: Qtde | C18: Descrição | J18: Valor | K18: Total | O18: Qtde | P18: Descrição | W18: Valor | X18: Total
B19: 1 | C19: Formatação | J19: 70 | K19: =J19*B19 -> 70 | O19: =B19 -> 1 | P19: =C19 -> Formatação | W19: =J19 -> 70 | X19: =K19 -> 70
K20: =J20*B20 -> 0 | O20: =B20 -> 0 | P20: =C20 -> 0 | W20: =J20 -> 0 | X20: =K20 -> 0
K21: =J21*B21 -> 0 | O21: =B21 -> 0 | P21: =C21 -> 0 | W21: =J21 -> 0 | X21: =K21 -> 0
K22: =J22*B22 -> 0 | O22: =B22 -> 0 | P22: =C22 -> 0 | W22: =J22 -> 0 | X22: =K22 -> 0
K23: =J23*B23 -> 0 | O23: =B23 -> 0 | P23: =C23 -> 0 | W23: =J23 -> 0 | X23: =K23 -> 0
K24: =J24*B24 -> 0 | O24: =B24 -> 0 | P24: =C24 -> 0 | W24: =J24 -> 0 | X24: =K24 -> 0
K25: =J25*B25 -> 0 | O25: =B25 -> 0 | P25: =C25 -> 0 | W25: =J25 -> 0 | X25: =K25 -> 0
K26: =J26*B26 -> 0 | O26: =B26 -> 0 | P26: =C26 -> 0 | W26: =J26 -> 0 | X26: =K26 -> 0
K27: =J27*B27 -> 0 | O27: =B27 -> 0 | P27: =C27 -> 0 | W27: =J27 -> 0 | X27: =K27 -> 0
K28: =J28*B28 -> 0 | O28: =B28 -> 0 | P28: =C28 -> 0 | W28: =J28 -> 0 | X28: =K28 -> 0
K29: =J29*B29 -> 0 | O29: =B29 -> 0 | P29: =C29 -> 0 | W29: =J29 -> 0 | X29: =K29 -> 0
K30: =J30*B30 -> 0 | O30: =B30 -> 0 | P30: =C30 -> 0 | W30: =J30 -> 0 | X30: =K30 -> 0
K31: =J31*B31 -> 0 | O31: =B31 -> 0 | P31: =C31 -> 0 | W31: =J31 -> 0 | X31: =K31 -> 0
... K33: =J33*B33 -> 0 | O33: =B33 -> 0 | P33: =C33 -> 0 | W33: =J33 -> 0 | X33: =K33 -> 0
K34: =J34*B34 -> 0 | O34: =B34 -> 0 | P34: =C37 -> 0 | W34: =J34 -> 0 | X34: =K34 -> 0
K35: =J35*B35 -> 0 | O35: =B35 -> 0 | P35: =C35 -> 0 | W35: =J35 -> 0 | X35: =K35 -> 0
K36: =J36*B36 -> 0 | O36: =B36 -> 0 | P36: =C36 -> 0 | W36: =J36 -> 0 | X36: =K36 -> 0
B37: Observação do serviço: | O37: Observação do serviço:
B38: Notebook Samsung RV415, com fonte, formatação simples. | O38: =B38 -> Notebook Samsung RV415, com fonte, formatação simples.
B43: Produtos deixados a mais de 90 dias seram vendidos !! | O43: Produtos deixados a mais de 90 dias seram vendidos !!
B46: Observação | I46: Valor Total | J46: =SUM(K19:K41) -> 70 | O46: Observação | P46: =C46 -> 0 | V46: Valor Total | W46: =SUM(X19:X41) -> 70
I47: Desconto | V47: Desconto | W47: =J47 -> 0
B48: Garantia | C48: 30 dias | E48: Data final | F48: =H5+30 -> 46246 | I48: Valor final | J48: =J46-J47 -> 70 | O48: Garantia | P48: 30 dias | R48: Data final | S48: =U5+30 -> 46246 | V48: Valor final | W48: =W46-W47 -> 70

Sheet Devedores
A1: Vendas CNPJ 2024 | I1: Contas a pagar 03 | N1: Divida | S1: Total dividas | W1: Divida higor | AB1: Produtos | AC1: Compras | AD1: Estoque
A2: Meses | B2: Meses | C2: Vendas Shopee | D2: Presencial | E2: Infinite | F2: Picpay | G2: Magalu | I2: Nome | J2: Nome | K2: dt | N2: Remédio | O2: 10x | P2: 50 | S2: Banco | T2: Valor sem desconto | U2: Valor com desconto | W2: Total divida | X2: =600 -> 600 | AB2: Adaptador IOS p2 | AC2: 1 | AD2: =AC2-AE2 -> 1
A3: 1 | B3: Janeiro | C3: 1528.12 | D3: 120 | E3: 0 | I3: Aluguel | J3: 600 | K3: 10 | N3: Pago | O3: =70+20+50 -> 140 | P3: 500 | S3: Itaú | T3: 537.49 | U3: 227.95 | W3: Falta pagar | X3: =X2-X13 -> 390 | AB3: Adaptador MICRO SD | AC3: 2 | AD3: =AC3-AE3 -> 2
A4: 2 | B4: Fevereiro | C4: 1018.94 | D4: 0 | E4: 0 | I4: NET1 | J4: 100 | K4: 10 | S4: Empresa MP | T4: 394.89 | U4: 177.71 | W4: ------------------- | X4: ------------ | AB4: Adaptador p2 - p10 | AC4: 1 | AD4: =AC4-AE4 -> 1
A5: 3 | B5: Março | C5: 300.48 | D5: 0 | E5: 50 | I5: Mae | J5: 100 | K5: 10 | N5: Total | O5: =O3-500 -> -360 | S5: Cartão MP | T5: 7046.09 | U5: 3107.47 | W5: Produtos pego | AB5: Adaptador p2 tipo c | AC5: 2 | AD5: =AC5-AE5 -> 2
A6: 4 | B6: Abril | C6: 481.53 | D6: 350 | E6: =SUM(2500+30+55+40+65+1805) -> 4495 | I6: CARTAO | J6: 545.16 | K6: 15 | S6: 99 | T6: 11194.34 | U6: 11194.34 | W6: Cadeado com Alarme | X6: 65 | AB6: Adaptador P3X2 - P2 | AC6: 1 | AD6: =AC6-AE6 -> 1
A7: 5 | B7: Maio | C7: 201.6 | D7: 0 | E7: =SUM(60+20+650) -> 730 | I7: RENATA | J7: 10 | K7: 15 | S7: Cartão NU | T7: 27027.55 | U7: 13427.4 | W7: Dinheiro emprestado | X7: 30 | AB7: Adaptador rede - usb | AC7: 1 | AD7: =AC7-AE7 -> 1
A8: 6 | B8: Junho | C8: 291.79 | D8: 0 | E8: =SUM(14+5+50+45+25+2+360+60+44+3+4+3+20+200) -> 835 | I8: CHIP | S8: Empresa NU | T8: =1021.42+14105.35 -> 15126.77 | U8: =532.34+7388.86 -> 7921.2 | W8: Trava de freio a disco | X8: 35 | AB8: Adaptador tipo c para usb | AC8: 7 | AD8: =AC8-AE8 -> 7
A9: 7 | B9: Julho | C9: 444.24 | D9: 0 | E9: =SUM(7+95+2+2500+30+70+30+50+330+15+18+45+10+2+150+10+10+15) -> 3389 | I9: Shopee 1 | J9: 220.8 | K9: 20 | S9: Neon | T9: 3303.72 | U9: 2758.75 | W9: Hub divisor | X9: 80 | AB9: Adaptador Tomada 2 Entradas + 3 Usb Celular Universal Led Variada | AC9: 2 | AD9: =AC9-AE9 -> 2
A10: 8 | B10: Agosto | C10: 552.75 | D10: 0 | E10: =SUM(2+10+6+22.5+3+2+5+2+11) -> 63.5 | I10: Shopee 2 | J10: 220.8 | K10: 20 | S10: Nu PJ | T10: 2434.54 | U10: 1544.43 | AB10: Adaptador v8 - Iphone | AC10: 2 | AD10: =AC10-AE10 -> 2
A11: 9 | B11: Setembro | C11: 234.8 | D11: 0 | E11: =SUM(50+2+42+30+10+5) -> 139 | I11: DARF | J11: 81 | K11: 20 | AB11: Adaptador VGA para HDMI | AC11: 3 | AD11: =AC11-AE11 -> 3
A12: 10 | B12: Outubro | C12: 312.44 | D12: 0 | E12: =SUM(30+10) -> 40 | I12: Aliexpress | J12: 54.47 | K12: 20 | S12: Total | T12: =SUM(T3:T11) -> 67065.39 | U12: =SUM(U3:U11) -> 40359.25 | AB12: Adaptador Wifi 2.5G | AC12: 3 | AD12: =AC12-AE12 -> 3
A13: 11 | B13: Novembro | C13: 564.38 | D13: 0 | G13: 669.7 | I13: NET CPF | J13: 100 | K13: 21 | W13: Total pego | X13: =SUM(X6:X12) -> 210 | AB13: Adaptador Wifi 2.5G Antena | AC13: 1 | AD13: =AC13-AE13 -> 1
A14: 12 | B14: Dezembro | C14: 3223.22 | I14: NET PJ | J14: 100 | K14: 21 | AB14: Adaptador Wifi 2.5G Antena MS | AC14: 1 | AD14: =AC14-AE14 -> 1
A15: Soma | C15: =SUM(C3:C14) -> 9154.29 | D15: =SUM(D3:D14) -> 470 | E15: 9759.5 | F15: =SUM(F3:F14) -> 0 | G15: =SUM(G3:G14) -> 669.7 | I15: AGUA | J15: 100 | K15: 27 | AB15: Alicate Universal 8 Id-4762A | AC15: 1 | AD15: =AC15-AE15 -> 1
A16: Total | C16: =SUM(C15:G15) -> 20053.49 | D16: Falta | E16: =81000-C16 -> 60946.51 | AB16: Amolador de faca | AC16: 2 | AD16: =AC16-AE16 -> 2
I17: TOTAL | J17: =SUM(J3:J15) -> 2232.23 | AB17: Antena Digital | AC17: 0 | AD17: =AC17-AE17 -> 0
A18: Vendas CNPJ 2024 | AB18: Balança 10kg | AC18: 2 | AD18: =AC18-AE18 -> 2
A19: Meses | B19: Meses | C19: Vendas Shopee | D19: Presencial | E19: Infiniti | AB19: Balança de mala | AC19: 1 | AD19: =AC19-AE19 -> 1
A20: 1 | B20: Janeiro | AB20: Balança De Precisão Xm-50522 | AC20: 3 | AD20: =AC20-AE20 -> 3
A21: 2 | B21: Fevereiro | AB21: Baralho C 2 Jogos Bar-69087 | AC21: 1 | AD21: =AC21-AE21 -> 1
A22: 3 | B22: Março | AB22: Baralho C 2 Jogos Bar-69087 | AC22: 5 | AD22: =AC22-AE22 -> 5
A23: 4 | B23: Abril | AB23: Bateria 9v | AC23: 1 | AD23: =AC23-AE23 -> 1
A24: 5 | B24: Maio | AB24: Blindagem | AC24: 1 | AD24: =AC24-AE24 -> 1
A25: 6 | B25: Junho | AB25: Bolsa Multifuncional Masculina De Peito | AC25: 2 | AD25: =AC25-AE25 -> 2
A26: 7 | B26: Julho | AB26: Bolsa Necessaire Organizadora Para Cosméticos | AC26: 1 | AD26: =AC26-AE26 -> 1
A27: 8 | B27: Agosto | AB27: Bomba D'Agua Automatica | AC27: 0 | AD27: =AC27-AE27 -> 0
A28: 9 | B28: Setembro | AB28: Bomba D'Agua manual | AC28: 1 | AD28: =AC28-AE28 -> 1
A29: 10 | B29: Outubro | AB29: Cabo Auxiliar P2 Kingo | AC29: 3 | AD29: =AC29-AE29 -> 3
A30: 11 | B30: Novembro | AB30: Cabo Colorido 2 Metros Iphone | AC30: 1 | AD30: =AC30-AE30 -> 1
A31: 12 | B31: Dezembro | AB31: Cabo Colorido 2 Metros Tipo C | AC31: 5 | AD31: =AC31-AE31 -> 5
A32: Soma | C32: =SUM(C20:C31) -> 0 | D32: =SUM(D20:D31) -> 0 | E32: =SUM(E20:E31) -> 0 | F32: =SUM(F20:F31) -> 0 | G32: =SUM(G20:G31) -> 0 | AB32: Cabo Colorido 2 Metros V8 | AC32: 1 | AD32: =AC32-AE32 -> 1
A33: Total | C33: =SUM(C32:G32) -> 0 | D33: Falta | E33: =81000-C33 -> 81000 | AB33: Cabo Colorido Iphone 1M | AC33: 7 | AD33: =AC33-AE33 -> 7
AB34: Cabo Colorido Tipo C 1M | AC34: 3 | AD34: =AC34-AE34 -> 3
AB35: Cabo Colorido v8 1M | AC35: 1 | AD35: =AC35-AE35 -> 1
AB36: cabo de força | AC36: 1 | AD36: =AC36-AE36 -> 1
AB37: Cabo De Força - Pc | AC37: 1 | AD37: =AC37-AE37 -> 1
AB38: Cabo Hdmi 2M | AC38: 2 | AD38: =AC38-AE38 -> 2
AB39: Cabo HDMI 4 em 1 | AC39: 1 | AD39: =AC39-AE39 -> 1
AB40: Cabo Hdmi 4M | AC40: 1 | AD40: =AC40-AE40 -> 1
AB41: Cabo Hmaster Tpc 4.8A | AC41: 2 | AD41: =AC41-AE41 -> 2
AB42: Cabo Inova Tc Cbo-12223 | AC42: 3 | AD42: =AC42-AE42 -> 3
AB43: Cabo iphone 20w | AC43: 5 | AD43: =AC43-AE43 -> 5
AB44: Cabo iphone caixa branca | AC44: 2 | AD44: =AC44-AE44 -> 2
AB45: Cabo Iphone Tipo C - Leo | AC45: 1 | AD45: =AC45-AE45 -> 1
... AB432: Fone de ouvido gamr q0008 | AC432: 1 | AD432: =AC432-AE432 -> 1
AB433: Memoria | AD433: =AC433-AE433 -> 0
AB434: Fonte pc 200w | AC434: 1 | AD434: =AC434-AE434 -> 1
AB435: filtro de linha 7 | AC435: 1 | AD435: =AC435-AE435 -> 1
AB436: Caddy | AC436: 1 | AD436: =AC436-AE436 -> 1
AB437: Pendrive 8gb | AC437: 1 | AD437: =AC437-AE437 -> 1
AB438: Carregador tipo C LE-484 | AC438: 5 | AD438: =AC438-AE438 -> 5
AB439: Suporte de Tv Simples | AC439: 1 | AD439: =AC439-AE439 -> 1
AB440: Powerbank 10000 BTE-084 | AC440: 1 | AD440: =AC440-AE440 -> 1
AB441: Caixa de som Grasep D-S4145 | AC441: 1 | AD441: =AC441-AE441 -> 1
AB442: Pendrive lenovo 16gb | AC442: 1 | AD442: =AC442-AE442 -> 1
AB443: Canivete multifuncional | AC443: 1 | AD443: =AC443-AE443 -> 1
AB444: adaptador wifi 6 | AC444: 1 | AD444: =AC444-AE444 -> 1
AB445: Aspirador 95000pa | AC445: 1 | AD445: =AC445-AE445 -> 1
... AB474: Unitv | AC474: 1 | AD474: =AC474-AE474 -> 1

Sheet jogos
A1: Jogos PS2 | B1: Atual | C1: qt | D1: Vendio | F1: Jogos Xbox | G1: Atual | H1: qt | J1: Peliculas Vendidas | P1: Peliculas Disponiveis
A2: 007 From Russi | B2: =C2-D2 -> 0 | C2: 1 | D2: 1 | F2: 007 Legends | G2: 1 | H2: 1 | J2: QT | K2: marca | L2: Modelo | M2: Compativel | O2: marca | P2: QT | Q2: Modelo | R2: Compativel
A3: Ace Bombat The Belkan War | B3: =C3-D3 -> 2 | C3: 3 | D3: 1 | F3: Ace combat assault horizon | G3: 1 | H3: 1 | J3: 2 | K3: Iphone | L3: XS MAX/ 11 PRO MAX | O3: Iphone | P3: 1 | Q3: 6G
A4: Astro Boy | B4: =C4-D4 -> 4 | C4: 4 | F4: Anarchy Reigns | G4: 1 | H4: 1 | J4: 2 | K4: Iphone | L4: XR / 11 | O4: Iphone | P4: 5 | Q4: 7 / 8 g
A5: Bad Boys miami takedown | B5: =C5-D5 -> 2 | C5: 2 | F5: Arcade | G5: 1 | H5: 1 | J5: 1 | K5: Iphone | L5: 13 | O5: Iphone PRIVACIDADE | P5: 1 | Q5: 7 / 8 g
A6: Barn Yard | B6: =C6-D6 -> 2 | C6: 2 | F6: Army Of Tiio | G6: 1 | H6: 1 | J6: 1 | K6: Iphone | L6: 7G / 8G | O6: Iphone | P6: 1 | Q6: 7 PLUS / 8 PLUS
A7: Batmam begins | B7: =C7-D7 -> 1 | C7: 1 | F7: Batman 3 lego | G7: 2 | H7: 2 | J7: 1 | K7: Iphone | L7: 15 | O7: Iphone PRIVACIDADE | P7: 4 | Q7: 7 PLUS / 8 PLUS
A8: Battlefield 2 Modern Combat | B8: =C8-D8 -> 1 | C8: 1 | F8: Batman Arkham City | G8: 1 | H8: 2 | J8: 1 | K8: Iphone | L8: 12 | O8: Iphone | P8: 3 | Q8: X / XS / 11 PRO | R8: XS - 11 PRO - A01 CORE
A9: Beach Volleyball | B9: =C9-D9 -> 2 | C9: 2 | F9: Bayoneta | G9: 1 | H9: 1 | J9: 1 | K9: Samsung | L9: A13 | O9: Iphone PRIVACIDADE | P9: 1 | Q9: XS / 11
A10: Bem 10 Utimate Alien | B10: =C10-D10 -> 3 | C10: 3 | F10: Bioshock | G10: 1 | H10: 1 | J10: 1 | K10: Samsung | L10: 13 4G | O10: Iphone | P10: 1 | Q10: XS / 11
A11: Bem 10 vilgah attacks | B11: =C11-D11 -> 1 | C11: 1 | F11: Bioshock 2 | G11: 1 | H11: 1 | J11: 1 | K11: Samsung | L11: A15 | O11: Iphone | P11: 2 | Q11: XS MAX | R11: POCO F1 / IPHONE XS MAX / IPHONE 11 PRO MAX
A12: Biohazard Outbreak File 2 | B12: =C12-D12 -> 2 | C12: 2 | F12: Bioshock Infinite | G12: 1 | H12: 1 | J12: 1 | K12: Samsung | L12: A20S | O12: Iphone | P12: 1 | Q12: 12 | R12: 12 PRO / IPHONE 11
A13: Black | B13: =C13-D13 -> 1 | C13: 7 | D13: 6 | F13: Borderlands 2 | G13: 2 | H13: 2 | J13: 1 | K13: Samsung | L13: A30S | O13: Iphone | P13: 1 | Q13: 12 PRO
A14: Blade 2 | B14: =C14-D14 -> 1 | C14: 1 | F14: Bound By Flame | G14: 1 | H14: 1 | J14: 1 | K14: Samsung | L14: A32 4G | O14: Iphone | P14: 2 | Q14: 12 PRO MAX
A15: Bomba Patch | B15: =C15-D15 -> 2 | C15: 2 | F15: BRAZUKAS 2023 | G15: 1 | H15: 1 | J15: 1 | K15: Samsung | L15: A24 | O15: Iphone | P15: 2 | Q15: 13 / 13 PRO | R15: IPHONE 13 / IPHONE 14 / E 14 PRO
A16: Bomba Patch 2024 | B16: =C16-D16 -> 0 | C16: 0 | F16: BRAZUKAS 2025 | G16: 1 | J16: 1 | K16: Samsung | L16: A51 | O16: Iphone | P16: 6 | Q16: 13 PRO MAX
A17: Bomba Patch Leonardo | B17: =C17-D17 -> 3 | C17: 3 | F17: Bulletstorm | G17: 1 | J17: 1 | K17: Samsung | L17: A53 | O17: Iphone PRIVACIDADE | P17: 2 | Q17: 13 PRO MAX / 14 PLUS
A18: Bomba Patch Mix Itaqui 2024 | B18: =C18-D18 -> 2 | C18: 2 | F18: Cabelas Dangerous Hunter 20 | G18: 1 | H18: 1 | J18: 1 | K18: Samsung | L18: A50 | O18: Iphone | P18: 1 | Q18: 14 / 14 PRO | R18: IPHONE 13 PRO / IPHONE 14 / IPHONE 13
A19: Bomberman Kart 3 | B19: =C19-D19 -> 1 | C19: 1 | F19: Cabelas Survival | G19: 1 | H19: 1 | J19: 1 | K19: Samsung | L19: A70 | O19: Iphone PRIVACIDADE | P19: 1 | Q19: 14 / 14 PRO | R19: IPHONE 13 PRO / IPHONE 14 / IPHONE 13
A20: Bomberman Land 3 | B20: =C20-D20 -> 2 | C20: 2 | F20: Calela African | G20: 1 | H20: 1 | J20: 1 | K20: Samsung | L20: S24 FE | O20: Iphone PRIVACIDADE | P20: 1 | Q20: 14 PRO MAX | R20: IPHONE 14 PRO MAX - IPHONE 13 PRO MAX - IPHONE 15 PRO MAX
A21: Bully | B21: =C21-D21 -> 0 | C21: 4 | D21: 4 | F21: call of duty black ops | G21: 1 | H21: 1 | J21: 1 | K21: Motorola | L21: G30 | O21: Iphone | P21: 3 | Q21: 14 PRO MAX | R21: IPHONE 14 PRO MAX - IPHONE 13 PRO MAX - IPHONE 15 PRO MAX
A22: Burnout 3 | B22: =C22-D22 -> 1 | C22: 5 | D22: 4 | F22: Capcom Digital Collection | G22: 1 | J22: 1 | K22: Motorola | L22: G73 | O22: Iphone | P22: 5 | Q22: 15 | R22: IPHONE 15 - IPHONE 15 PRO
A23: Call Of Duty Word At War | B23: =C23-D23 -> 1 | C23: 3 | D23: 2 | F23: Captain America Super Soldier | G23: 1 | H23: 1 | J23: 1 | K23: Motorola | L23: G54 | O23: Iphone | P23: 1 | Q23: 15 PLUS | R23: IPHONE 14 PRO MAX - IPHONE 13 PRO MAX - IPHONE 15 PRO MAX
A24: Cars | B24: =C24-D24 -> 5 | C24: 5 | F24: Clash Of The Titans | G24: 1 | H24: 1 | J24: 1 | K24: Motorola | L24: M32 | O24: Sansung | P24: 2 | Q24: j5 prime
A25: Castevania Curse Of Dark | B25: =C25-D25 -> 2 | C25: 3 | D25: 1 | F25: Crysis 2 | G25: 1 | H25: 1 | J25: 1 | K25: Xaiome | L25: XM 9 SE | O25: Sansung | P25: 2 | Q25: A01 | R25: XIAOMI MI9 SE / MI PLAY
A26: Chicken Little | B26: =C26-D26 -> 3 | C26: 3 | F26: Dance Dance Revolution | G26: 2 | H26: 1 | J26: 1 | K26: Xaiome | L26: MI 9T | O26: Sansung | P26: 6 | Q26: A15 | R26: A24 - M34 - A25
A27: Conflict Global Terror | B27: =C27-D27 -> 1 | C27: 1 | F27: Darkvoid | G27: 1 | H27: 1 | J27: 1 | K27: Xaiome | L27: PC X5 PRO | O27: Sansung | P27: 1 | Q27: A21 / A 21S | R27: A21S - MOTO G52 - POCO M3 PRO - MOTO G41
A28: crash action pack | B28: =C28-D28 -> 0 | C28: 0 | F28: Dead Islaand Riptide | G28: 1 | H28: 1 | J28: 1 | K28: Xaiome | L28: RD 8 | O28: Sansung | P28: 2 | Q28: A22 5G | R28: MOTO G50 / MOTO G30 / SAMSUN A12 / SAMSUNG M12 / SAMSUNG A02S
A29: Dark Watch | B29: =C29-D29 -> 0 | C29: 2 | D29: 2 | F29: Deadpol | G29: 1 | H29: 1 | O29: Sansung | P29: 1 | Q29: A24 | R29: SAMSUNG / M34 4G / M21S / M31
A30: Def Jam Fight for ny | B30: =C30-D30 -> 1 | C30: 1 | F30: Devil May Cry 4 | G30: 1 | H30: 1 | O30: Sansung | P30: 1 | Q30: A25 5G
A31: Digimon Rumble Arena 2 | B31: =C31-D31 -> 1 | C31: 2 | D31: 1 | F31: Dirt 3 | G31: 1 | H31: 1 | O31: Sansung | P31: 2 | Q31: A31 / A32 | R31: A20 / A30 /A50 / M31 / G8 PLUS / NOTE 8
A32: Donkey Kong Country The Trilogy | B32: =C32-D32 -> 5 | C32: 7 | D32: 2 | F32: Disney universe | G32: 1 | H32: 2 | O32: Sansung | P32: 1 | Q32: A34 | R32: S22+ / A54 / A24
A33: Down Hill Domination | B33: =C33-D33 -> 1 | C33: 3 | D33: 2 | F33: Duck Tales | G33: 1 | O33: Sansung | P33: 2 | Q33: A35 / A35 5G | R33: A55 - M35 - S23 PLUS - S22 PLUS
A34: Drive | B34: =C34-D34 -> 4 | C34: 5 | D34: 1 | F34: Dynasty Warriors 8 | G34: 1 | H34: 1 | O34: Sansung | P34: 2 | Q34: A 71 | R34: A80 - A21 - POCO X3 PRO - MOTO G41 - MOTO G52 - XIAOMI MI 11 LITE - MOTO G62 - REALME 7 PRO - REDMI NOTE 10 S - XIAOMI NOTE 10 - A71
A35: E Football 2024 | B35: =C35-D35 -> 4 | C35: 4 | F35: Dynasty Warriors Empire | G35: 1 | H35: 1 | O35: Sansung | P35: 1 | Q35: A72 | R35: MI POCO F3 / M51 / MOTO G52 / XIAOMI REDMI NOTE 10 PRO / XIAOMI MI 11i
A36: E Football 2024 Wjd | B36: =C36-D36 -> 1 | C36: 1 | F36: Enemy Front | G36: 1 | H36: 1 | O36: Sansung | P36: 1 | Q36: S10 E
A37: Evil Dead Regeneration | B37: =C37-D37 -> 1 | C37: 1 | F37: F3Ar | G37: 1 | H37: 1 | O37: Sansung | P37: 2 | Q37: S22 | R37: S21 FE
A38: F1 06 | B38: =C38-D38 -> 3 | C38: 3 | F38: Fallout 3 | G38: 1 | H38: 1 | O38: Sansung | P38: 3 | Q38: S23FE | R38: S22 PLUS - A54 - S23 PLUS
A39: Family Guy Video Game | B39: =C39-D39 -> 1 | C39: 1 | F39: Guita hero AEROSMIT | G39: 1 | H39: 1 | O39: Sansung | P39: 1 | Q39: S23 | R39: S22+
A40: Fantastic 4 | B40: =C40-D40 -> 2 | C40: 2 | F40: Guitar hero 3 legends of rock | G40: 1 | O40: Motorola | P40: 1 | Q40: G5
A41: Fifa 2019 | B41: =C41-D41 -> 1 | C41: 1 | F41: Indiana Jones 2 lego | G41: 1 | O41: Motorola | P41: 1 | Q41: G6 PLUS
A42: Final Fantasy X | B42: =C42-D42 -> 0 | C42: 1 | D42: 1 | F42: Indiana Jones lego | G42: 1 | H42: 1 | O42: Motorola | P42: 1 | Q42: G6
A43: Final Fantasy X-2 | B43: =C43-D43 -> 0 | C43: 2 | D43: 2 | F43: Injustice Gods Amongus | G43: 1 | H43: 1 | O43: Motorola | P43: 2 | Q43: G7 PLAY | R43: G7 / G7 PLAY / G8 PLUS / G8 PLAY / A01
A44: Ghost Recon 2 | B44: =C44-D44 -> 1 | C44: 1 | F44: Just Cause 2 | G44: 1 | H44: 1 | O44: Motorola | P44: 1 | Q44: G5 PLUS | R44: REDMI NOTE 3
A45: God Of War 1 | B45: =C45-D45 -> 1 | C45: 4 | D45: 3 | F45: Just dance 2015 | G45: 1 | H45: 2 | O45: Motorola | P45: 2 | Q45: G7 PLUS | R45: NOTE 7 / A20 / A30 / G7 / G7 PLUS /G8 PLUS / G8 PLAY
A46: God Of War 2 | B46: =C46-D46 -> 1 | C46: 5 | D46: 4 | F46: just dance 2019 | G46: 1 | H46: 2 | O46: Motorola | P46: 3 | Q46: E5 / G6 PLAY | R46: MOTO G6 PLAY
A47: GTA 5 | B47: =C47-D47 -> 0 | C47: 1 | D47: 1 | F47: Khights Contract | G47: 1 | H47: 1 | O47: Motorola | P47: 3 | Q47: G8 | R47: MOTO G8 / POCO M3 / XIAMI 11 LITE / REDMI NOTE 11 / REDMI NOTE 10 / POCO X4 / RELME 7 PRO / SAMSUNG A52
A48: GTA San andres | B48: =C48-D48 -> 1 | C48: 6 | D48: 5 | F48: Left 4 Dead | G48: 1 | H48: 1 | O48: Motorola | P48: 2 | Q48: G8 POWER LITE | R48: MOTO G9 / G9 PLAY / E7 POWER / E7 PLUS / A70 / K50S / K41S / REDMI 9 / REDMI 9A / REDMI 9C
A49: Gta Vice City | B49: =C49-D49 -> 3 | C49: 3 | F49: Left 4 Dead 2 | G49: 1 | H49: 1 | O49: Motorola | P49: 2 | Q49: G8 PLUS | R49: A10S / A20 / A30S / G8 PLUS / G8 PLAY / NOTE 7 / NOTE 8
A50: Harry Potter | B50: =C50-D50 -> 2 | C50: 2 | F50: Lost Planet 3 | G50: 1 | H50: 1 | O50: Motorola | P50: 1 | Q50: G8 PLAY | R50: A10 G8 Play G8 Plus G7 Plus
A51: Indiana jones lego the original | B51: =C51-D51 -> 1 | C51: 1 | F51: Madagascar 3 | G51: 1 | H51: 1 | O51: Motorola | P51: 1 | Q51: G8 POWER | R51: MOTO G8 / ONE HYPER / A11 / NOTE 9
A52: I-Ninja | B52: =C52-D52 -> 1 | C52: 1 | F52: Marvel Super Hero Squard | G52: 1 | H52: 1 | O52: Motorola | P52: 1 | Q52: G9 PLUS | R52: A12
A53: Jurassic The Hunted | B53: =C53-D53 -> 2 | C53: 2 | F53: Mass2 Effect | G53: 1 | H53: 1 | O53: Motorola | P53: 2 | Q53: G9 PLAY | R53: A03 / M23 / A12 / A13 / G30 / G50 / E20 / A20S / E 7 POWER / ONE FUNSION
A54: Justice League Heroes | B54: =C54-D54 -> 2 | C54: 2 | F54: Metalgearrising | G54: 1 | H54: 1 | O54: Motorola | P54: 1 | Q54: G9 POWER | R54: MOTO G200
A55: Kilzone | B55: =C55-D55 -> 2 | C55: 2 | F55: Metro Last Light | G55: 1 | H55: 1 | O55: Motorola | P55: 2 | Q55: G10 / G20 / G30 | R55: MOTO E20 / ONE FUSIO / G20 / G30 / G9 PLAY / E7 PLUS / E7 PLAY / A02S
A56: King Kong | B56: =C56-D56 -> 3 | C56: 3 | F56: Midnight Club los angeles | G56: 1 | H56: 1 | O56: Motorola | P56: 2 | Q56: G14 | R56: G71 / G62 / G53 / G32 / G13 / G22 / G54
A57: Los Increibles La Amenaza Del Socavador | B57: =C57-D57 -> 1 | C57: 1 | F57: Minecraft | G57: 1 | H57: 1 | O57: Motorola | P57: 1 | Q57: G30 | R57: MOTO G10 - REALME C25 - REALME C11 - A23 - G20 - MOTO E20 - MOTO ONE FUSION - MOTO E13
A58: Los Sims | B58: =C58-D58 -> 1 | C58: 1 | F58: Minecraft Story Mode | G58: 2 | H58: 1 | O58: Motorola | P58: 2 | Q58: M32 | R58: SAMSUNG A22 / M22
A59: Madagascar | B59: =C59-D59 -> 0 | C59: 0 | F59: Mini Ninjas | G59: 1 | H59: 1 | O59: Motorola | P59: 1 | Q59: M34 | R59: A34 4G / S22+
A60: Mafia | B60: =C60-D60 -> 2 | C60: 2 | F60: Mirror'S Edge | G60: 1 | H60: 1 | O60: Motorola | P60: 1 | Q60: G42 | R60: G41 / G52 / G71 / A53 / REDMI NOTE 10 / A11
A61: Marvel X Capcom | B61: =C61-D61 -> 1 | C61: 1 | F61: Morph X | G61: 3 | H61: 1 | O61: Motorola | P61: 5 | Q61: G51 | R61: K62 / MOTO G51 / A11 / MOTO ONE FUSION / POCO F3 / XIAOMI MI 11 LIGTH / MOTO G71 / XIAOMI MI 11 / REALME C6 PRO / A11
A62: Medal Of Honor Vanguard | B62: =C62-D62 -> 0 | C62: 1 | D62: 1 | F62: Mortal Kombat Dc Universe | G62: 1 | H62: 1 | O62: Motorola | P62: 1 | Q62: G53 | R62: G62 / G71 / REDIMI NOTE 11 4G / S20 FE / RM NOTE 10 4G / RM NOTE 10 S
A63: Megaman X8 | B63: =C63-D63 -> 1 | C63: 1 | F63: N3 2 | G63: 1 | H63: 1 | O63: Motorola | P63: 8 | Q63: G54 | R63: G34 - G54 - G71 - G62 - G53 - G32 - G13 - G22 - G14
A64: Metal slug anthology | B64: =C64-D64 -> 1 | C64: 1 | F64: Naruto Rise Of A Ninja | G64: 1 | H64: 1 | O64: Motorola | P64: 2 | Q64: G71 5G
A65: Mickey Mouse Collection | B65: =C65-D65 -> 0 | C65: 0 | F65: Naruto The Broken Bond | G65: 1 | H65: 2 | O65: Motorola | P65: 4 | Q65: G73 | R65: MOTO G04 - MOTO G34 - MOTO G32 - MOTO G73 - NOTE 12 - NOTE 13
A66: mortal Kombat Armageddon | B66: =C66-D66 -> 1 | C66: 1 | F66: Need For Speed Mostwanted | G66: 1 | H66: 1 | O66: Motorola | P66: 1 | Q66: G100 | R66: moto g40 fusion / moto g60
A67: Moto Gp08 | B67: =C67-D67 -> 4 | C67: 4 | F67: Ninja 2 | G67: 1 | H67: 1 | O67: Motorola | P67: 1 | Q67: G200 | R67: MOTO G60 - MOTO G9 PLUS - MOTO G200
A68: Motocross Mania 3 | B68: =C68-D68 -> 3 | C68: 3 | F68: Novo pes 2023 | G68: 1 | H68: 1 | O68: Motorola | P68: 1 | Q68: EDGE 20 / EDGE 20 PRO
A69: Motor Storm Arctic Edge | B69: =C69-D69 -> 2 | C69: 2 | F69: Pac-Man | G69: 1 | H69: 1 | O69: Motorola | P69: 2 | Q69: EDGE 30 NEO
A70: Naruto Utimate Ninja | B70: =C70-D70 -> 0 | C70: 1 | D70: 1 | F70: PES 13 | G70: 1 | H70: 1 | O70: Motorola | P70: 2 | Q70: ONE | R70: K9 / K8 PLUS / POCO F1 / MI 8 LITE / ZENFONE 5 / P30 / NOTE 6 PRO / E6 PLAY
A71: Naruto Utimate Ninja 3 | B71: =C71-D71 -> -1 | C71: 0 | D71: 1 | F71: Pirates Of The Caribbean | G71: 1 | H71: 1 | O71: Xaiome | P71: 1 | Q71: MI 8 | R71: MI 8 PRO
A72: Nba 2012 | B72: =C72-D72 -> 1 | C72: 1 | F72: Prey | G72: 1 | H72: 1 | O72: Xaiome | P72: 1 | Q72: MI 8 LITE | R72: K9 / K8 PLUS / POCO F1 / MI 8 LITE / ZENFONE 5 / P30 / NOTE 6 PRO / E6 PLAY
A73: Need For Speed Carbon | B73: =C73-D73 -> 0 | C73: 0 | F73: Prince Of Persia Prodigy | G73: 1 | O73: Xaiome | P73: 4 | Q73: RD NOTE 8 PRO | R73: M10S
A74: Need For Speed Hot Mostwanted | B74: =C74-D74 -> 1 | C74: 1 | F74: Prototype 2 | G74: 1 | H74: 1 | O74: Xaiome | P74: 1 | Q74: RM NOTE 9S | R74: A71 - A80
A75: Need For Speed Hot Pursuit | B75: =C75-D75 -> 2 | C75: 2 | F75: Rango | G75: 1 | H75: 1 | O75: Xaiome | P75: 1 | Q75: RM 9 | R75: SAMSUNG M21S / SAMSUNG M31
A76: Need For Speed Underground | B76: =C76-D76 -> 0 | C76: 0 | F76: Rapala For Kinect | G76: 1 | H76: 1 | O76: Xaiome | P76: 3 | Q76: RM 9C | R76: A23 / A12 / A32 / MOTO E 7 PLUS / A23 / A03S / REDMI 9 POWER / REDMI 9T / REALME C11 / REALME C25 / POCO M3 / REDMI 9A / REDMI 9I
A77: Neeed For Speed Underground 2 | B77: =C77-D77 -> -1 | C77: 0 | D77: 1 | F77: Ratatouille | G77: 1 | H77: 1 | O77: Xaiome | P77: 1 | Q77: 9T | R77: REDMI NOTE 8T / REDMI NOTE 9 4G / POCO M3
A78: Nicktoons Attack Of Th Toybots | B78: =C78-D78 -> 1 | C78: 1 | F78: Rio | G78: 1 | H78: 1 | O78: Xaiome | P78: 2 | Q78: XM NOTE 10 PRO | R78: A73 / M51 / A52 / A71 / A72 / A21S / A21 / MOTO G STYLUS / REDMI NOTE 10 / REDMI NOTE 10S / REDMI NOTE 10 PRO / MI 11 i / XIAOMI MI 11 LITE
A79: One Piegce Grand Adventure | B79: =C79-D79 -> 1 | C79: 1 | F79: Rise Of The Argonauts | G79: 1 | H79: 1 | O79: Xaiome | P79: 1 | Q79: XM 10 LITE
A80: Over The Hedge | B80: =C80-D80 -> 1 | C80: 1 | F80: Risen | G80: 2 | H80: 1 | O80: Xaiome | P80: 3 | Q80: RM 10C
A81: P4 Persona 4 | B81: =C81-D81 -> 2 | C81: 2 | F81: Risen 2 | G81: 1 | H81: 1 | O81: Xaiome | P81: 2 | Q81: NOTE 10 PRO | R81: G53 / G32 / G82 / G71 REDIMI NOTE 10 PRO / XIAOMI MI11 / SAMSUNG A72 / LG K51S / SAMSUNG A73 / MI 11 LITE
A82: Pac Man Word 3 | B82: =C82-D82 -> 4 | C82: 4 | F82: Risen 3 | G82: 1 | H82: 1 | O82: Xaiome | P82: 2 | Q82: NOTE 10 4G
A83: Panzer elite action | B83: =C83-D83 -> 1 | C83: 1 | F83: Rock Band 3 | G83: 2 | H83: 2 | O83: Xaiome | P83: 1 | Q83: RM NOTE 11 / 11S / 12S | R83: NOTE 10 / A51 / A11 / S20 FE
A84: Pes 2013 | B84: =C84-D84 -> 1 | C84: 1 | F84: Rock Of The Dead | G84: 1 | H84: 1 | O84: Xaiome | P84: 1 | Q84: RM NOTE 11 4G
A85: Pes 2019 | B85: =C85-D85 -> 2 | C85: 2 | F85: Saints Row The Third | G85: 1 | H85: 1 | O85: Xaiome | P85: 2 | Q85: RM NOTE 12 PRO
A86: Pes 2024 | B86: =C86-D86 -> 6 | C86: 6 | F86: Section 8 | G86: 1 | H86: 2 | O86: Xaiome | P86: 1 | Q86: RM 12
A87: Pes Treme Terra V10 | B87: =C87-D87 -> 1 | C87: 1 | F87: Sherek Forever After | G87: 1 | H87: 1 | O87: Xaiome | P87: 2 | Q87: RM NOTE 12
A88: Peter Jacksons King Kong | B88: =C88-D88 -> 0 | C88: 0 | F88: Singularity | G88: 1 | H88: 1 | O88: Xaiome | P88: 3 | Q88: NOTE 12 C
A89: Rainbow Six 3 | B89: =C89-D89 -> 1 | C89: 1 | F89: Sombras De Mordor | G89: 1 | O89: Xaiome | P89: 1 | Q89: NOTE 12 S
A90: Ratatouille | B90: =C90-D90 -> 1 | C90: 1 | F90: Soul Calibur V | G90: 1 | H90: 1 | O90: Xaiome | P90: 3 | Q90: RM NOTE 13 PRO
A91: Red Dead Revolver | B91: =C91-D91 -> 1 | C91: 1 | F91: Spide-Man Shattered Dimensions | G91: 1 | H91: 1 | O91: Xaiome | P91: 3 | Q91: RM 13 C | R91: Samsung Galaxy A06 - A05 / A05S / Redmi 13C / Realme Note 50 / Realme C53 / Realme C51 / Realme C61 / Poco C65
A92: Resident Evil Code Veronica Dublado | B92: =C92-D92 -> 1 | C92: 1 | F92: Spiden-Man Edge Of Time | G92: 2 | H92: 1 | O92: Xaiome | P92: 3 | Q92: PC F5 /F5 PRO
A93: Rumble Roses | B93: =C93-D93 -> 1 | C93: 1 | F93: Spider man the amazing | G93: 1 | H93: 1 | O93: Xaiome | P93: 2 | Q93: PC M5 4G
A94: Saint Sena | B94: =C94-D94 -> 1 | C94: 1 | F94: Spider-Man The Amazing 2 | G94: 1 | H94: 1 | O94: Xaiome | P94: 1 | Q94: X6 / X6 PRO
A95: Scooby-Doo | B95: =C95-D95 -> 3 | C95: 3 | F95: Splinter Cell Clacklist | G95: 1 | H95: 1 | O95: Xaiome | P95: 1 | Q95: XM A3
A96: Sega Essentials 7X1 | B96: =C96-D96 -> 1 | C96: 1 | F96: Spyro | G96: 1 | H96: 2 | O96: Xaiome | P96: 2 | Q96: POCO M3
A97: Sherek 2 | B97: =C97-D97 -> 1 | C97: 1 | F97: Star Trek Legacy | G97: 1 | H97: 1 | O97: Xaiome | P97: 2 | Q97: NOTE 20 5G
A98: Sherek The Third | B98: =C98-D98 -> 0 | C98: 0 | F98: Star Wars The Force | G98: 1 | H98: 2 | O98: Xaiome | P98: 1 | Q98: PC X3
A99: Socom Combined Assault | B99: =C99-D99 -> 1 | C99: 1 | F99: Street Fighter 4 | G99: 1 | H99: 1
A100: Sonic Utimate Genesis | B100: =C100-D100 -> 1 | C100: 1 | F100: Tdu 2 | G100: 1 | H100: 1
...

Sheet Relatorio
A1: Total de vendas | X1: Produto | Y1: Uni
A2: Ano | B2: QT | C2: Valor gasto | D2: Valor vendido | E2: Lucro | X2: impressao preta | Y2: =COUNTIF('Vendas 2026'!C:C,X2) -> 19
A3: 2024 | B3: =SUM('Vendas 2024'!D2:D846) -> 1576 | C3: =SUM('Vendas 2024'!H2:H846) -> 10772.959 | D3: =SUM('Vendas 2024'!J:J) -> 27772.776 | E3: =D3-C3 -> 16999.817 | X3: Jogo ps2 shopee | Y3: =COUNTIF('Vendas 2026'!C:C,X3) -> 102
A4: 2025 | B4: =SUM(Table_24[QT]) -> 1826 | C4: =SUM('Vendas 2025'!H:H) -> 11786.313 | D4: =SUM('Vendas 2025'!J:J) -> 35020.98 | E4: =D4-C4 -> 23234.667 | X4: pelicula 3d | Y4: =COUNTIF('Vendas 2026'!C:C,X4) -> 13
A5: 2026 | B5: =SUM('Vendas 2026'!D2:D1048576) -> 679 | C5: =SUM('Vendas 2026'!H:H) -> 13468.662 | D5: =SUM('Vendas 2026'!J:J) -> 23013.06 | E5: =D5-C5 -> 9544.3983 | X5: Cheirinho para Carro | Y5: =COUNTIF('Vendas 2026'!C:C,X5) -> 21
X6: kit 10 jogos ps2 | Y6: =COUNTIF('Vendas 2026'!C:C,X6) -> 4
A7: Ano | C7: Shopee | D7: Fisica | E7: Tiktok | F7: Total | X7: Desentupidor | Y7: =COUNTIF('Vendas 2026'!C:C,X7) -> 3
A8: 2025 | C8: =COUNTIF('Vendas 2025'!F:F,Relatorio!C7) -> 68 | D8: =COUNTIF('Vendas 2025'!F:F,Relatorio!D7) -> 829 | E8: =COUNTIF('Vendas 2025'!F:F,Relatorio!E7) -> 13 | F8: =SUM(C8:E8) -> 910 | X8: Moeba | Y8: =COUNTIF('Vendas 2026'!C:C,X8) -> 2
A9: 2026 | C9: =COUNTIF(Table_246[Vendedor],Relatorio!C7) -> 187 | D9: =COUNTIF(Table_246[Vendedor],Relatorio!D7) -> 222 | E9: =COUNTIF(Table_246[Vendedor],Relatorio!E7) -> 41 | F9: =SUM(C9:E9) -> 450 | X9: serviço aleatorio | Y9: =COUNTIF('Vendas 2026'!C:C,X9) -> 3
X10: cabo iphone 20w | Y10: =COUNTIF('Vendas 2026'!C:C,X10) -> 2
X11: Carregador completo iphone | Y11: =COUNTIF('Vendas 2026'!C:C,X11) -> 0
X12: cheirinho | Y12: =COUNTIF('Vendas 2026'!C:C,X12) -> 1
X13: nterruptor De Controle Remoto | Y13: =COUNTIF('Vendas 2026'!C:C,X13) -> 1
X14: Case 2.5 Hd | Y14: =COUNTIF('Vendas 2026'!C:C,X14) -> 1
X15: Restauraçao dados | Y15: =COUNTIF('Vendas 2026'!C:C,X15) -> 1
X16: gravaçao de musica | Y16: =COUNTIF('Vendas 2026'!C:C,X16) -> 0
X17: boneco lego kit | Y17: =COUNTIF('Vendas 2026'!C:C,X17) -> 2
X18: durex | Y18: =COUNTIF('Vendas 2026'!C:C,X18) -> 1
X19: Pen Drive Com 10 Jogos Para PS2 | Y19: =COUNTIF('Vendas 2026'!C:C,X19) -> 1
X20: protetor documento | Y20: =COUNTIF('Vendas 2026'!C:C,X20) -> 1
X21: kit maçarico | Y21: =COUNTIF('Vendas 2026'!C:C,X21) -> 1
... X49: JOGOS DE PS2 | Y49: =COUNTIF('Vendas 2026'!C:C,X49) -> 9

Sheet Relatório Mensal
A1: Relatório de Vendas por Mês
A3: Ano | B3: Mês | C3: Nome do Mês | D3: Quantidade Vendida | E3: Valor Total Vendido | F3: Lucro Total
A4: 2024 | B4: 1 | C4: Janeiro | D4: =SUMIF('Vendas 2024'!A:A,1,'Vendas 2024'!D:D) -> 39 | E4: =SUMIF('Vendas 2024'!A:A,1,'Vendas 2024'!J:J) -> 1602.5 | F4: =SUMIF('Vendas 2024'!A:A,1,'Vendas 2024'!M:M) -> 699.06
A5: 2024 | B5: 2 | C5: Fevereiro | D5: =SUMIF('Vendas 2024'!A:A,2,'Vendas 2024'!D:D) -> 128 | E5: =SUMIF('Vendas 2024'!A:A,2,'Vendas 2024'!J:J) -> 2821.45 | F5: =SUMIF('Vendas 2024'!A:A,2,'Vendas 2024'!M:M) -> 1483.64
A6: 2024 | B6: 3 | C6: Março | D6: =SUMIF('Vendas 2024'!A:A,3,'Vendas 2024'!D:D) -> 90 | E6: =SUMIF('Vendas 2024'!A:A,3,'Vendas 2024'!J:J) -> 2774.31 | F6: =SUMIF('Vendas 2024'!A:A,3,'Vendas 2024'!M:M) -> 1572.94
A7: 2024 | B7: 4 | C7: Abril | D7: =SUMIF('Vendas 2024'!A:A,4,'Vendas 2024'!D:D) -> 97 | E7: =SUMIF('Vendas 2024'!A:A,4,'Vendas 2024'!J:J) -> 3156 | F7: =SUMIF('Vendas 2024'!A:A,4,'Vendas 2024'!M:M) -> 1607.52
A8: 2024 | B8: 5 | C8: Maio | D8: =SUMIF('Vendas 2024'!A:A,5,'Vendas 2024'!D:D) -> 86 | E8: =SUMIF('Vendas 2024'!A:A,5,'Vendas 2024'!J:J) -> 2106.39 | F8: =SUMIF('Vendas 2024'!A:A,5,'Vendas 2024'!M:M) -> 1323.67
A9: 2024 | B9: 6 | C9: Junho | D9: =SUMIF('Vendas 2024'!A:A,6,'Vendas 2024'!D:D) -> 186 | E9: =SUMIF('Vendas 2024'!A:A,6,'Vendas 2024'!J:J) -> 1955.096 | F9: =SUMIF('Vendas 2024'!A:A,6,'Vendas 2024'!M:M) -> 1140.266
A10: 2024 | B10: 7 | C10: Julho | D10: =SUMIF('Vendas 2024'!A:A,7,'Vendas 2024'!D:D) -> 166 | E10: =SUMIF('Vendas 2024'!A:A,7,'Vendas 2024'!J:J) -> 1837 | F10: =SUMIF('Vendas 2024'!A:A,7,'Vendas 2024'!M:M) -> 1339.83
A11: 2024 | B11: 8 | C11: Agosto | D11: =SUMIF('Vendas 2024'!A:A,8,'Vendas 2024'!D:D) -> 181 | E11: =SUMIF('Vendas 2024'!A:A,8,'Vendas 2024'!J:J) -> 1998.5 | F11: =SUMIF('Vendas 2024'!A:A,8,'Vendas 2024'!M:M) -> 1511.2945
A12: 2024 | B12: 9 | C12: Setembro | D12: =SUMIF('Vendas 2024'!A:A,9,'Vendas 2024'!D:D) -> 160 | E12: =SUMIF('Vendas 2024'!A:A,9,'Vendas 2024'!J:J) -> 2324.72 | F12: =SUMIF('Vendas 2024'!A:A,9,'Vendas 2024'!M:M) -> 1407.2271
A13: 2024 | B13: 10 | C13: Outubro | D13: =SUMIF('Vendas 2024'!A:A,10,'Vendas 2024'!D:D) -> 163 | E13: =SUMIF('Vendas 2024'!A:A,10,'Vendas 2024'!J:J) -> 1656.78 | F13: =SUMIF('Vendas 2024'!A:A,10,'Vendas 2024'!M:M) -> 1264.829
A14: 2024 | B14: 11 | C14: Novembro | D14: =SUMIF('Vendas 2024'!A:A,11,'Vendas 2024'!D:D) -> 144 | E14: =SUMIF('Vendas 2024'!A:A,11,'Vendas 2024'!J:J) -> 2532.5 | F14: =SUMIF('Vendas 2024'!A:A,11,'Vendas 2024'!M:M) -> 1820.3595
A15: 2024 | B15: 12 | C15: Dezembro | D15: =SUMIF('Vendas 2024'!A:A,12,'Vendas 2024'!D:D) -> 135 | E15: =SUMIF('Vendas 2024'!A:A,12,'Vendas 2024'!J:J) -> 2997.53 | F15: =SUMIF('Vendas 2024'!A:A,12,'Vendas 2024'!M:M) -> 1823.6812
A16: Total 2024 | D16: =SUM(D4:D15) -> 1575 | E16: =SUM(E4:E15) -> 27762.776 | F16: =SUM(F4:F15) -> 16994.317
A18: 2025 | B18: 1 | C18: Janeiro | D18: =SUMIF('Vendas 2025'!A:A,1,'Vendas 2025'!D:D) -> 157 | E18: =SUMIF('Vendas 2025'!A:A,1,'Vendas 2025'!J:J) -> 2794.75 | F18: =SUMIF('Vendas 2025'!A:A,1,'Vendas 2025'!M:M) -> 2205.079
A19: 2025 | B19: 2 | C19: Fevereiro | D19: =SUMIF('Vendas 2025'!A:A,2,'Vendas 2025'!D:D) -> 114 | E19: =SUMIF('Vendas 2025'!A:A,2,'Vendas 2025'!J:J) -> 2417.5 | F19: =SUMIF('Vendas 2025'!A:A,2,'Vendas 2025'!M:M) -> 1788.689
A20: 2025 | B20: 3 | C20: Março | D20: =SUMIF('Vendas 2025'!A:A,3,'Vendas 2025'!D:D) -> 126 | E20: =SUMIF('Vendas 2025'!A:A,3,'Vendas 2025'!J:J) -> 2597.67 | F20: =SUMIF('Vendas 2025'!A:A,3,'Vendas 2025'!M:M) -> 1438.532
A21: 2025 | B21: 4 | C21: Abril | D21: =SUMIF('Vendas 2025'!A:A,4,'Vendas 2025'!D:D) -> 327 | E21: =SUMIF('Vendas 2025'!A:A,4,'Vendas 2025'!J:J) -> 4854.5 | F21: =SUMIF('Vendas 2025'!A:A,4,'Vendas 2025'!M:M) -> 3859.25
A22: 2025 | B22: 5 | C22: Maio | D22: =SUMIF('Vendas 2025'!A:A,5,'Vendas 2025'!D:D) -> 109 | E22: =SUMIF('Vendas 2025'!A:A,5,'Vendas 2025'!J:J) -> 1409.5 | F22: =SUMIF('Vendas 2025'!A:A,5,'Vendas 2025'!M:M) -> 1121.34
A23: 2025 | B23: 6 | C23: Junho | D23: =SUMIF('Vendas 2025'!A:A,6,'Vendas 2025'!D:D) -> 98 | E23: =SUMIF('Vendas 2025'!A:A,6,'Vendas 2025'!J:J) -> 2367.5 | F23: =SUMIF('Vendas 2025'!A:A,6,'Vendas 2025'!M:M) -> 2115.7
A24: 2025 | B24: 7 | C24: Julho | D24: =SUMIF('Vendas 2025'!A:A,7,'Vendas 2025'!D:D) -> 187 | E24: =SUMIF('Vendas 2025'!A:A,7,'Vendas 2025'!J:J) -> 2124.5 | F24: =SUMIF('Vendas 2025'!A:A,7,'Vendas 2025'!M:M) -> 1443.18
A25: 2025 | B25: 8 | C25: Agosto | D25: =SUMIF('Vendas 2025'!A:A,8,'Vendas 2025'!D:D) -> 179 | E25: =SUMIF('Vendas 2025'!A:A,8,'Vendas 2025'!J:J) -> 1918.5 | F25: =SUMIF('Vendas 2025'!A:A,8,'Vendas 2025'!M:M) -> 1200.8067
A26: 2025 | B26: 9 | C26: Setembro | D26: =SUMIF('Vendas 2025'!A:A,9,'Vendas 2025'!D:D) -> 119 | E26: =SUMIF('Vendas 2025'!A:A,9,'Vendas 2025'!J:J) -> 1916 | F26: =SUMIF('Vendas 2025'!A:A,9,'Vendas 2025'!M:M) -> 1127.53
A27: 2025 | B27: 10 | C27: Outubro | D27: =SUMIF('Vendas 2025'!A:A,10,'Vendas 2025'!D:D) -> 175 | E27: =SUMIF('Vendas 2025'!A:A,10,'Vendas 2025'!J:J) -> 4380.68 | F27: =SUMIF('Vendas 2025'!A:A,10,'Vendas 2025'!M:M) -> 2227.48
A28: 2025 | B28: 11 | C28: Novembro | D28: =SUMIF('Vendas 2025'!A:A,11,'Vendas 2025'!D:D) -> 105 | E28: =SUMIF('Vendas 2025'!A:A,11,'Vendas 2025'!J:J) -> 2802.57 | F28: =SUMIF('Vendas 2025'!A:A,11,'Vendas 2025'!M:M) -> 1750.86
A29: 2025 | B29: 12 | C29: Dezembro | D29: =SUMIF('Vendas 2025'!A:A,12,'Vendas 2025'!D:D) -> 130 | E29: =SUMIF('Vendas 2025'!A:A,12,'Vendas 2025'!J:J) -> 5437.31 | F29: =SUMIF('Vendas 2025'!A:A,12,'Vendas 2025'!M:M) -> 2978.22
A30: Total 2025 | D30: =SUM(D18:D29) -> 1826 | E30: =SUM(E18:E29) -> 35020.98 | F30: =SUM(F18:F29) -> 23256.667
A32: 2026 | B32: 1 | C32: Janeiro | D32: =SUMIF('Vendas 2026'!A:A,1,'Vendas 2026'!D:D) -> 109 | E32: =SUMIF('Vendas 2026'!A:A,1,'Vendas 2026'!J:J) -> 2040.69 | F32: =SUMIF('Vendas 2026'!A:A,1,'Vendas 2026'!K:K) -> 2040.69
A33: 2026 | B33: 2 | C33: Fevereiro | D33: =SUMIF('Vendas 2026'!A:A,2,'Vendas 2026'!D:D) -> 119 | E33: =SUMIF('Vendas 2026'!A:A,2,'Vendas 2026'!J:J) -> 2040.85 | F33: =SUMIF('Vendas 2026'!A:A,2,'Vendas 2026'!K:K) -> 2040.85
A34: 2026 | B34: 3 | C34: Março | D34: =SUMIF('Vendas 2026'!A:A,3,'Vendas 2026'!D:D) -> 73 | E34: =SUMIF('Vendas 2026'!A:A,3,'Vendas 2026'!J:J) -> 3096.99 | F34: =SUMIF('Vendas 2026'!A:A,3,'Vendas 2026'!K:K) -> 3096.99
A35: 2026 | B35: 4 | C35: Abril | D35: =SUMIF('Vendas 2026'!A:A,4,'Vendas 2026'!D:D) -> 93 | E35: =SUMIF('Vendas 2026'!A:A,4,'Vendas 2026'!J:J) -> 3790.88 | F35: =SUMIF('Vendas 2026'!A:A,4,'Vendas 2026'!K:K) -> 3790.88
A36: 2026 | B36: 5 | C36: Maio | D36: =SUMIF('Vendas 2026'!A:A,5,'Vendas 2026'!D:D) -> 169 | E36: =SUMIF('Vendas 2026'!A:A,5,'Vendas 2026'!J:J) -> 4049.72 | F36: =SUMIF('Vendas 2026'!A:A,5,'Vendas 2026'!K:K) -> 4049.72
A37: 2026 | B37: 6 | C37: Junho | D37: =SUMIF('Vendas 2026'!A:A,6,'Vendas 2026'!D:D) -> 116 | E37: =SUMIF('Vendas 2026'!A:A,6,'Vendas 2026'!J:J) -> 7993.93 | F37: =SUMIF('Vendas 2026'!A:A,6,'Vendas 2026'!K:K) -> 7477.79
A38: 2026 | B38: 7 | C38: Julho | D38: =SUMIF('Vendas 2026'!A:A,7,'Vendas 2026'!D:D) -> 0 | E38: =SUMIF('Vendas 2026'!A:A,7,'Vendas 2026'!J:J) -> 0 | F38: =SUMIF('Vendas 2026'!A:A,7,'Vendas 2026'!K:K) -> 0
A39: 2026 | B39: 8 | C39: Agosto | D39: =SUMIF('Vendas 2026'!A:A,8,'Vendas 2026'!D:D) -> 0 | E39: =SUMIF('Vendas 2026'!A:A,8,'Vendas 2026'!J:J) -> 0 | F39: =SUMIF('Vendas 2026'!A:A,8,'Vendas 2026'!K:K) -> 0
A40: 2026 | B40: 9 | C40: Setembro | D40: =SUMIF('Vendas 2026'!A:A,9,'Vendas 2026'!D:D) -> 0 | E40: =SUMIF('Vendas 2026'!A:A,9,'Vendas 2026'!J:J) -> 0 | F40: =SUMIF('Vendas 2026'!A:A,9,'Vendas 2026'!K:K) -> 0
A41: 2026 | B41: 10 | C41: Outubro | D41: =SUMIF('Vendas 2026'!A:A,10,'Vendas 2026'!D:D) -> 0 | E41: =SUMIF('Vendas 2026'!A:A,10,'Vendas 2026'!J:J) -> 0 | F41: =SUMIF('Vendas 2026'!A:A,10,'Vendas 2026'!K:K) -> 0
A42: 2026 | B42: 11 | C42: Novembro | D42: =SUMIF('Vendas 2026'!A:A,11,'Vendas 2026'!D:D) -> 0 | E42: =SUMIF('Vendas 2026'!A:A,11,'Vendas 2026'!J:J) -> 0 | F42: =SUMIF('Vendas 2026'!A:A,11,'Vendas 2026'!K:K) -> 0
A43: 2026 | B43: 12 | C43: Dezembro | D43: =SUMIF('Vendas 2026'!A:A,12,'Vendas 2026'!D:D) -> 0 | E43: =SUMIF('Vendas 2026'!A:A,12,'Vendas 2026'!J:J) -> 0 | F43: =SUMIF('Vendas 2026'!A:A,12,'Vendas 2026'!K:K) -> 0
A44: Total 2026 | D44: =SUM(D32:D43) -> 679 | E44: =SUM(E32:E43) -> 23013.06 | F44: =SUM(F32:F43) -> 22496.92
A46: TOTAL GERAL | D46: =D16+D30+D44 -> 4080 | E46: =E16+E30+E44 -> 85796.816 | F46: =F16+F30+F44 -> 62747.904
