Workbook

Sheet devedores
C1: =SUM(C3:C13) -> 1414.4 | G1: Cliente | H1: Parcelas | I1: Prestação | J1: Pago | K1: Data | L1: V.J
A2: Nome | B2: Valor | C2: Falta | D2: Pagou | E2: OBS | G2: Carol | H2: 10x | I2: 72.8 | J2: 6 | K2: =TODAY() -> 44895 | L2: =(K2-K3) -> 441
A3: Gerente tatico | B3: 50 | C3: 0 | D3: 50 | E3: Caloteiros | G3: 44531 | K3: 44454
A4: Pedro | B4: 230 | D4: 100 | E4: Caloteiros | K4: Total
A5: Carlos ETB | B5: 205 | D5: 90 | E5: Caloteiros | G5: Gian | H5: 10 | I5: 35 | J5: 1 | K5: =J5*I5 -> 35
A6: Rafael portaria | B6: =600 -> 600 | C6: =B6-D6 -> 200 | D6: =200+100+100 -> 400 | E6: =IF(C6=0,"Pago","Pendente") -> Pendente | G6: Diego | H6: 10 | I6: 35 | J6: 1 | K6: =J6*I6 -> 35
A7: Gian | B7: =(1820+10+40)+L2+24.5 -> 2335.5 | C7: =B7-D7 -> 763.5 | D7: =1220+300+52 -> 1572 | E7: =IF(C7=0,"Pago","Pendente") -> Pendente | G7: Andre | H7: 10 | I7: 35 | J7: 1 | K7: =J7*I7 -> 35
A8: Carol | B8: 727.7 | C8: =B8-D8 -> 290.9 | D8: =I2*J2 -> 436.8 | E8: =IF(C8=0,"Pago","Pendente") -> Pendente | G8: Fernando | H8: 10 | I8: 35 | J8: 4.3 | K8: =J8*I8 -> 150.5
A9: marcellin | B9: =10+5+(150) -> 165 | C9: =B9-D9 -> 0 | D9: 165 | E9: =IF(C9=0,"Pago","Pendente") -> Pago | G9: Luiz | H9: 10 | I9: 35 | J9: 10 | K9: =J9*I9 -> 350
A10: Ray | B10: =50+80+30 -> 160 | C10: =B10-D10 -> 10 | D10: 150 | E10: =IF(C10=0,"Pago","Pendente") -> Pendente
A11: Andre | B11: =80+20 -> 100 | C11: =B11-D11 -> 0 | D11: 100 | E11: =IF(C11=0,"Pago","Pendente") -> Pago
A12: wemersson | B12: 300 | C12: =B12-D12 -> 150 | D12: 150 | E12: =IF(C12=0,"Pago","Pendente") -> Pendente
A13: Leandro | B13: 440 | C13: =B13-D13 -> 0 | D13: 440 | E13: =IF(C13=0,"Pago","Pendente") -> Pago
A15: Gian | B15: 350 | C15: =B15-D15 -> 315 | D15: =J5*I5 -> 35 | E15: =IF(C15=0,"Pago","Pendente") -> Pendente
A16: Diego | B16: 350 | C16: =B16-D16 -> 315 | D16: =J6*I6 -> 35 | E16: =IF(C16=0,"Pago","Pendente") -> Pendente
A17: Andre | B17: 350 | C17: =B17-D17 -> 315 | D17: =J7*I7 -> 35 | E17: =IF(C17=0,"Pago","Pendente") -> Pendente
A18: Fernando | B18: 350 | C18: =B18-D18 -> 200 | D18: 150 | E18: =IF(C18=0,"Pago","Pendente") -> Pendente
A19: Luiz | B19: 350 | C19: =B19-D19 -> 0 | D19: =J9*I9 -> 350 | E19: =IF(C19=0,"Pago","Pendente") -> Pago
A20: Total | B20: =SUM(B15:B19) -> 1750 | C20: =SUM(C15:C19) -> 1145 | D20: =SUM(D15:D19) -> 605

Sheet Relatorio
A1: 2019 | B1: Gasto | C1: Venda | D1: 2019 | E1: QT | G1: 2020 | H1: Gasto | I1: Venda | J1: 2020 | K1: QT | L1: QT | N1: 2021 | O1: Gasto | P1: Venda | Q1: 2021 | R1: QT | S1: QT. Local | T1: QV Shopee
A2: Janeiro | B2: 0 | C2: 310 | D2: 310 | E2: 0 | G2: Janeiro | H2: 1482.4 | I2: 4122.3 | J2: 2639.9 | K2: 63 | N2: Janeiro | O2: =vendas!D2 -> 3701.8 | P2: =vendas!E2 -> 7125.45 | Q2: =vendas!F2 -> 3423.65 | R2: =vendas!G2 -> 319 | S2: =vendas!I2 -> 38 | T2: =vendas!H2 -> 281
A3: Fevereiro | B3: 0 | C3: 45 | D3: 45 | E3: 0 | G3: Fevereiro | H3: 1348.19 | I3: 2617 | J3: 1268.81 | K3: 53 | N3: Fevereiro | O3: =vendas!D87 -> 5248.7 | P3: =vendas!E87 -> 11712.68 | Q3: =vendas!F87 -> 6463.98 | R3: =vendas!G87 -> 696 | S3: =vendas!I87 -> 60 | T3: =vendas!H87 -> 636
A4: Março | B4: 923.6 | C4: 1662 | D4: 738.4 | E4: 40 | G4: Março | H4: 1501.37 | I4: 3257.75 | J4: 1756.38 | K4: 79 | N4: Março | O4: =vendas!D146 -> 1461.0417 | P4: =vendas!E146 -> 8961.0417 | Q4: =vendas!F146 -> 8483.6883 | R4: =vendas!G146 -> 517 | S4: =vendas!I146 -> 42 | T4: =vendas!H146 -> 475
A5: Abril | B5: 1575.99 | C5: 2775.5 | D5: 1199.51 | E5: 50 | G5: Abril | H5: 3123.31 | I5: 6498 | J5: 3374.69 | K5: 148 | N5: Abril | O5: =vendas!D226 -> 7240.8 | P5: =vendas!E226 -> 14329.375 | Q5: =vendas!F226 -> 7088.575 | R5: =vendas!G226 -> 481 | S5: 27 | T5: 458
A6: Maio | B6: 2048.2 | C6: 3807 | D6: 2048.2 | E6: 75 | G6: Maio | H6: 4743.96 | I6: 10370.5 | J6: 5626.54 | K6: 255 | N6: Maio | O6: =vendas!D295 -> 3278.5667 | P6: =vendas!E295 -> 7054.35 | Q6: =vendas!F295 -> 3775.7833 | R6: =vendas!G295 -> 364 | S6: =vendas!I226 -> 35 | T6: =vendas!H295 -> 338
A7: Junho | B7: 2852.09 | C7: 5267 | D7: 2414.91 | E7: 129 | G7: Junho | H7: 2795.75 | I7: 6103.99 | J7: 3308.24 | K7: 124 | N7: Junho | O7: =vendas!D349 -> 2899.04 | P7: =vendas!E349 -> 6008.82 | Q7: =vendas!F349 -> 3109.78 | R7: =vendas!G349 -> 292 | S7: =vendas!I349 -> 14 | T7: =vendas!H349 -> 278
A8: Julho | B8: 3060.23 | C8: 5746.5 | D8: 2686.27 | E8: 150 | G8: Julho | H8: 2287.08 | I8: 5556 | J8: 3268.92 | K8: 112 | N8: Julho | O8: =vendas!D413 -> 2126.1833 | P8: =vendas!E413 -> 4830.65 | Q8: =vendas!F413 -> 2704.4667 | R8: =vendas!G413 -> 223 | S8: =vendas!I413 -> 24 | T8: =vendas!H413 -> 199
A9: Agosto | B9: 2057.59 | C9: 3756.8 | D9: 1788.21 | E9: 68 | G9: Agosto | H9: 2519.5 | I9: 5025 | J9: 2505.5 | K9: 78 | N9: Agosto | O9: =vendas!D477 -> 5508.6967 | P9: =vendas!E477 -> 5830.11 | Q9: =vendas!F477 -> 3012.4933 | R9: =vendas!G477 -> 201 | S9: =vendas!I477 -> 38 | T9: =vendas!H477 -> 163
A10: Setembro | B10: 2319.62 | C10: 4003.9 | D10: 1684.28 | E10: 66 | G10: Setembro | H10: 2261.71 | I10: 5004 | J10: 2742.29 | K10: 140 | N10: Setembro | O10: =vendas!D560 -> 2017.22 | P10: =vendas!E560 -> 10125.51 | Q10: =vendas!F560 -> 5233.89 | R10: =vendas!G560 -> 527 | S10: =vendas!I560 -> 53 | T10: =vendas!H560 -> 474
A11: Outubro | B11: 5257.26 | C11: 6788.82 | D11: 3284.34 | E11: 162 | G11: Outubro | H11: 1695.72 | I11: 3885 | J11: 2189.28 | K11: 67 | N11: Outubro | O11: =vendas!D653 -> 4107.9 | P11: =vendas!E653 -> 8220.23 | Q11: =vendas!F653 -> 4112.33 | R11: =vendas!G653 -> 245 | S11: =vendas!I653 -> 32 | T11: =vendas!H653 -> 213
A12: Novembro | B12: 1752.24 | C12: 3394.41 | D12: 1642.17 | E12: 79 | G12: Novembro | H12: 2108.77 | I12: 4560.45 | J12: 2451.68 | K12: 158 | N12: Novembro | O12: =vendas!D726 -> 3150.4 | P12: =vendas!E726 -> 6205.02 | Q12: =vendas!F726 -> 3054.62 | R12: =vendas!G726 -> 367 | S12: =vendas!I726 -> 26 | T12: =vendas!H726 -> 341
A13: Dezembro | B13: 2756.16 | C13: 4343.2 | D13: 2482.02 | E13: 72 | G13: Dezembro | H13: 3461.24 | I13: 7616.16 | J13: 4190.92 | K13: 254 | N13: Dezembro | O13: =vendas!D797 -> 3421.3067 | P13: =vendas!E797 -> 6739.9954 | Q13: =vendas!F797 -> 3318.6887 | R13: =vendas!G797 -> 395 | S13: =vendas!I797 -> 31 | T13: =vendas!H797 -> 364
A14: Total | B14: 24602.98 | C14: 41900.13 | D14: 20323.31 | E14: 891 | G14: Total | H14: 29329 | I14: 64616.15 | J14: 35323.15 | K14: 1531 | L14: =SUM(L2:L13) -> 0 | N14: Total | O14: =SUM(O2:O13) -> 44161.655 | P14: =SUM(P2:P13) -> 97143.232 | Q14: =SUM(Q2:Q13) -> 53781.945 | R14: =SUM(R2:R13) -> 4627 | S14: =SUM(S2:S13) -> 420 | T14: =SUM(T2:T13) -> 4220

Sheet vendas
B1: Vendas | C1: Item | D1: Pago | E1: Vendido | F1: Lucro | G1: Situação | H1: Shopee | I1: V. BSB
A2: Janeiro | D2: =SUM(D3:D86) -> 3701.8 | E2: =SUM(E3:E86) -> 7125.45 | F2: =SUM(F3:F86) -> 3423.65 | G2: =H2+I2 -> 319 | H2: =277+4 -> 281 | I2: 38
A3: 73 | B3: balança 10kg | D3: 30 | E3: 40 | F3: =E3-D3 -> 10 | G3: vendido
A4: 74 | B4: Barbeador de nariz | D4: 9 | E4: 15 | F4: =E4-D4 -> 6 | G4: vendido | I4: 44209
A5: 75 | B5: Barbeador inova 3780 | D5: 25 | E5: 50 | F5: =E5-D5 -> 25 | G5: vendido | I5: 44209
A6: 76 | B6: Bluetooth car | D6: 12 | E6: 20 | F6: =E6-D6 -> 8 | G6: vendido | I6: 44203
A7: 77 | B7: Bomba filtro galao | D7: 10 | E7: 40 | F7: =E7-D7 -> 30 | G7: vendido | I7: 44200
A8: 78 | B8: Bomba filtro galao | D8: 10 | E8: 25 | F8: =E8-D8 -> 15 | G8: vendido
A9: 79 | B9: Bomba filtro galao eletrico | D9: 22 | E9: 45 | F9: =E9-D9 -> 23 | G9: vendido
A10: 80 | B10: Cabo 2m iphone | D10: 7 | E10: 15 | F10: =E10-D10 -> 8 | G10: vendido | I10: 44204
A11: 81 | B11: Cabo hdmi 4k 10m | D11: 35 | E11: 60 | F11: =E11-D11 -> 25 | G11: vendido
A12: 82 | B12: Cabo ipega tipo c | D12: 8 | E12: 20 | F12: =E12-D12 -> 12 | G12: vendido
A13: 83 | B13: case HD | D13: 30 | E13: 50 | F13: =E13-D13 -> 20 | G13: vendido
A14: 84 | B14: chave universal | D14: 26 | E14: 50 | F14: =E14-D14 -> 24 | G14: vendido
A15: 85 | B15: Espremedor pasta | D15: 14.9 | E15: 30 | F15: =E15-D15 -> 15.1 | G15: vendido
A16: 86 | B16: Fone pcell pequeno | D16: 3 | E16: 15 | F16: =E16-D16 -> 12 | G16: vendido | I16: 44209
A17: 87 | B17: Fone pcell pequeno | D17: 5 | E17: 15 | F17: =E17-D17 -> 10 | G17: vendido | I17: 44209
A18: 88 | B18: formataçao | D18: 0 | E18: 70 | F18: =E18-D18 -> 70 | G18: vendido
A19: 89 | B19: Gatilho simples | D19: 4 | E19: 15 | F19: =E19-D19 -> 11 | G19: vendido | I19: 44209
A20: 90 | B20: Gatilho simples | D20: 4 | E20: 15 | F20: =E20-D20 -> 11 | G20: vendido | I20: 44209
A21: 91 | B21: Gatilho simples | D21: 4 | E21: 20 | F21: =E21-D21 -> 16 | G21: vendido
A22: 92 | B22: Globo de luz grande | D22: 60 | E22: 90 | F22: =E22-D22 -> 30 | G22: vendido | I22: 44200
A23: 93 | B23: Globo de luz pequeno | D23: 35 | E23: 70 | F23: =E23-D23 -> 35 | G23: vendido | I23: 44202
A24: 94 | B24: Globo de luz pequeno | D24: 35 | E24: 70 | F24: =E24-D24 -> 35 | G24: vendido | I24: 44209
A25: 95 | B25: Globo de luz pequeno | D25: 35 | E25: 70 | F25: =E25-D25 -> 35 | G25: vendido
A26: 96 | B26: Kit ferramenta | D26: 28 | E26: 50 | F26: =E26-D26 -> 22 | G26: vendido
A27: 97 | B27: kit manicure | D27: 10 | E27: 20 | F27: =E27-D27 -> 10 | G27: vendido | I27: 44204
A28: 98 | B28: kit manicure eletrica | D28: 15 | E28: 30 | F28: =E28-D28 -> 15 | G28: vendido | I28: 44203
A29: 99 | B29: kit reparo bike | D29: 2.5 | E29: 5 | F29: =E29-D29 -> 2.5 | G29: vendido
A30: 100 | B30: led usb bike | D30: 20 | E30: 50 | F30: =E30-D30 -> 30 | G30: vendido
A31: 101 | B31: Manta de trabalho | D31: 18 | E31: 40 | F31: =E31-D31 -> 22 | G31: vendido | I31: 44207
A32: 102 | B32: maquina de costura | D32: 7 | E32: 20 | F32: =E32-D32 -> 13 | G32: vendido
A33: 103 | B33: maquina de costura | D33: 7 | E33: 20 | F33: =E33-D33 -> 13 | G33: vendido
A34: 104 | B34: memory card 32mb | D34: 16 | E34: 50 | F34: =E34-D34 -> 34 | G34: vendido
A35: 105 | B35: mini depilador | D35: 13 | E35: 20 | F35: =E35-D35 -> 7 | G35: vendido | I35: 44204
A36: 106 | B36: mini depilador | D36: 13 | E36: 30 | F36: =E36-D36 -> 17 | G36: vendido
A37: 107 | B37: plano de tv | D37: 15 | E37: 30 | F37: =E37-D37 -> 15 | G37: vendido
A38: 108 | B38: SSD 240gb | D38: 160 | E38: 250 | F38: =E38-D38 -> 90 | G38: vendido
A39: 109 | B39: SSD 240gb | D39: 160 | E39: 200 | F39: =E39-D39 -> 40 | G39: vendido
A40: 110 | B40: transmissor veicular x8 | D40: 23 | E40: 50 | F40: =E40-D40 -> 27 | G40: vendido
A41: 111 | B41: Mini Máquina De Costura Manual Portátil De Mão Tecido | D41: =E41-F41 -> 324 | E41: 868.72 | F41: 544.72 | G41: vendido | H41: shopee
A42: 112 | B42: Bateria Litio 2032 Unitário Cr2032 1 unidades | D42: =E42-F42 -> 37 | E42: 79.57 | F42: 42.57 | G42: vendido | H42: shopee
A43: 113 | B43: Super Cola Instantânea Metal Madeira Plástico | D43: =E43-F43 -> 33 | E43: 62.36 | F43: 29.36 | G43: vendido | H43: shopee
A44: 114 | B44: Kit Reparo Para Pneu Sem Câmara | D44: =E44-F44 -> 110 | E44: 221.1 | F44: 111.1 | G44: vendido | H44: shopee
A45: 115 | B45: Lanterna Lampião 6+1 LED Recarregável Bivolt com USB - JH-5800T | D45: =E45-F45 -> 306 | E45: 520.09 | F45: 214.09 | G45: vendido | H45: shopee
A46: 116 | B46: Globo de luz de discoteca rotativo para festas, | D46: =E46-F46 -> 1225 | E46: 2287.14 | F46: 1062.14 | G46: vendido | H46: shopee
A47: 117 | B47: Kit Com 15 Tipo De Botoes Diversos Costura | D47: =E47-F47 -> 31.5 | E47: 93.92 | F47: 62.42 | G47: vendido | H47: shopee
A48: 118 | B48: Película Vidro Temperado Vários modelos. | D48: =E48-F48 -> 14.4 | E48: 38.56 | F48: 24.16 | G48: vendido | H48: shopee
A49: 119 | B49: Maquina Higiênica Aparadora / Aparador Depilador De Pelos Nariz e Orelha | D49: =E49-F49 -> 63 | E49: 89.56 | F49: 26.56 | G49: vendido | H49: shopee
A50: 120 | B50: Fone de Ouvido Pmcell Fo -11 Original C/ Microfone | D50: =E50-F50 -> 15 | E50: 23.79 | F50: 8.79 | G50: vendido | H50: shopee
A51: 121 | B51: Fio de Solda Estanho Cobix Tubinho 1mm 22 Gramas 1 Unidade | D51: =E51-F51 -> 42 | E51: 62.8 | F51: 20.8 | G51: vendido | H51: shopee
A52: 122 | B52: Cooler Fan Rgb Master Led Fc1302 120x120mm | D52: =E52-F52 -> 120 | E52: 168.9 | F52: 48.9 | G52: vendido | H52: shopee
... A78: 146 | B78: Unha Postiça Kits (contendo 20 unhas + cola ) Professional Instant Nail Tips | D78: =E78-F78 -> 1 | E78: 11.59 | F78: 10.59 | G78: vendido | H78: shopee
A79: 146 | B79: maquina de costura | D79: 5 | E79: 16 | F79: =SUM(E79-D79) -> 11 | G79: vendido | H79: shopee
A80: 146 | B80: maquina de costura | D80: 5 | E80: 16 | F80: =SUM(E80-D80) -> 11 | G80: vendido | H80: shopee
A81: 146 | B81: Lampaia | D81: 17 | E81: 30 | F81: =SUM(E81-D81) -> 13 | G81: vendido | H81: shopee
A82: 146 | B82: mini taiser | D82: 25 | E82: 40 | F82: =SUM(E82-D82) -> 15 | G82: vendido | H82: shopee
A83: 146
A84: 146
A85: 146
A87: Fevereiro | D87: =SUM(D88:D145) -> 5248.7 | E87: =SUM(E88:E145) -> 11712.68 | F87: =SUM(F88:F145) -> 6463.98 | G87: =SUM(C88:C145) -> 696 | H87: =G87-I87 -> 636 | I87: =COUNTIF(H88:H216,"bsb") -> 60
A88: 69 | B88: gatilho simples | C88: 1 | D88: 4 | E88: 25 | F88: =E88-D88 -> 21 | G88: vendido | H88: bsb
A89: 61 | B89: Smartband d20 | C89: 1 | D89: 22 | E89: 110 | F89: =E89-D89 -> 88 | G89: vendido | H89: bsb
A90: 72 | B90: plano de tv | C90: 1 | D90: 15 | E90: 30 | F90: =E90-D90 -> 15 | G90: vendido | H90: bsb
A91: 73 | B91: Mouse gamer mu2908 | C91: 1 | D91: 15 | E91: 35 | F91: =E91-D91 -> 20 | G91: vendido | H91: bsb
A92: 74 | B92: celular g6 | C92: 1 | D92: 0 | E92: 405 | F92: =E92-D92 -> 405 | G92: vendido | H92: bsb
A93: 75 | B93: Cartao onibuns | C93: 1 | D93: 0 | E93: 200 | F93: =E93-D93 -> 200 | G93: vendido | H93: bsb
A94: 95 | B94: Globo de luz de discoteca rotativo para festas, | C94: 1 | D94: 35 | E94: 85 | F94: =E94-D94 -> 50 | G94: vendido | H94: bsb
A95: 96 | B95: teclado tv box | C95: 1 | D95: 28 | E95: 60 | F95: =E95-D95 -> 32 | G95: vendido | H95: bsb
A96: 97 | B96: Globo de luz de discoteca rotativo para festas, | C96: 1 | D96: 35 | E96: 83 | F96: =E96-D96 -> 48 | G96: vendido | H96: bsb
A97: 98 | B97: Globo de luz de discoteca rotativo para festas, | C97: 1 | D97: 35 | E97: 70 | F97: =E97-D97 -> 35 | G97: vendido | H97: bsb
A98: 99 | B98: PC | C98: 1 | D98: 300 | E98: 500 | F98: =E98-D98 -> 200 | G98: vendido | H98: bsb
A99: 100 | B99: manta termica | C99: 1 | D99: 18 | E99: 40 | F99: =E99-D99 -> 22 | G99: vendido | H99: bsb
... A105: 106 | B105: bomba eletrica | C105: 1 | D105: 28 | E105: 55 | F105: =E105-D105 -> 27 | G105: vendido | H105: bsb
A106: 107 | B106: Mini Máquina De Costura Manual Portátil De Mão Tecido | C106: 163 | D106: 978 | E106: 2394.59 | F106: 1416.59 | G106: vendido | H106: shopee
A107: 108 | B107: Globo de luz de discoteca rotativo, para festas, luz estroboscópica | C107: 37 | D107: 1295 | E107: 2319.84 | F107: 1024.84 | G107: vendido | H107: shopee
A108: 109 | B108: Kit Reparo Pneu Abs Remendo Sem Camara Carros Motos | C108: 112 | D108: 560 | E108: 1170.73 | F108: 610.73 | G108: vendido | H108: shopee
A109: 110 | B109: Super Mini Taser Defense Choque Ideal Para Mulheres | C109: 19 | D109: 475 | E109: 910.83 | F109: 435.83 | G109: vendido | H109: shopee
A110: 111 | B110: Lanterna Lampião 6+1 LED Recarregável Bivolt com USB - JH-5800T | C110: 23 | D110: 391 | E110: 674.82 | F110: 283.82 | G110: vendido | H110: shopee
A111: 112 | B111: Calculadora Cientifica Profissional Modelo Id-8267c | C111: 12 | D111: 108 | E111: 329.42 | F111: 221.42 | G111: vendido | H111: shopee
A112: 113 | B112: ESPELHO RETROVISOR PARA BIKE HIGH ONE | C112: 32 | D112: 64 | E112: 246.99 | F112: 182.99 | G112: vendido | H112: shopee
A113: 114 | B113: Bateria Litio 2032 Unitário Cr2032 1 unidades | C113: 113 | D113: 113 | E113: 269.88 | F113: 156.88 | G113: vendido | H113: shopee
A114: 115 | B114: Relógio Inteligente Smartwatch D20 Bluetooth Monitor Saúde | C114: 1 | D114: 20 | E114: 142.21 | F114: 122.21 | G114: vendido | H114: shopee
A115: 116 | B115: Organizador gaveteiro 7000 com 16 gavetas | C115: 2 | D115: 50 | E115: 151.76 | F115: 101.76 | G115: vendido | H115: shopee
A116: 117 | B116: Película Vidro Temperado Vários modelos. | C116: 33 | D116: 49.5 | E116: 135.13 | F116: 85.63 | G116: vendido | H116: shopee
A117: 118 | B117: Almofada de Isolamento Térmico Magnético Estação de Solda Plataforma de Manutenção resistente ao Calor Reparação Isolamento Tapete de Trabalho | C117: 4 | D117: 52 | E117: 131.3 | F117: 79.3 | G117: vendido | H117: shopee
... A145: 146 | B145: Adaptador Usb 2.0 Ethernet Rj45 Fácil Instalação | C145: 1 | D145: 17 | E145: 17.5 | F145: 0.5 | G145: vendido | H145: shopee
A146: Março | D146: =SUM(D147:D225) -> 1461.0417 | E146: =SUM(E147:E225) -> 8961.0417 | F146: =SUM(F147:F225) -> 8483.6883 | G146: =SUM(C147:C225) -> 517 | H146: =G146-I146 -> 475 | I146: =COUNTIF(H147:H225,"bsb") -> 42
A147: 72 | B147: Gatilho ak66 | D147: 22 | E147: 40 | F147: =E147-D147 -> 18 | G147: vendido | H147: bsb
A148: 37 | B148: Chave tok/alen | C148: 1 | D148: 13.5 | E148: 20 | F148: =E148-D148 -> 6.5 | G148: vendido | H148: bsb
A149: 213 | B149: fone inova sem fio | C149: 1 | D149: 65 | E149: 120 | F149: =E149-D149 -> 55 | G149: vendido | H149: bsb
A150: 214 | B150: fone oriignal | C150: 1 | D150: 9 | E150: 25 | F150: =E150-D150 -> 16 | G150: vendido | H150: bsb
A151: 215 | B151: Corrente moto/bike | C151: 1 | D151: 25 | E151: 50 | F151: =E151-D151 -> 25 | G151: vendido | H151: bsb
A152: 216 | B152: aparador de pelo nariz | C152: 1 | D152: 9 | E152: 30 | F152: =E152-D152 -> 21 | G152: vendido | H152: bsb
A153: 217 | B153: Memory Card 8mb P/ Ps2 Kp-032 - Knup | C153: 1 | D153: 12 | E153: 35 | F153: =E153-D153 -> 23 | G153: vendido | H153: bsb
A154: 218 | B154: capa iphone | C154: 1 | D154: 13 | E154: 30 | F154: =E154-D154 -> 17 | G154: vendido | H154: bsb
A155: 219 | B155: Pelicula iphone | C155: 1 | D155: 1.5 | E155: 10 | F155: =E155-D155 -> 8.5 | G155: vendido | H155: bsb
A156: 220 | B156: despertador | C156: 1 | D156: 12 | E156: 50 | F156: =E156-D156 -> 38 | G156: vendido | H156: bsb
A157: 222 | B157: kit reparo pneu bike | C157: 1 | D157: 22 | E157: 35 | F157: =E157-D157 -> 13 | G157: vendido | H157: bsb
A158: 222 | B158: kit reparo pneu bike | C158: 1 | D158: 22 | E158: 35 | F158: =E158-D158 -> 13 | G158: vendido | H158: bsb
...

Sheet Planilha5
A3: Rótulos de Linha | B3: Soma de Quantidade | C3: Soma de Valor gasto | D3: Soma de Valor venddo | E3: Soma de Valor do lucro | F3: Contagem de vendas shopee
A4: 1PCS Glossy Multicolored Business ID Credit Card Cash Pocket Holder Wallet Aluminium Alloy Outer Plastic Inner Waterproof Case | C4: 2.5 | D4: 13.32 | E4: 10.82 | F4: 1
A5: A 70 Spray Líquido 200 ml - Nutriex | B5: 31 | C5: 176 | D5: 361.7222 | E5: 191.0622 | F5: 6
A6: ACENDEDOR DE FOGÃO | B6: 2 | C6: 6 | D6: 40.26 | E6: 28.26 | F6: 1
A7: Adaptador Fonte carregador para PSP 2000 3000 game portátil | C7: 14 | D7: 20 | E7: 6 | F7: 1
A8: Adaptador OTG USB V8 | B8: 1 | C8: 2.5 | D8: 8.32 | E8: 5.82 | F8: 1
A9: Adaptador Para Fone Headset Microfone Lapela P2 X P3 Áudio | B9: 1 | C9: 13 | D9: 34.56 | E9: 21.56 | F9: 3
A10: Adaptador Usb 2.0 Ethernet Rj45 Fácil Instalação | B10: 1 | C10: 22 | D10: 45.5 | E10: 23.5 | F10: 2
A11: adaptador wifi | C11: 82 | D11: 160 | E11: 78 | F11: 5
A12: ADESIVO COLA RATO - RATOEIRA ADESIVA HM | B12: 13 | C12: 28.5 | D12: 81.9316 | E12: 53.4316 | F12: 2
A13: Adptador bluet | C13: 2 | D13: 20 | E13: 18 | F13: 1
A14: adptador carro | C14: 10 | D14: 35 | E14: 25 | F14: 2
A15: adptador wifi | C15: 16 | D15: 30 | E15: 14 | F15: 1
A16: Afiador Amolador De Facas Tesoura Canivete Facão C/ Ventosa | B16: 3 | C16: 16 | D16: 28.0308 | E16: 12.0308 | F16: 3
A17: Afiador de facas de cozinha Restauração de ferramentas de afiação de facas de 3 estágios e lâminas polonesas | B17: 3 | C17: 41 | D17: 84.87 | E17: 43.87 | F17: 2
A18: Alicate de remoção de cabo coaxial / alicate rotativo / cortador de cabo coaxial Monster | C18: 0 | D18: 19.99 | E18: 19.99 | F18: 1
A19: Almofada de Isolamento Térmico Magnético Estação de Solda | C19: 54 | D19: 120.01 | E19: 66.01 | F19: 1
A20: Almofada de Isolamento Térmico Magnético Estação de Solda Plataforma de Manutenção resistente ao Calor Reparação Isolamento Tapete de Trabalho | B20: 4 | C20: 106 | D20: 220.87 | E20: 114.87 | F20: 3
A21: almofada termica | C21: 18 | D21: 40 | E21: 22 | F21: 1
A22: aparador de pelo nariz | C22: 9 | D22: 30 | E22: 21 | F22: 1
A23: APARELHO DE BARBEAR METAL HM-10 HOME&HOME | B23: 2 | C23: 17.5 | D23: 48.75 | E23: 31.25 | F23: 4
A24: Aparelho nariz | C24: 18 | D24: 40 | E24: 22 | F24: 2
A25: Aparelho Removedor Cravos Sucção Vácuo Extrator Espinha 4em1 | B25: 1 | C25: 55 | D25: 75.6928 | E25: 20.6928 | F25: 3
A26: apliador de tela celular | C26: 20 | D26: 40 | E26: 20 | F26: 1
A27: Aspirador de Pó e Líquido Automotivo Portátil 12V 60W com Luz de LED Preto e Vermelho | B27: 17 | C27: 554 | D27: 1398.07 | E27: 564.07 | F27: 8
A28: Avatto tuya wifi sensor de porta | C28: 16 | D28: 50 | E28: 34 | F28: 1
A29: aviao controle | C29: 35 | D29: 40 | E29: 5 | F29: 1
A30: balança 10kg | C30: 30 | D30: 40 | E30: 10 | F30: 1
A31: Balança comida | C31: 30 | D31: 50 | E31: 20 | F31: 1
A32: Balões Transparente COMPLETO DE BASTÃO Com Led Colorido + Vareta | B32: 2 | C32: 18 | D32: 37.51 | E32: 19.51 | F32: 1
A33: Barbeador de nariz | C33: 9 | D33: 15 | E33: 6 | F33: 1
A34: Barbeador inova 3780 | C34: 25 | D34: 50 | E34: 25 | F34: 1
A35: Bateria 23a 12v 1unidade Ótima Qualidade | B35: 26 | C35: 31.2 | D35: 74.26 | E35: 43.06 | F35: 1
A36: Bateria 9V Hi-Watt 6F22M | B36: 1 | C36: 2.5 | D36: 3.81 | E36: 1.31 | F36: 1
A37: Bateria 9v Hw Original Comum Não Recarregável | B37: 2 | C37: 15 | D37: 19.1336 | E37: 4.1336 | F37: 2
A38: Bateria A23 12v 1unidade Ótima Qualidade | B38: 44 | C38: 230.9 | D38: 635.3418 | E38: 379.2418 | F38: 7
A39: Bateria De Litio 3v Tipo Botão CR2025 Knup Kp-bt2025 | B39: 99 | C39: 68.033333 | D39: 309.1838 | E39: 243.8538 | F39: 9
A40: Bateria Litio 2032 Unitário Cr2032 1 unidades | B40: 447 | C40: 289.1 | D40: 1235.9996 | E40: 770.8196 | F40: 11
A41: Bateria Recarregável 6800 V 3.7 mAh 26650 Protegido Li-ion Battery para Lanterna Farol Levou Acessório | B41: 1 | C41: 15 | D41: 33.6 | E41: 18.6 | F41: 1
A42: Bateria Recarregável 6800 V 3.7 mAh Li-ion Battery para Lanterna Farol Levou Acessório | B42: 2 | C42: 24 | D42: 40.1472 | E42: 16.1472 | F42: 1
A43: Binóculos Vyper999 Pro 😱😱🔥 | C43: 40 | D43: 80 | E43: 40 | F43: 1
A44: Bluetooth car | C44: 12 | D44: 20 | E44: 8 | F44: 1
A45: Bolas LOL Surprise + 1 Boneca + 4 Cards Para Meninas | B45: 1 | C45: 6 | D45: 20.8608 | E45: 14.8608 | F45: 1
A46: bolhas moda | C46: 17 | D46: 30 | E46: 13 | F46: 1
A47: Bolsa Case Suporte Quadro Porta Celular Bike Bicicleta Fone | B47: 1 | C47: 25 | D47: 50 | E47: 25 | F47: 1
A48: bomba eletrica | C48: 28 | D48: 55 | E48: 27 | F48: 1
A49: bomba eletrica galao | C49: 18 | D49: 35 | E49: 17 | F49: 1
A50: Bomba filtro galao | C50: 20 | D50: 65 | E50: 45 | F50: 2
A51: Bomba filtro galao eletrico | C51: 22 | D51: 45 | E51: 23 | F51: 1
A52: Bomba filtro simples | C52: 20 | D52: 50 | E52: 30 | F52: 2
A53: bomba galao | C53: 10 | D53: 25 | E53: 15 | F53: 1
A54: Bomba Para Galão de Água Mineral Garrafão 10 Ou 20 Litros !! - Clink | C54: 10 | D54: 20 | E54: 10 | F54: 1
A55: Brinquedo Beyblade Tornado Extreme Top Sytem YTL 0193 Yaha | B55: 1 | C55: 10 | D55: 18.57 | E55: 8.57 | F55: 1
A56: Cabo 2m iphone | C56: 7 | D56: 15 | E56: 8 | F56: 1
A57: Cabo aux | C57: 3 | D57: 10 | E57: 7 | F57: 1
A58: Cabo auxiliar | C58: 6.5 | D58: 10 | E58: 3.5 | F58: 1
A59: Cabo Dados Carregador USB 30 Pinos Para iPhone 4 iPad iPod | B59: 4 | C59: 8 | D59: 38.03 | E59: 37.43 | F59: 2
A60: Cabo de Dados KinGo para Iphone | B60: 3 | C60: 23 | D60: 33.1538 | E60: 10.1538 | F60: 2
A61: Cabo de Dados KinGo para Iphone - 1m | B61: 1 | C61: 8 | D61: 18.75 | E61: 10.75 | F61: 1
A62: Cabo Hardline VGA 3M HLVGA 3.0 | C62: 13 | D62: 23.43 | E62: 10.43 | F62: 1
A63: Cabo hdmi 4k 10m | C63: 35 | D63: 60 | E63: 25 | F63: 1
A64: cabo ipad | C64: 9 | D64: 20 | E64: 11 | F64: 1
A65: Cabo ipega tipo c | C65: 8 | D65: 20 | E65: 12 | F65: 1
A66: cabo iphone | C66: 2 | D66: 15 | E66: 13 | F66: 1
A67: cabo magnetico | C67: 17 | D67: 40 | E67: 23 | F67: 1
A68: Cabo Micro Usb v8 , serve em vários aparelhos eletrônicos celulares | B68: 16 | C68: 165.3 | D68: 301.54 | E68: 125.04 | F68: 6
A69: Cabo RCA Cristal Injetado de 1 Metros | B69: 1 | C69: 7 | D69: 12.3 | E69: 5.3 | F69: 1
A70: Cabo USB iphone 4/4s | B70: 5 | C70: 10 | D70: 26.04 | E70: 16.04 | F70: 1
A71: cabo v8 kingo | C71: 6 | D71: 12 | E71: 6 | F71: 1
A72: cabo vga | C72: 12 | D72: 20 | E72: 8 | F72: 1
A73: Cabo Vga Hd15 - M/M O.D 3.0 | C73: 7 | D73: 15 | E73: 8 | F73: 1
A74: Cadeado Profissional Com 3 Chaves Codificadas 40mm | B74: 11 | C74: 79 | D74: 207.04 | E74: 103.99 | F74: 5
A75: Caixa 2kp | C75: 0 | D75: 100 | E75: 100 | F75: 1
A76: caixa de grave | C76: 0 | D76: 40 | E76: 40 | F76: 1
A77: caixa de som | C77: 40 | D77: 80 | E77: 40 | F77: 1
A78: Caixa jbl boombox mini | C78: 100 | D78: 110 | E78: 10 | F78: 1
A79: Calculadora Cientifica Profissional Modelo Id-8267c | B79: 14 | C79: 135.99 | D79: 386.69 | E79: 250.7 | F79: 4
A80: Caneta Testador De Dinheiro Nota Falsa Money Teste Detector | C80: 10 | D80: 59.41 | E80: 49.41 | F80: 1
A81: Capa De Braço Suporte Braçadeira De Celular Corrida Academia | B81: 2 | C81: 15 | D81: 60.81 | E81: 38.81 | F81: 2
A82: capa iphone | C82: 13 | D82: 30 | E82: 17 | F82: 1
A83: Capa Para Celular Impermeável - Aquática - Cores Sortidas | C83: 4 | D83: 12.96 | E83: 8.96 | F83: 1
A84: Capacete Ciclista Adulto Regulagem Bike Ciclismo - Promoção | C84: 70 | D84: 179.75 | E84: 109.75 | F84: 1
A85: capinha | C85: 3 | D85: 10 | E85: 7 | F85: 1
A86: Capinha a02 | C86: 7.5 | D86: 15 | E86: 7.5 | F86: 1
A87: Capinha celular | C87: 15 | D87: 30 | E87: 15 | F87: 2
A88: capinha iphone | C88: 22.8 | D88: 50 | E88: 27.2 | F88: 3
A89: carregador iphone | C89: 19 | D89: 50 | E89: 31 | F89: 1
A90: Carregador Portatil Powerbank 5.000mah Inova Com Anatel | B90: 1 | C90: 30 | D90: 51.68 | E90: 21.68 | F90: 1
A91: CARREGADOR PORTÁTIL ULTRAFINO - POWER BANK 10000mah PINENG UNIVERSAL LINHA | B91: 2 | C91: 76 | D91: 97.94 | E91: 21.94 | F91: 1
A92: carregador v8 | C92: 7 | D92: 25 | E92: 18 | F92: 1
A93: Carregador v8 hms | C93: 54 | D93: 105 | E93: 51 | F93: 3
A94: carregador v8 simples | C94: 15 | D94: 40 | E94: 25 | F94: 3
A95: carregador veicular | C95: 25 | D95: 45 | E95: 20 | F95: 2
A96: Cartao onibuns | C96: 0 | D96: 200 | E96: 200 | F96: 1
A97: case | C97: 20 | D97: 50 | E97: 30 | F97: 1
A98: case HD | C98: 30 | D98: 50 | E98: 20 | F98: 1
A99: cashback | C99: 0 | D99: 322 | E99: 322 | F99: 1
A100: celular g6 | C100: 0 | D100: 405 | E100: 405 | F100: 1
A101: Chapéu Australiano Pesca Caminhada Camping Proteção Nuca Sol | B101: 1 | C101: 16 | D101: 30.71 | E101: 14.71 | F101: 2
A102: Chapeu flamengo | C102: 19 | D102: 30 | E102: 11 | F102: 1
...

Sheet Planilha1
A1: Codigo | B1: Produtos | C1: Quantidade | D1: Valor gasto | E1: Valor venddo | F1: Valor do lucro | G1: vendas shopee | H1: Coluna1 | I1: Vendas df2 | K1: Produto | L1: Qunt | M1: Valor gasto | N1: Valor vendido | O1: lucro
A2: 58 | B2: 1PCS Glossy Multicolored Business ID Credit Card Cash Pocket Holder Wallet Aluminium Alloy Outer Plastic Inner Waterproof Case | C2: 1 | D2: =E2-F2 -> 2.5 | E2: 13.32 | F2: 10.82 | G2: vendido | H2: shopee | K2: {=_xlfn.UNIQUE(Tabela1[Produtos])} -> 1PCS Glossy Multicolored Business ID Credit Card Cash Pocket Holder Wallet Aluminium Alloy Outer Plastic Inner Waterproof Case | L2: =SUMIF(Tabela1[Produtos],K2,Tabela1[Quantidade]) -> 1 | M2: =SUMIF(Tabela1[Produtos],K2,Tabela1[Valor gasto]) -> 2.5 | N2: =SUMIF(Tabela1[Produtos],K2,Tabela1[Valor venddo]) -> 13.32 | O2: =SUMIF(Tabela1[Produtos],K2,Tabela1[Valor do lucro]) -> 10.82
A3: 538 | B3: A 70 Spray Líquido 200 ml - Nutriex | C3: 8 | D3: 56 | E3: 120.69 | F3: =SUM(E3-D3) -> 64.69 | G3: vendido | H3: Shopee | K3: A 70 Spray Líquido 200 ml - Nutriex | L3: =SUMIF(Tabela1[Produtos],K3,Tabela1[Quantidade]) -> 32 | M3: =SUMIF(Tabela1[Produtos],K3,Tabela1[Valor gasto]) -> 176 | N3: =SUMIF(Tabela1[Produtos],K3,Tabela1[Valor venddo]) -> 361.7222 | O3: =SUMIF(Tabela1[Produtos],K3,Tabela1[Valor do lucro]) -> 191.0622
A4: 898 | B4: A 70 Spray Líquido 200 ml - Nutriex | C4: 8 | D4: 48 | E4: 100.6222 | F4: =E4-D4 -> 52.6222 | G4: vendido | H4: Shopee | K4: ACENDEDOR DE FOGÃO | L4: =SUMIF(Tabela1[Produtos],K4,Tabela1[Quantidade]) -> 2 | M4: =SUMIF(Tabela1[Produtos],K4,Tabela1[Valor gasto]) -> 6 | N4: =SUMIF(Tabela1[Produtos],K4,Tabela1[Valor venddo]) -> 40.26 | O4: =SUMIF(Tabela1[Produtos],K4,Tabela1[Valor do lucro]) -> 28.26
A5: 124 | B5: A 70 Spray Líquido 200 ml - Nutriex | C5: 7 | D5: 24.5 | E5: 49.46 | F5: 24.96 | G5: vendido | H5: shopee | K5: Adaptador Fonte carregador para PSP 2000 3000 game portátil | L5: =SUMIF(Tabela1[Produtos],K5,Tabela1[Quantidade]) -> 1 | M5: =SUMIF(Tabela1[Produtos],K5,Tabela1[Valor gasto]) -> 14 | N5: =SUMIF(Tabela1[Produtos],K5,Tabela1[Valor venddo]) -> 20 | O5: =SUMIF(Tabela1[Produtos],K5,Tabela1[Valor do lucro]) -> 6
A6: 266 | B6: A 70 Spray Líquido 200 ml - Nutriex | C6: 4 | D6: 3.5 | E6: 14 | F6: 15.84 | G6: vendido | H6: Shopee | K6: Adaptador OTG USB V8 | L6: =SUMIF(Tabela1[Produtos],K7,Tabela1[Quantidade]) -> 3 | M6: =SUMIF(Tabela1[Produtos],K7,Tabela1[Valor gasto]) -> 13 | N6: =SUMIF(Tabela1[Produtos],K7,Tabela1[Valor venddo]) -> 34.56 | O6: =SUMIF(Tabela1[Produtos],K7,Tabela1[Valor do lucro]) -> 21.56
A7: 755 | B7: A 70 Spray Líquido 200 ml - Nutriex | C7: 4 | D7: 16 | E7: 38.49 | F7: 22.49 | G7: vendido | H7: Shopee | K7: Adaptador Para Fone Headset Microfone Lapela P2 X P3 Áudio | L7: =SUMIF(Tabela1[Produtos],#REF!,Tabela1[Quantidade]) -> 0 | M7: =SUMIF(Tabela1[Produtos],#REF!,Tabela1[Valor gasto]) -> 0 | N7: =SUMIF(Tabela1[Produtos],#REF!,Tabela1[Valor venddo]) -> 0 | O7: =SUMIF(Tabela1[Produtos],#REF!,Tabela1[Valor do lucro]) -> 0
A8: 586 | B8: A 70 Spray Líquido 200 ml - Nutriex | C8: 1 | D8: 28 | E8: 38.46 | F8: =E8-D8 -> 10.46 | G8: vendido | H8: bsb | K8: Adaptador Usb 2.0 Ethernet Rj45 Fácil Instalação | L8: =SUMIF(Tabela1[Produtos],K8,Tabela1[Quantidade]) -> 2 | M8: =SUMIF(Tabela1[Produtos],K8,Tabela1[Valor gasto]) -> 22 | N8: =SUMIF(Tabela1[Produtos],K8,Tabela1[Valor venddo]) -> 45.5 | O8: =SUMIF(Tabela1[Produtos],K8,Tabela1[Valor do lucro]) -> 23.5
A9: 706 | B9: ACENDEDOR DE FOGÃO | C9: 2 | D9: 6 | E9: 40.26 | F9: 28.26 | G9: vendido | H9: Shopee | K9: Adaptador Wifi | L9: =SUMIF(Tabela1[Produtos],K9,Tabela1[Quantidade]) -> 5 | M9: =SUMIF(Tabela1[Produtos],K9,Tabela1[Valor gasto]) -> 82 | N9: =SUMIF(Tabela1[Produtos],K9,Tabela1[Valor venddo]) -> 160 | O9: =SUMIF(Tabela1[Produtos],K9,Tabela1[Valor do lucro]) -> 78
A10: 433 | B10: Adaptador Fonte carregador para PSP 2000 3000 game portátil | C10: 1 | D10: 14 | E10: 20 | F10: =E10-D10 -> 6 | G10: vendido | H10: bsb | K10: ADESIVO COLA RATO - RATOEIRA ADESIVA HM | L10: =SUMIF(Tabela1[Produtos],K10,Tabela1[Quantidade]) -> 13 | M10: =SUMIF(Tabela1[Produtos],K10,Tabela1[Valor gasto]) -> 28.5 | N10: =SUMIF(Tabela1[Produtos],K10,Tabela1[Valor venddo]) -> 81.9316 | O10: =SUMIF(Tabela1[Produtos],K10,Tabela1[Valor do lucro]) -> 53.4316
A11: 690 | B11: Adaptador OTG USB V8 | C11: 1 | D11: 2.5 | E11: 8.32 | F11: 5.82 | G11: vendido | H11: Shopee | K11: adptador carro | L11: =SUMIF(Tabela1[Produtos],K11,Tabela1[Quantidade]) -> 3 | M11: =SUMIF(Tabela1[Produtos],K11,Tabela1[Valor gasto]) -> 12 | N11: =SUMIF(Tabela1[Produtos],K11,Tabela1[Valor venddo]) -> 55 | O11: =SUMIF(Tabela1[Produtos],K11,Tabela1[Valor do lucro]) -> 43
A12: 508 | B12: Adaptador Para Fone Headset Microfone Lapela P2 X P3 Áudio | C12: 1 | D12: 2 | E12: 8 | F12: =SUM(E12-D12) -> 6 | G12: vendido | H12: Shopee | K12: adptador wifi | L12: =SUMIF(Tabela1[Produtos],K12,Tabela1[Quantidade]) -> 1 | M12: =SUMIF(Tabela1[Produtos],K12,Tabela1[Valor gasto]) -> 16 | N12: =SUMIF(Tabela1[Produtos],K12,Tabela1[Valor venddo]) -> 30 | O12: =SUMIF(Tabela1[Produtos],K12,Tabela1[Valor do lucro]) -> 14
A13: 341 | B13: Adaptador Para Fone Headset Microfone Lapela P2 X P3 Áudio | C13: 1 | D13: 2 | E13: 15.01 | F13: =E13-D13 -> 13.01 | G13: vendido | H13: bsb | K13: Afiador Amolador De Facas Tesoura Canivete Facão C/ Ventosa | L13: =SUMIF(Tabela1[Produtos],K13,Tabela1[Quantidade]) -> 3 | M13: =SUMIF(Tabela1[Produtos],K13,Tabela1[Valor gasto]) -> 16 | N13: =SUMIF(Tabela1[Produtos],K13,Tabela1[Valor venddo]) -> 28.0308 | O13: =SUMIF(Tabela1[Produtos],K13,Tabela1[Valor do lucro]) -> 12.0308
A14: 587 | B14: Adaptador Para Fone Headset Microfone Lapela P2 X P3 Áudio | C14: 1 | D14: 9 | E14: 11.55 | F14: =E14-D14 -> 2.55 | G14: vendido | H14: bsb | K14: Afiador de facas de cozinha Restauração de ferramentas de afiação de facas de 3 estágios e lâminas polonesas | L14: =SUMIF(Tabela1[Produtos],K14,Tabela1[Quantidade]) -> 3 | M14: =SUMIF(Tabela1[Produtos],K14,Tabela1[Valor gasto]) -> 41 | N14: =SUMIF(Tabela1[Produtos],K14,Tabela1[Valor venddo]) -> 84.87 | O14: =SUMIF(Tabela1[Produtos],K14,Tabela1[Valor do lucro]) -> 43.87
A15: 143 | B15: Adaptador Usb 2.0 Ethernet Rj45 Fácil Instalação | C15: 1 | D15: 17 | E15: 17.5 | F15: 0.5 | G15: vendido | H15: shopee | K15: Alicate de remoção de cabo coaxial / alicate rotativo / cortador de cabo coaxial Monster | L15: =SUMIF(Tabela1[Produtos],K15,Tabela1[Quantidade]) -> 1 | M15: =SUMIF(Tabela1[Produtos],K15,Tabela1[Valor gasto]) -> 0 | N15: =SUMIF(Tabela1[Produtos],K15,Tabela1[Valor venddo]) -> 19.99 | O15: =SUMIF(Tabela1[Produtos],K15,Tabela1[Valor do lucro]) -> 19.99
A16: 59 | B16: Adaptador Usb 2.0 Ethernet Rj45 Fácil Instalação | C16: 1 | D16: =E16-F16 -> 5 | E16: 28 | F16: 23 | G16: vendido | H16: shopee | K16: Almofada de Isolamento Térmico Magnético Estação de Solda | L16: =SUMIF(Tabela1[Produtos],K16,Tabela1[Quantidade]) -> 1 | M16: =SUMIF(Tabela1[Produtos],K16,Tabela1[Valor gasto]) -> 54 | N16: =SUMIF(Tabela1[Produtos],K16,Tabela1[Valor venddo]) -> 120.01 | O16: =SUMIF(Tabela1[Produtos],K16,Tabela1[Valor do lucro]) -> 66.01
A17: 286 | B17: Adaptador Wifi | C17: 1 | D17: 16 | E17: 30 | F17: =E17-D17 -> 14 | G17: Vendido | H17: bsb | K17: Almofada de Isolamento Térmico Magnético Estação de Solda Plataforma de Manutenção resistente ao Calor Reparação Isolamento Tapete de Trabalho | L17: =SUMIF(Tabela1[Produtos],K17,Tabela1[Quantidade]) -> 16 | M17: =SUMIF(Tabela1[Produtos],K17,Tabela1[Valor gasto]) -> 232 | N17: =SUMIF(Tabela1[Produtos],K17,Tabela1[Valor venddo]) -> 515.89 | O17: =SUMIF(Tabela1[Produtos],K17,Tabela1[Valor do lucro]) -> 292.16
A18: 288 | B18: Adaptador Wifi | C18: 1 | D18: 16 | E18: 35 | F18: =E18-D18 -> 19 | G18: Vendido | H18: bsb | K18: aparador de pelo nariz | L18: =SUMIF(Tabela1[Produtos],K18,Tabela1[Quantidade]) -> 4 | M18: =SUMIF(Tabela1[Produtos],K18,Tabela1[Valor gasto]) -> 36 | N18: =SUMIF(Tabela1[Produtos],K18,Tabela1[Valor venddo]) -> 85 | O18: =SUMIF(Tabela1[Produtos],K18,Tabela1[Valor do lucro]) -> 49
A19: 554 | B19: Adaptador Wifi | C19: 1 | D19: 18 | E19: 35 | F19: =E19-D19 -> 17 | G19: vendido | H19: bsb | K19: APARELHO DE BARBEAR METAL HM-10 HOME&HOME | L19: =SUMIF(Tabela1[Produtos],K19,Tabela1[Quantidade]) -> 4 | M19: =SUMIF(Tabela1[Produtos],K19,Tabela1[Valor gasto]) -> 17.5 | N19: =SUMIF(Tabela1[Produtos],K19,Tabela1[Valor venddo]) -> 48.75 | O19: =SUMIF(Tabela1[Produtos],K19,Tabela1[Valor do lucro]) -> 31.25
A20: 573 | B20: Adaptador Wifi | C20: 1 | D20: 16 | E20: 30 | F20: =E20-D20 -> 14 | G20: vendido | H20: bsb | K20: Aparelho Removedor Cravos Sucção Vácuo Extrator Espinha 4em1 | L20: =SUMIF(Tabela1[Produtos],K20,Tabela1[Quantidade]) -> 3 | M20: =SUMIF(Tabela1[Produtos],K20,Tabela1[Valor gasto]) -> 55 | N20: =SUMIF(Tabela1[Produtos],K20,Tabela1[Valor venddo]) -> 75.6928 | O20: =SUMIF(Tabela1[Produtos],K20,Tabela1[Valor do lucro]) -> 20.6928
A21: 574 | B21: Adaptador Wifi | C21: 1 | D21: 16 | E21: 30 | F21: =E21-D21 -> 14 | G21: vendido | H21: bsb | K21: apliador de tela celular | L21: =SUMIF(Tabela1[Produtos],K21,Tabela1[Quantidade]) -> 1 | M21: =SUMIF(Tabela1[Produtos],K21,Tabela1[Valor gasto]) -> 20 | N21: =SUMIF(Tabela1[Produtos],K21,Tabela1[Valor venddo]) -> 40 | O21: =SUMIF(Tabela1[Produtos],K21,Tabela1[Valor do lucro]) -> 20
A22: 756 | B22: ADESIVO COLA RATO - RATOEIRA ADESIVA HM | C22: 8 | D22: 16 | E22: 54.15 | F22: 38.15 | G22: vendido | H22: Shopee | K22: Aspirador de Pó e Líquido Automotivo Portátil 12V 60W com Luz de LED Preto e Vermelho | L22: =SUMIF(Tabela1[Produtos],K22,Tabela1[Quantidade]) -> 20 | M22: =SUMIF(Tabela1[Produtos],K22,Tabela1[Valor gasto]) -> 554 | N22: =SUMIF(Tabela1[Produtos],K22,Tabela1[Valor venddo]) -> 1398.07 | O22: =SUMIF(Tabela1[Produtos],K22,Tabela1[Valor do lucro]) -> 564.07
A23: 899 | B23: ADESIVO COLA RATO - RATOEIRA ADESIVA HM | C23: 5 | D23: 12.5 | E23: 27.7816 | F23: =E23-D23 -> 15.2816 | G23: vendido | H23: Shopee | K23: Avatto tuya wifi sensor de porta | L23: =SUMIF(Tabela1[Produtos],K23,Tabela1[Quantidade]) -> 1 | M23: =SUMIF(Tabela1[Produtos],K23,Tabela1[Valor gasto]) -> 16 | N23: =SUMIF(Tabela1[Produtos],K23,Tabela1[Valor venddo]) -> 50 | O23: =SUMIF(Tabela1[Produtos],K23,Tabela1[Valor do lucro]) -> 34
A24: 565 | B24: adptador carro | C24: 1 | D24: 2 | E24: 20 | F24: =E24-D24 -> 18 | G24: vendido | H24: bsb | K24: aviao controle | L24: =SUMIF(Tabela1[Produtos],K24,Tabela1[Quantidade]) -> 1 | M24: =SUMIF(Tabela1[Produtos],K24,Tabela1[Valor gasto]) -> 35 | N24: =SUMIF(Tabela1[Produtos],K24,Tabela1[Valor venddo]) -> 40 | O24: =SUMIF(Tabela1[Produtos],K24,Tabela1[Valor do lucro]) -> 5
A25: 651 | B25: adptador carro | C25: 1 | D25: 2 | E25: 20 | F25: =E25-D25 -> 18 | G25: vendido | H25: bsb | K25: balança 10kg | L25: =SUMIF(Tabela1[Produtos],K25,Tabela1[Quantidade]) -> 2 | M25: =SUMIF(Tabela1[Produtos],K25,Tabela1[Valor gasto]) -> 60 | N25: =SUMIF(Tabela1[Produtos],K25,Tabela1[Valor venddo]) -> 90 | O25: =SUMIF(Tabela1[Produtos],K25,Tabela1[Valor do lucro]) -> 30
A26: 638 | B26: adptador carro | C26: 1 | D26: 8 | E26: 15 | F26: =E26-D26 -> 7 | G26: vendido | H26: bsb | K26: Balões Transparente COMPLETO DE BASTÃO Com Led Colorido + Vareta | L26: =SUMIF(Tabela1[Produtos],K26,Tabela1[Quantidade]) -> 2 | M26: =SUMIF(Tabela1[Produtos],K26,Tabela1[Valor gasto]) -> 18 | N26: =SUMIF(Tabela1[Produtos],K26,Tabela1[Valor venddo]) -> 37.51 | O26: =SUMIF(Tabela1[Produtos],K26,Tabela1[Valor do lucro]) -> 19.51
A27: 334 | B27: adptador wifi | C27: 1 | D27: 16 | E27: 30 | F27: =E27-D27 -> 14 | G27: vendido | H27: bsb | K27: Barbeador inova 3780 | L27: =SUMIF(Tabela1[Produtos],K27,Tabela1[Quantidade]) -> 1 | M27: =SUMIF(Tabela1[Produtos],K27,Tabela1[Valor gasto]) -> 25 | N27: =SUMIF(Tabela1[Produtos],K27,Tabela1[Valor venddo]) -> 50 | O27: =SUMIF(Tabela1[Produtos],K27,Tabela1[Valor do lucro]) -> 25
A28: 687 | B28: Afiador Amolador De Facas Tesoura Canivete Facão C/ Ventosa | C28: 1 | D28: 5 | E28: 10 | F28: 5 | G28: vendido | H28: Shopee | K28: Bateria 9v Hw Original Comum Não Recarregável | L28: =SUMIF(Tabela1[Produtos],K28,Tabela1[Quantidade]) -> 4 | M28: =SUMIF(Tabela1[Produtos],K28,Tabela1[Valor gasto]) -> 17.5 | N28: =SUMIF(Tabela1[Produtos],K28,Tabela1[Valor venddo]) -> 22.9436 | O28: =SUMIF(Tabela1[Produtos],K28,Tabela1[Valor do lucro]) -> 5.4436
A29: 822 | B29: Afiador Amolador De Facas Tesoura Canivete Facão C/ Ventosa | C29: 1 | D29: 5 | E29: 10.29 | F29: 5.29 | G29: vendido | H29: Shopee | K29: Bateria A23 12v 1unidade Ótima Qualidade | L29: =SUMIF(Tabela1[Produtos],K29,Tabela1[Quantidade]) -> 73 | M29: =SUMIF(Tabela1[Produtos],K29,Tabela1[Valor gasto]) -> 262.1 | N29: =SUMIF(Tabela1[Produtos],K29,Tabela1[Valor venddo]) -> 709.6018 | O29: =SUMIF(Tabela1[Produtos],K29,Tabela1[Valor do lucro]) -> 422.3018
A30: 900 | B30: Afiador Amolador De Facas Tesoura Canivete Facão C/ Ventosa | C30: 1 | D30: 6 | E30: 7.7408 | F30: =E30-D30 -> 1.7408 | G30: vendido | H30: Shopee | K30: Bateria De Litio 3v Tipo Botão CR2025 Knup Kp-bt2025 | L30: =SUMIF(Tabela1[Produtos],K30,Tabela1[Quantidade]) -> 102 | M30: =SUMIF(Tabela1[Produtos],K30,Tabela1[Valor gasto]) -> 68.033333 | N30: =SUMIF(Tabela1[Produtos],K30,Tabela1[Valor venddo]) -> 309.1838 | O30: =SUMIF(Tabela1[Produtos],K30,Tabela1[Valor do lucro]) -> 243.8538
A31: 118 | B31: Afiador de facas de cozinha Restauração de ferramentas de afiação de facas de 3 estágios e lâminas polonesas | C31: 2 | D31: 26 | E31: 64.87 | F31: 38.87 | G31: vendido | H31: shopee | K31: Bateria Litio 2032 Unitário Cr2032 1 unidades | L31: =SUMIF(Tabela1[Produtos],K31,Tabela1[Quantidade]) -> 451 | M31: =SUMIF(Tabela1[Produtos],K31,Tabela1[Valor gasto]) -> 289.1 | N31: =SUMIF(Tabela1[Produtos],K31,Tabela1[Valor venddo]) -> 1235.9996 | O31: =SUMIF(Tabela1[Produtos],K31,Tabela1[Valor do lucro]) -> 770.8196
A32: 823 | B32: Afiador de facas de cozinha Restauração de ferramentas de afiação de facas de 3 estágios e lâminas polonesas | C32: 1 | D32: 15 | E32: 20 | F32: 5 | G32: vendido | H32: Shopee | K32: Bateria Recarregável 6800 V 3.7 mAh 26650 Protegido Li-ion Battery para Lanterna Farol Levou Acessório | L32: =SUMIF(Tabela1[Produtos],K32,Tabela1[Quantidade]) -> 3 | M32: =SUMIF(Tabela1[Produtos],K32,Tabela1[Valor gasto]) -> 39 | N32: =SUMIF(Tabela1[Produtos],K32,Tabela1[Valor venddo]) -> 73.7472 | O32: =SUMIF(Tabela1[Produtos],K32,Tabela1[Valor do lucro]) -> 34.7472
A33: 588 | B33: Alicate de remoção de cabo coaxial / alicate rotativo / cortador de cabo coaxial Monster | C33: 1 | D33: 0 | E33: 19.99 | F33: =E33-D33 -> 19.99 | G33: vendido | H33: bsb | K33: Binóculos Vyper999 Pro 😱😱🔥 | L33: =SUMIF(Tabela1[Produtos],K33,Tabela1[Quantidade]) -> 1 | M33: =SUMIF(Tabela1[Produtos],K33,Tabela1[Valor gasto]) -> 40 | N33: =SUMIF(Tabela1[Produtos],K33,Tabela1[Valor venddo]) -> 80 | O33: =SUMIF(Tabela1[Produtos],K33,Tabela1[Valor do lucro]) -> 40
A34: 434 | B34: Almofada de Isolamento Térmico Magnético Estação de Solda | C34: 1 | D34: 54 | E34: 120.01 | F34: =E34-D34 -> 66.01 | G34: vendido | H34: bsb | K34: Bluetooth car | L34: =SUMIF(Tabela1[Produtos],K34,Tabela1[Quantidade]) -> 1 | M34: =SUMIF(Tabela1[Produtos],K34,Tabela1[Valor gasto]) -> 12 | N34: =SUMIF(Tabela1[Produtos],K34,Tabela1[Valor venddo]) -> 20 | O34: =SUMIF(Tabela1[Produtos],K34,Tabela1[Valor do lucro]) -> 8
A35: 115 | B35: Almofada de Isolamento Térmico Magnético Estação de Solda Plataforma de Manutenção resistente ao Calor Reparação Isolamento Tapete de Trabalho | C35: 4 | D35: 52 | E35: 131.3 | F35: 79.3 | G35: vendido | H35: shopee | K35: Bolas LOL Surprise + 1 Boneca + 4 Cards Para Meninas | L35: =SUMIF(Tabela1[Produtos],K35,Tabela1[Quantidade]) -> 1 | M35: =SUMIF(Tabela1[Produtos],K35,Tabela1[Valor gasto]) -> 6 | N35: =SUMIF(Tabela1[Produtos],K35,Tabela1[Valor venddo]) -> 20.8608 | O35: =SUMIF(Tabela1[Produtos],K35,Tabela1[Valor do lucro]) -> 14.8608
A36: 54 | B36: Almofada de Isolamento Térmico Magnético Estação de Solda Plataforma de Manutenção resistente ao Calor Reparação Isolamento Tapete de Trabalho | C36: 1 | D36: =E36-F36 -> 36 | E36: 58.98 | F36: 22.98 | G36: vendido | H36: shopee | K36: bolhas moda | L36: =SUMIF(Tabela1[Produtos],K36,Tabela1[Quantidade]) -> 1 | M36: =SUMIF(Tabela1[Produtos],K36,Tabela1[Valor gasto]) -> 17 | N36: =SUMIF(Tabela1[Produtos],K36,Tabela1[Valor venddo]) -> 30 | O36: =SUMIF(Tabela1[Produtos],K36,Tabela1[Valor do lucro]) -> 13
A37: 342 | B37: Almofada de Isolamento Térmico Magnético Estação de Solda Plataforma de Manutenção resistente ao Calor Reparação Isolamento Tapete de Trabalho | C37: 1 | D37: 18 | E37: 30.59 | F37: =E37-D37 -> 12.59 | G37: vendido | H37: bsb | K37: Bolsa Case Suporte Quadro Porta Celular Bike Bicicleta Fone | L37: =SUMIF(Tabela1[Produtos],K37,Tabela1[Quantidade]) -> 1 | M37: =SUMIF(Tabela1[Produtos],K37,Tabela1[Valor gasto]) -> 25 | N37: =SUMIF(Tabela1[Produtos],K37,Tabela1[Valor venddo]) -> 50 | O37: =SUMIF(Tabela1[Produtos],K37,Tabela1[Valor do lucro]) -> 25
A38: 423 | B38: Almofada de Isolamento Térmico Magnético Estação de Solda Plataforma de Manutenção resistente ao Calor Reparação Isolamento Tapete de Trabalho | C38: 1 | D38: 18 | E38: 40 | F38: =E38-D38 -> 22 | G38: vendido | H38: bsb | K38: Bomba filtro galao | L38: =SUMIF(Tabela1[Produtos],K38,Tabela1[Quantidade]) -> 6 | M38: =SUMIF(Tabela1[Produtos],K38,Tabela1[Valor gasto]) -> 60 | N38: =SUMIF(Tabela1[Produtos],K38,Tabela1[Valor venddo]) -> 160 | O38: =SUMIF(Tabela1[Produtos],K38,Tabela1[Valor do lucro]) -> 100
A39: 614 | B39: Almofada de Isolamento Térmico Magnético Estação de Solda Plataforma de Manutenção resistente ao Calor Reparação Isolamento Tapete de Trabalho | C39: 1 | D39: 18 | E39: 31.31 | F39: =E39-D39 -> 13.31 | G39: vendido | H39: bsb | K39: Bomba filtro galao eletrico | L39: =SUMIF(Tabela1[Produtos],K39,Tabela1[Quantidade]) -> 3 | M39: =SUMIF(Tabela1[Produtos],K39,Tabela1[Valor gasto]) -> 68 | N39: =SUMIF(Tabela1[Produtos],K39,Tabela1[Valor venddo]) -> 135 | O39: =SUMIF(Tabela1[Produtos],K39,Tabela1[Valor do lucro]) -> 67
A40: 239 | B40: Almofada de Isolamento Térmico Magnético Estação de Solda Plataforma de Manutenção resistente ao Calor Reparação Isolamento Tapete de Trabalho | C40: 4 | D40: 18 | E40: 72 | F40: 62.27 | G40: vendido | H40: Shopee | K40: Brinquedo Beyblade Tornado Extreme Top Sytem YTL 0193 Yaha | L40: =SUMIF(Tabela1[Produtos],K40,Tabela1[Quantidade]) -> 1 | M40: =SUMIF(Tabela1[Produtos],K40,Tabela1[Valor gasto]) -> 10 | N40: =SUMIF(Tabela1[Produtos],K40,Tabela1[Valor venddo]) -> 18.57 | O40: =SUMIF(Tabela1[Produtos],K40,Tabela1[Valor do lucro]) -> 8.57
A41: 316 | B41: Almofada de Isolamento Térmico Magnético Estação de Solda Plataforma de Manutenção resistente ao Calor Reparação Isolamento Tapete de Trabalho | C41: 1 | D41: 18 | E41: 31.12 | F41: 13.12 | G41: Vendido | H41: Shopee | K41: Cabo 2m iphone | L41: =SUMIF(Tabela1[Produtos],K41,Tabela1[Quantidade]) -> 1 | M41: =SUMIF(Tabela1[Produtos],K41,Tabela1[Valor gasto]) -> 7 | N41: =SUMIF(Tabela1[Produtos],K41,Tabela1[Valor venddo]) -> 15 | O41: =SUMIF(Tabela1[Produtos],K41,Tabela1[Valor do lucro]) -> 8
A42: 523 | B42: Almofada de Isolamento Térmico Magnético Estação de Solda Plataforma de Manutenção resistente ao Calor Reparação Isolamento Tapete de Trabalho | C42: 1 | D42: 18 | E42: 40.59 | F42: =SUM(E42-D42) -> 22.59 | G42: vendido | H42: Shopee | K42: Cabo auxiliar | L42: =SUMIF(Tabela1[Produtos],K42,Tabela1[Quantidade]) -> 2 | M42: =SUMIF(Tabela1[Produtos],K42,Tabela1[Valor gasto]) -> 9.5 | N42: =SUMIF(Tabela1[Produtos],K42,Tabela1[Valor venddo]) -> 20 | O42: =SUMIF(Tabela1[Produtos],K42,Tabela1[Valor do lucro]) -> 10.5
A43: 29 | B43: Almofada de Isolamento Térmico Magnético Estação de Solda Plataforma de Manutenção resistente ao Calor Reparação Isolamento Tapete de Trabalho | C43: 1 | D43: 18 | E43: 40 | F43: =E43-D43 -> 22 | G43: vendido | H43: bsb | K43: Cabo Dados Carregador USB 30 Pinos Para iPhone 4 iPad iPod | L43: =SUMIF(Tabela1[Produtos],K43,Tabela1[Quantidade]) -> 4 | M43: =SUMIF(Tabela1[Produtos],K43,Tabela1[Valor gasto]) -> 8 | N43: =SUMIF(Tabela1[Produtos],K43,Tabela1[Valor venddo]) -> 38.03 | O43: =SUMIF(Tabela1[Produtos],K43,Tabela1[Valor do lucro]) -> 37.43
A44: 97 | B44: Almofada de Isolamento Térmico Magnético Estação de Solda Plataforma de Manutenção resistente ao Calor Reparação Isolamento Tapete de Trabalho | C44: 1 | D44: 18 | E44: 40 | F44: =E44-D44 -> 22 | G44: vendido | H44: bsb | K44: Cabo de Dados KinGo para Iphone | L44: =SUMIF(Tabela1[Produtos],K44,Tabela1[Quantidade]) -> 3 | M44: =SUMIF(Tabela1[Produtos],K44,Tabela1[Valor gasto]) -> 23 | N44: =SUMIF(Tabela1[Produtos],K44,Tabela1[Valor venddo]) -> 33.1538 | O44: =SUMIF(Tabela1[Produtos],K44,Tabela1[Valor do lucro]) -> 10.1538
A45: 194 | B45: aparador de pelo nariz | C45: 1 | D45: 9 | E45: 30 | F45: =E45-D45 -> 21 | G45: vendido | H45: bsb | K45: Cabo de Dados KinGo para Iphone - 1m | L45: =SUMIF(Tabela1[Produtos],K45,Tabela1[Quantidade]) -> 1 | M45: =SUMIF(Tabela1[Produtos],K45,Tabela1[Valor gasto]) -> 8 | N45: =SUMIF(Tabela1[Produtos],K45,Tabela1[Valor venddo]) -> 18.75 | O45: =SUMIF(Tabela1[Produtos],K45,Tabela1[Valor do lucro]) -> 10.75
A46: 275 | B46: aparador de pelo nariz | C46: 1 | D46: 9 | E46: 20 | F46: =E46-D46 -> 11 | G46: Vendido | H46: bsb | K46: Cabo Hardline VGA 3M HLVGA 3.0 | L46: =SUMIF(Tabela1[Produtos],K46,Tabela1[Quantidade]) -> 1 | M46: =SUMIF(Tabela1[Produtos],K46,Tabela1[Valor gasto]) -> 13 | N46: =SUMIF(Tabela1[Produtos],K46,Tabela1[Valor venddo]) -> 23.43 | O46: =SUMIF(Tabela1[Produtos],K46,Tabela1[Valor do lucro]) -> 10.43
A47: 287 | B47: aparador de pelo nariz | C47: 1 | D47: 9 | E47: 20 | F47: =E47-D47 -> 11 | G47: Vendido | H47: bsb | K47: Cabo hdmi 4k 10m | L47: =SUMIF(Tabela1[Produtos],K47,Tabela1[Quantidade]) -> 1 | M47: =SUMIF(Tabela1[Produtos],K47,Tabela1[Valor gasto]) -> 35 | N47: =SUMIF(Tabela1[Produtos],K47,Tabela1[Valor venddo]) -> 60 | O47: =SUMIF(Tabela1[Produtos],K47,Tabela1[Valor do lucro]) -> 25
A48: 2 | B48: aparador de pelo nariz | C48: 1 | D48: 9 | E48: 15 | F48: =E48-D48 -> 6 | G48: vendido | H48: bsb | K48: cabo ipad | L48: =SUMIF(Tabela1[Produtos],K48,Tabela1[Quantidade]) -> 1 | M48: =SUMIF(Tabela1[Produtos],K48,Tabela1[Valor gasto]) -> 9 | N48: =SUMIF(Tabela1[Produtos],K48,Tabela1[Valor venddo]) -> 20 | O48: =SUMIF(Tabela1[Produtos],K48,Tabela1[Valor do lucro]) -> 11
A49: 290 | B49: APARELHO DE BARBEAR METAL HM-10 HOME&HOME | C49: 1 | D49: 2.5 | E49: 7.5 | F49: 5 | G49: Vendido | H49: Shopee | K49: Cabo ipega tipo c | L49: =SUMIF(Tabela1[Produtos],K49,Tabela1[Quantidade]) -> 1 | M49: =SUMIF(Tabela1[Produtos],K49,Tabela1[Valor gasto]) -> 8 | N49: =SUMIF(Tabela1[Produtos],K49,Tabela1[Valor venddo]) -> 20 | O49: =SUMIF(Tabela1[Produtos],K49,Tabela1[Valor do lucro]) -> 12
A50: 509 | B50: APARELHO DE BARBEAR METAL HM-10 HOME&HOME | C50: 1 | D50: 2.5 | E50: 10 | F50: =SUM(E50-D50) -> 7.5 | G50: vendido | H50: Shopee | K50: cabo iphone | L50: =SUMIF(Tabela1[Produtos],K50,Tabela1[Quantidade]) -> 1 | M50: =SUMIF(Tabela1[Produtos],K50,Tabela1[Valor gasto]) -> 2 | N50: =SUMIF(Tabela1[Produtos],K50,Tabela1[Valor venddo]) -> 15 | O50: =SUMIF(Tabela1[Produtos],K50,Tabela1[Valor do lucro]) -> 13
A51: 60 | B51: APARELHO DE BARBEAR METAL HM-10 HOME&HOME | C51: 1 | D51: =E51-F51 -> 2.5 | E51: 5 | F51: 2.5 | G51: vendido | H51: shopee | K51: cabo magnetico | L51: =SUMIF(Tabela1[Produtos],K51,Tabela1[Quantidade]) -> 1 | M51: =SUMIF(Tabela1[Produtos],K51,Tabela1[Valor gasto]) -> 17 | N51: =SUMIF(Tabela1[Produtos],K51,Tabela1[Valor venddo]) -> 40 | O51: =SUMIF(Tabela1[Produtos],K51,Tabela1[Valor do lucro]) -> 23
A52: 435 | B52: APARELHO DE BARBEAR METAL HM-10 HOME&HOME | C52: 1 | D52: 10 | E52: 26.25 | F52: =E52-D52 -> 16.25 | G52: vendido | H52: bsb | K52: Cabo Micro Usb v8 , serve em vários aparelhos eletrônicos celulares | L52: =SUMIF(Tabela1[Produtos],K52,Tabela1[Quantidade]) -> 19 | M52: =SUMIF(Tabela1[Produtos],K52,Tabela1[Valor gasto]) -> 165.3 | N52: =SUMIF(Tabela1[Produtos],K52,Tabela1[Valor venddo]) -> 301.54 | O52: =SUMIF(Tabela1[Produtos],K52,Tabela1[Valor do lucro]) -> 125.04
A53: 901 | B53: Aparelho Removedor Cravos Sucção Vácuo Extrator Espinha 4em1 | C53: 1 | D53: 25 | E53: 20.5328 | F53: =E53-D53 -> -4.4672 | G53: vendido | H53: Shopee | K53: Cabo RCA Cristal Injetado de 1 Metros | L53: =SUMIF(Tabela1[Produtos],K53,Tabela1[Quantidade]) -> 1 | M53: =SUMIF(Tabela1[Produtos],K53,Tabela1[Valor gasto]) -> 7 | N53: =SUMIF(Tabela1[Produtos],K53,Tabela1[Valor venddo]) -> 12.3 | O53: =SUMIF(Tabela1[Produtos],K53,Tabela1[Valor do lucro]) -> 5.3
A54: 343 | B54: Aparelho Removedor Cravos Sucção Vácuo Extrator Espinha 4em1 | C54: 1 | D54: 10 | E54: 28.41 | F54: =E54-D54 -> 18.41 | G54: vendido | H54: bsb | K54: Cabo USB iphone 4/4s | L54: =SUMIF(Tabela1[Produtos],K54,Tabela1[Quantidade]) -> 5 | M54: =SUMIF(Tabela1[Produtos],K54,Tabela1[Valor gasto]) -> 10 | N54: =SUMIF(Tabela1[Produtos],K54,Tabela1[Valor venddo]) -> 26.04 | O54: =SUMIF(Tabela1[Produtos],K54,Tabela1[Valor do lucro]) -> 16.04
A55: 589 | B55: Aparelho Removedor Cravos Sucção Vácuo Extrator Espinha 4em1 | C55: 1 | D55: 20 | E55: 26.75 | F55: =E55-D55 -> 6.75 | G55: vendido | H55: bsb | K55: cabo v8 kingo | L55: =SUMIF(Tabela1[Produtos],K55,Tabela1[Quantidade]) -> 1 | M55: =SUMIF(Tabela1[Produtos],K55,Tabela1[Valor gasto]) -> 6 | N55: =SUMIF(Tabela1[Produtos],K55,Tabela1[Valor venddo]) -> 12 | O55: =SUMIF(Tabela1[Produtos],K55,Tabela1[Valor do lucro]) -> 6
A56: 652 | B56: apliador de tela celular | C56: 1 | D56: 20 | E56: 40 | F56: =E56-D56 -> 20 | G56: vendido | H56: bsb | K56: cabo vga | L56: =SUMIF(Tabela1[Produtos],K56,Tabela1[Quantidade]) -> 1 | M56: =SUMIF(Tabela1[Produtos],K56,Tabela1[Valor gasto]) -> 12 | N56: =SUMIF(Tabela1[Produtos],K56,Tabela1[Valor venddo]) -> 20 | O56: =SUMIF(Tabela1[Produtos],K56,Tabela1[Valor do lucro]) -> 8
A57: 713 | B57: Aspirador de Pó e Líquido Automotivo Portátil 12V 60W com Luz de LED Preto e Vermelho | C57: 9 | D57: 35 | E57: 505.89 | F57: 190.89 | G57: vendido | H57: Shopee | K57: Cabo Vga Hd15 - M/M O.D 3.0 | L57: =SUMIF(Tabela1[Produtos],K57,Tabela1[Quantidade]) -> 1 | M57: =SUMIF(Tabela1[Produtos],K57,Tabela1[Valor gasto]) -> 7 | N57: =SUMIF(Tabela1[Produtos],K57,Tabela1[Valor venddo]) -> 15 | O57: =SUMIF(Tabela1[Produtos],K57,Tabela1[Valor do lucro]) -> 8
A58: 824 | B58: Aspirador de Pó e Líquido Automotivo Portátil 12V 60W com Luz de LED Preto e Vermelho | C58: 3 | D58: 114 | E58: 206.32 | F58: 92.32 | G58: vendido | H58: Shopee | K58: Cadeado Profissional Com 3 Chaves Codificadas 40mm | L58: =SUMIF(Tabela1[Produtos],K58,Tabela1[Quantidade]) -> 13 | M58: =SUMIF(Tabela1[Produtos],K58,Tabela1[Valor gasto]) -> 79 | N58: =SUMIF(Tabela1[Produtos],K58,Tabela1[Valor venddo]) -> 207.04 | O58: =SUMIF(Tabela1[Produtos],K58,Tabela1[Valor do lucro]) -> 103.99
A59: 529 | B59: Aspirador de Pó e Líquido Automotivo Portátil 12V 60W com Luz de LED Preto e Vermelho | C59: 2 | D59: 60 | E59: 109.98 | F59: =SUM(E59-D59) -> 49.98 | G59: vendido | H59: Shopee | K59: Caixa jbl boombox mini | L59: =SUMIF(Tabela1[Produtos],K59,Tabela1[Quantidade]) -> 1 | M59: =SUMIF(Tabela1[Produtos],K59,Tabela1[Valor gasto]) -> 100 | N59: =SUMIF(Tabela1[Produtos],K59,Tabela1[Valor venddo]) -> 110 | O59: =SUMIF(Tabela1[Produtos],K59,Tabela1[Valor do lucro]) -> 10
A60: 757 | B60: Aspirador de Pó e Líquido Automotivo Portátil 12V 60W com Luz de LED Preto e Vermelho | C60: 2 | D60: 70 | E60: 98.65 | F60: 28.65 | G60: vendido | H60: Shopee | K60: Calculadora Cientifica Profissional Modelo Id-8267c | L60: =SUMIF(Tabela1[Produtos],K60,Tabela1[Quantidade]) -> 15 | M60: =SUMIF(Tabela1[Produtos],K60,Tabela1[Valor gasto]) -> 135.99 | N60: =SUMIF(Tabela1[Produtos],K60,Tabela1[Valor venddo]) -> 386.69 | O60: =SUMIF(Tabela1[Produtos],K60,Tabela1[Valor do lucro]) -> 250.7
A61: 902 | B61: Aspirador de Pó e Líquido Automotivo Portátil 12V 60W com Luz de LED Preto e Vermelho | C61: 1 | D61: 35 | E61: 45.92 | F61: =E61-D61 -> 10.92 | G61: vendido | H61: Shopee | K61: Caneta Testador De Dinheiro Nota Falsa Money Teste Detector | L61: =SUMIF(Tabela1[Produtos],K61,Tabela1[Quantidade]) -> 1 | M61: =SUMIF(Tabela1[Produtos],K61,Tabela1[Valor gasto]) -> 10 | N61: =SUMIF(Tabela1[Produtos],K61,Tabela1[Valor venddo]) -> 59.41 | O61: =SUMIF(Tabela1[Produtos],K61,Tabela1[Valor do lucro]) -> 49.41
A62: 344 | B62: Aspirador de Pó e Líquido Automotivo Portátil 12V 60W com Luz de LED Preto e Vermelho | C62: 1 | D62: 30 | E62: 59.99 | F62: =E62-D62 -> 29.99 | G62: vendido | H62: bsb | K62: Capa De Braço Suporte Braçadeira De Celular Corrida Academia | L62: =SUMIF(Tabela1[Produtos],K62,Tabela1[Quantidade]) -> 3 | M62: =SUMIF(Tabela1[Produtos],K62,Tabela1[Valor gasto]) -> 15 | N62: =SUMIF(Tabela1[Produtos],K62,Tabela1[Valor venddo]) -> 60.81 | O62: =SUMIF(Tabela1[Produtos],K62,Tabela1[Valor do lucro]) -> 38.81
A63: 436 | B63: Aspirador de Pó e Líquido Automotivo Portátil 12V 60W com Luz de LED Preto e Vermelho | C63: 1 | D63: 30 | E63: 66.07 | F63: =E63-D63 -> 36.07 | G63: vendido | H63: bsb | K63: capa iphone | L63: =SUMIF(Tabela1[Produtos],K63,Tabela1[Quantidade]) -> 1 | M63: =SUMIF(Tabela1[Produtos],K63,Tabela1[Valor gasto]) -> 13 | N63: =SUMIF(Tabela1[Produtos],K63,Tabela1[Valor venddo]) -> 30 | O63: =SUMIF(Tabela1[Produtos],K63,Tabela1[Valor do lucro]) -> 17
A64: 590 | B64: Aspirador de Pó e Líquido Automotivo Portátil 12V 60W com Luz de LED Preto e Vermelho | C64: 1 | D64: 180 | E64: 305.25 | F64: =E64-D64 -> 125.25 | G64: vendido | H64: bsb | K64: Capa Para Celular Impermeável - Aquática - Cores Sortidas | L64: =SUMIF(Tabela1[Produtos],K64,Tabela1[Quantidade]) -> 1 | M64: =SUMIF(Tabela1[Produtos],K64,Tabela1[Valor gasto]) -> 4 | N64: =SUMIF(Tabela1[Produtos],K64,Tabela1[Valor venddo]) -> 12.96 | O64: =SUMIF(Tabela1[Produtos],K64,Tabela1[Valor do lucro]) -> 8.96
A65: 662 | B65: Avatto tuya wifi sensor de porta | C65: 1 | D65: 16 | E65: 50 | F65: =E65-D65 -> 34 | G65: vendido | H65: bsb | K65: Capacete Ciclista Adulto Regulagem Bike Ciclismo - Promoção | L65: =SUMIF(Tabela1[Produtos],K65,Tabela1[Quantidade]) -> 1 | M65: =SUMIF(Tabela1[Produtos],K65,Tabela1[Valor gasto]) -> 70 | N65: =SUMIF(Tabela1[Produtos],K65,Tabela1[Valor venddo]) -> 179.75 | O65: =SUMIF(Tabela1[Produtos],K65,Tabela1[Valor do lucro]) -> 109.75
A66: 796 | B66: aviao controle | C66: 1 | D66: 35 | E66: 40 | F66: =E66-D66 -> 5 | G66: vendido | H66: bsb | K66: capinha | L66: =SUMIF(Tabela1[Produtos],K66,Tabela1[Quantidade]) -> 1 | M66: =SUMIF(Tabela1[Produtos],K66,Tabela1[Valor gasto]) -> 3 | N66: =SUMIF(Tabela1[Produtos],K66,Tabela1[Valor venddo]) -> 10 | O66: =SUMIF(Tabela1[Produtos],K66,Tabela1[Valor do lucro]) -> 7
A67: 1 | B67: balança 10kg | C67: 1 | D67: 30 | E67: 40 | F67: =E67-D67 -> 10 | G67: vendido | H67: bsb | K67: Capinha celular | L67: =SUMIF(Tabela1[Produtos],K67,Tabela1[Quantidade]) -> 4 | M67: =SUMIF(Tabela1[Produtos],K67,Tabela1[Valor gasto]) -> 25.3 | N67: =SUMIF(Tabela1[Produtos],K67,Tabela1[Valor venddo]) -> 55 | O67: =SUMIF(Tabela1[Produtos],K67,Tabela1[Valor do lucro]) -> 29.7
A68: 422 | B68: balança 10kg | C68: 1 | D68: 30 | E68: 50 | F68: =E68-D68 -> 20 | G68: vendido | H68: bsb | K68: Capinha iphone | L68: =SUMIF(Tabela1[Produtos],K68,Tabela1[Quantidade]) -> 2 | M68: =SUMIF(Tabela1[Produtos],K68,Tabela1[Valor gasto]) -> 20 | N68: =SUMIF(Tabela1[Produtos],K68,Tabela1[Valor venddo]) -> 40 | O68: =SUMIF(Tabela1[Produtos],K68,Tabela1[Valor do lucro]) -> 20
A69: 758 | B69: Balões Transparente COMPLETO DE BASTÃO Com Led Colorido + Vareta | C69: 2 | D69: 18 | E69: 37.51 | F69: 19.51 | G69: vendido | H69: Shopee | K69: carregador iphone | L69: =SUMIF(Tabela1[Produtos],K69,Tabela1[Quantidade]) -> 1 | M69: =SUMIF(Tabela1[Produtos],K69,Tabela1[Valor gasto]) -> 19 | N69: =SUMIF(Tabela1[Produtos],K69,Tabela1[Valor venddo]) -> 50 | O69: =SUMIF(Tabela1[Produtos],K69,Tabela1[Valor do lucro]) -> 31
A70: 3 | B70: Barbeador inova 3780 | C70: 1 | D70: 25 | E70: 50 | F70: =E70-D70 -> 25 | G70: vendido | H70: bsb | K70: Carregador Portatil Powerbank 5.000mah Inova Com Anatel | L70: =SUMIF(Tabela1[Produtos],K70,Tabela1[Quantidade]) -> 1 | M70: =SUMIF(Tabela1[Produtos],K70,Tabela1[Valor gasto]) -> 30 | N70: =SUMIF(Tabela1[Produtos],K70,Tabela1[Valor venddo]) -> 51.68 | O70: =SUMIF(Tabela1[Produtos],K70,Tabela1[Valor do lucro]) -> 21.68
A71: 292 | B71: Bateria 9v Hw Original Comum Não Recarregável | C71: 1 | D71: 2.5 | E71: 3.81 | F71: 1.31 | G71: Vendido | H71: Shopee | K71: CARREGADOR PORTÁTIL ULTRAFINO - POWER BANK 10000mah PINENG UNIVERSAL LINHA | L71: =SUMIF(Tabela1[Produtos],K71,Tabela1[Quantidade]) -> 2 | M71: =SUMIF(Tabela1[Produtos],K71,Tabela1[Valor gasto]) -> 76 | N71: =SUMIF(Tabela1[Produtos],K71,Tabela1[Valor venddo]) -> 97.94 | O71: =SUMIF(Tabela1[Produtos],K71,Tabela1[Valor do lucro]) -> 21.94
A72: 903 | B72: Bateria 9v Hw Original Comum Não Recarregável | C72: 2 | D72: 10 | E72: 8.1836 | F72: =E72-D72 -> -1.8164 | G72: vendido | H72: Shopee | K72: carregador v8 | L72: =SUMIF(Tabela1[Produtos],K72,Tabela1[Quantidade]) -> 1 | M72: =SUMIF(Tabela1[Produtos],K72,Tabela1[Valor gasto]) -> 7 | N72: =SUMIF(Tabela1[Produtos],K72,Tabela1[Valor venddo]) -> 25 | O72: =SUMIF(Tabela1[Produtos],K72,Tabela1[Valor do lucro]) -> 18
A73: 437 | B73: Bateria 9v Hw Original Comum Não Recarregável | C73: 1 | D73: 5 | E73: 10.95 | F73: =E73-D73 -> 5.95 | G73: vendido | H73: bsb | K73: Carregador v8 hms | L73: =SUMIF(Tabela1[Produtos],K73,Tabela1[Quantidade]) -> 3 | M73: =SUMIF(Tabela1[Produtos],K73,Tabela1[Valor gasto]) -> 54 | N73: =SUMIF(Tabela1[Produtos],K73,Tabela1[Valor venddo]) -> 105 | O73: =SUMIF(Tabela1[Produtos],K73,Tabela1[Valor do lucro]) -> 51
A74: 291 | B74: Bateria A23 12v 1unidade Ótima Qualidade | C74: 26 | D74: 31.2 | E74: 74.26 | F74: 43.06 | G74: Vendido | H74: Shopee | K74: carregador v8 simples | L74: =SUMIF(Tabela1[Produtos],K74,Tabela1[Quantidade]) -> 3 | M74: =SUMIF(Tabela1[Produtos],K74,Tabela1[Valor gasto]) -> 15 | N74: =SUMIF(Tabela1[Produtos],K74,Tabela1[Valor venddo]) -> 40 | O74: =SUMIF(Tabela1[Produtos],K74,Tabela1[Valor do lucro]) -> 25
A75: 542 | B75: Bateria A23 12v 1unidade Ótima Qualidade | C75: 22 | D75: 22 | E75: 60.71 | F75: =SUM(E75-D75) -> 38.71 | G75: vendido | H75: Shopee | K75: carregador veicular | L75: =SUMIF(Tabela1[Produtos],K75,Tabela1[Quantidade]) -> 2 | M75: =SUMIF(Tabela1[Produtos],K75,Tabela1[Valor gasto]) -> 25 | N75: =SUMIF(Tabela1[Produtos],K75,Tabela1[Valor venddo]) -> 45 | O75: =SUMIF(Tabela1[Produtos],K75,Tabela1[Valor do lucro]) -> 20
A76: 708 | B76: Bateria A23 12v 1unidade Ótima Qualidade | C76: 19 | D76: =7/5 -> 1.4 | E76: 71.37 | F76: 44.77 | G76: vendido | H76: Shopee | K76: case | L76: =SUMIF(Tabela1[Produtos],K76,Tabela1[Quantidade]) -> 1 | M76: =SUMIF(Tabela1[Produtos],K76,Tabela1[Valor gasto]) -> 20 | N76: =SUMIF(Tabela1[Produtos],K76,Tabela1[Valor venddo]) -> 50 | O76: =SUMIF(Tabela1[Produtos],K76,Tabela1[Valor do lucro]) -> 30
A77: 825 | B77: Bateria A23 12v 1unidade Ótima Qualidade | C77: 2 | D77: 2.8 | E77: 29.57 | F77: 26.77 | G77: vendido | H77: Shopee | K77: case HD | L77: =SUMIF(Tabela1[Produtos],K77,Tabela1[Quantidade]) -> 1 | M77: =SUMIF(Tabela1[Produtos],K77,Tabela1[Valor gasto]) -> 30 | N77: =SUMIF(Tabela1[Produtos],K77,Tabela1[Valor venddo]) -> 50 | O77: =SUMIF(Tabela1[Produtos],K77,Tabela1[Valor do lucro]) -> 20
A78: 904 | B78: Bateria A23 12v 1unidade Ótima Qualidade | C78: 1 | D78: 1.4 | E78: 4.9118 | F78: =E78-D78 -> 3.5118 | G78: vendido | H78: Shopee | K78: Chapéu Australiano Pesca Caminhada Camping Proteção Nuca Sol | L78: =SUMIF(Tabela1[Produtos],K78,Tabela1[Quantidade]) -> 2 | M78: =SUMIF(Tabela1[Produtos],K78,Tabela1[Valor gasto]) -> 16 | N78: =SUMIF(Tabela1[Produtos],K78,Tabela1[Valor venddo]) -> 30.71 | O78: =SUMIF(Tabela1[Produtos],K78,Tabela1[Valor do lucro]) -> 14.71
A79: 345 | B79: Bateria A23 12v 1unidade Ótima Qualidade | C79: 1 | D79: 84 | E79: 226.54 | F79: =E79-D79 -> 142.54 | G79: vendido | H79: bsb | K79: Chapéu Palha Cerveja - Time - Pierside | L79: =SUMIF(Tabela1[Produtos],K79,Tabela1[Quantidade]) -> 4 | M79: =SUMIF(Tabela1[Produtos],K79,Tabela1[Valor gasto]) -> 94 | N79: =SUMIF(Tabela1[Produtos],K79,Tabela1[Valor venddo]) -> 210.51 | O79: =SUMIF(Tabela1[Produtos],K79,Tabela1[Valor do lucro]) -> 116.51
A80: 438 | B80: Bateria A23 12v 1unidade Ótima Qualidade | C80: 1 | D80: 100.1 | E80: 201.82 | F80: =E80-D80 -> 101.72 | G80: vendido | H80: bsb | K80: Chave para Mandril HT S02 - 13 MM P/MANDRIL 10 MM - 3/8 | L80: =SUMIF(Tabela1[Produtos],K80,Tabela1[Quantidade]) -> 7 | M80: =SUMIF(Tabela1[Produtos],K80,Tabela1[Valor gasto]) -> 21 | N80: =SUMIF(Tabela1[Produtos],K80,Tabela1[Valor venddo]) -> 42.8234 | O80: =SUMIF(Tabela1[Produtos],K80,Tabela1[Valor do lucro]) -> 21.8234
A81: 591 | B81: Bateria A23 12v 1unidade Ótima Qualidade | C81: 1 | D81: 19.2 | E81: 40.42 | F81: =E81-D81 -> 21.22 | G81: vendido | H81: bsb | K81: Chave tok/alen | L81: =SUMIF(Tabela1[Produtos],K81,Tabela1[Quantidade]) -> 1 | M81: =SUMIF(Tabela1[Produtos],K81,Tabela1[Valor gasto]) -> 13.5 | N81: =SUMIF(Tabela1[Produtos],K81,Tabela1[Valor venddo]) -> 20 | O81: =SUMIF(Tabela1[Produtos],K81,Tabela1[Valor do lucro]) -> 6.5
A82: 543 | B82: Bateria De Litio 3v Tipo Botão CR2025 Knup Kp-bt2025 | C82: 73 | D82: 43.8 | E82: 233.24 | F82: =SUM(E82-D82) -> 189.44 | G82: vendido | H82: Shopee | K82: chave universal | L82: =SUMIF(Tabela1[Produtos],K82,Tabela1[Quantidade]) -> 2 | M82: =SUMIF(Tabela1[Produtos],K82,Tabela1[Valor gasto]) -> 48 | N82: =SUMIF(Tabela1[Produtos],K82,Tabela1[Valor venddo]) -> 100 | O82: =SUMIF(Tabela1[Produtos],K82,Tabela1[Valor do lucro]) -> 52
A83: 293 | B83: Bateria De Litio 3v Tipo Botão CR2025 Knup Kp-bt2025 | C83: 10 | D83: 6 | E83: 28.3 | F83: 22.3 | G83: Vendido | H83: Shopee | K83: chinela | L83: =SUMIF(Tabela1[Produtos],K83,Tabela1[Quantidade]) -> 1 | M83: =SUMIF(Tabela1[Produtos],K83,Tabela1[Valor gasto]) -> 20 | N83: =SUMIF(Tabela1[Produtos],K83,Tabela1[Valor venddo]) -> 40 | O83: =SUMIF(Tabela1[Produtos],K83,Tabela1[Valor do lucro]) -> 20
A84: 759 | B84: Bateria De Litio 3v Tipo Botão CR2025 Knup Kp-bt2025 | C84: 6 | D84: 4.2 | E84: 6.56 | F84: 2.36 | G84: vendido | H84: Shopee | K84: Climatizador | L84: =SUMIF(Tabela1[Produtos],K84,Tabela1[Quantidade]) -> 9 | M84: =SUMIF(Tabela1[Produtos],K84,Tabela1[Valor gasto]) -> 543 | N84: =SUMIF(Tabela1[Produtos],K84,Tabela1[Valor venddo]) -> 1170 | O84: =SUMIF(Tabela1[Produtos],K84,Tabela1[Valor do lucro]) -> 627
A85: 692 | B85: Bateria De Litio 3v Tipo Botão CR2025 Knup Kp-bt2025 | C85: 4 | D85: =3.5/5 -> 0.7 | E85: 9.22 | F85: 6.42 | G85: vendido | H85: Shopee | K85: Conjunto de chave de fenda de precisão de 6 peça | L85: =SUMIF(Tabela1[Produtos],K85,Tabela1[Quantidade]) -> 3 | M85: =SUMIF(Tabela1[Produtos],K85,Tabela1[Valor gasto]) -> 12 | N85: =SUMIF(Tabela1[Produtos],K85,Tabela1[Valor venddo]) -> 24.51 | O85: =SUMIF(Tabela1[Produtos],K85,Tabela1[Valor do lucro]) -> 12.51
A86: 265 | B86: Bateria De Litio 3v Tipo Botão CR2025 Knup Kp-bt2025 | C86: 3 | D86: 0.83333333 | E86: 2.5 | F86: 6.47 | G86: vendido | H86: Shopee | K86: Controlador de dedo de jogo de telefone móvel antiderrapante respirável | L86: =SUMIF(Tabela1[Produtos],K86,Tabela1[Quantidade]) -> 9 | M86: =SUMIF(Tabela1[Produtos],K86,Tabela1[Valor gasto]) -> 16 | N86: =SUMIF(Tabela1[Produtos],K86,Tabela1[Valor venddo]) -> 70.31 | O86: =SUMIF(Tabela1[Produtos],K86,Tabela1[Valor do lucro]) -> 76.31
A87: 905 | B87: Bateria De Litio 3v Tipo Botão CR2025 Knup Kp-bt2025 | C87: 3 | D87: 2.1 | E87: 2.1238 | F87: =E87-D87 -> 0.0238 | G87: vendido | H87: Shopee | K87: Controle Para Celular Pubg Free Fire + Manete Gamepad | L87: =SUMIF(Tabela1[Produtos],K87,Tabela1[Quantidade]) -> 1 | M87: =SUMIF(Tabela1[Produtos],K87,Tabela1[Valor gasto]) -> 15 | N87: =SUMIF(Tabela1[Produtos],K87,Tabela1[Valor venddo]) -> 37.269 | O87: =SUMIF(Tabela1[Produtos],K87,Tabela1[Valor do lucro]) -> 22.269
A88: 346 | B88: Bateria De Litio 3v Tipo Botão CR2025 Knup Kp-bt2025 | C88: 1 | D88: 2 | E88: 7.8 | F88: =E88-D88 -> 5.8 | G88: vendido | H88: bsb | K88: Controle Remoto Celular Android E iPhone Bluetooth Shutter | L88: =SUMIF(Tabela1[Produtos],K88,Tabela1[Quantidade]) -> 6 | M88: =SUMIF(Tabela1[Produtos],K88,Tabela1[Valor gasto]) -> 66 | N88: =SUMIF(Tabela1[Produtos],K88,Tabela1[Valor venddo]) -> 146.68 | O88: =SUMIF(Tabela1[Produtos],K88,Tabela1[Valor do lucro]) -> 80.68
A89: 439 | B89: Bateria De Litio 3v Tipo Botão CR2025 Knup Kp-bt2025 | C89: 1 | D89: 7 | E89: 14.96 | F89: =E89-D89 -> 7.96 | G89: vendido | H89: bsb | K89: Controle Remoto Celular Android E iPhone Bluetooth Shutter --- 20 und | L89: =SUMIF(Tabela1[Produtos],K89,Tabela1[Quantidade]) -> 40 | M89: =SUMIF(Tabela1[Produtos],K89,Tabela1[Valor gasto]) -> 6 | N89: =SUMIF(Tabela1[Produtos],K89,Tabela1[Valor venddo]) -> 240 | O89: =SUMIF(Tabela1[Produtos],K89,Tabela1[Valor do lucro]) -> 154.57
A90: 592 | B90: Bateria De Litio 3v Tipo Botão CR2025 Knup Kp-bt2025 | C90: 1 | D90: 1.4 | E90: 4.48 | F90: =E90-D90 -> 3.08 | G90: vendido | H90: bsb | K90: controle tv box | L90: =SUMIF(Tabela1[Produtos],K90,Tabela1[Quantidade]) -> 2 | M90: =SUMIF(Tabela1[Produtos],K90,Tabela1[Valor gasto]) -> 20 | N90: =SUMIF(Tabela1[Produtos],K90,Tabela1[Valor venddo]) -> 40 | O90: =SUMIF(Tabela1[Produtos],K90,Tabela1[Valor do lucro]) -> 20
A91: 717 | B91: Bateria Litio 2032 Unitário Cr2032 1 unidades | C91: 221 | D91: =4.5/5 -> 0.9 | E91: 533.65 | F91: 334.75 | G91: vendido | H91: Shopee | K91: Conversor Digital Terrestre DIG-7020 | L91: =SUMIF(Tabela1[Produtos],K91,Tabela1[Quantidade]) -> 1 | M91: =SUMIF(Tabela1[Produtos],K91,Tabela1[Valor gasto]) -> 90 | N91: =SUMIF(Tabela1[Produtos],K91,Tabela1[Valor venddo]) -> 123 | O91: =SUMIF(Tabela1[Produtos],K91,Tabela1[Valor do lucro]) -> 33
A92: 111 | B92: Bateria Litio 2032 Unitário Cr2032 1 unidades | C92: 113 | D92: 113 | E92: 269.88 | F92: 156.88 | G92: vendido | H92: shopee | K92: Cooler Fan Rgb Master Led Fc1302 120x120mm | L92: =SUMIF(Tabela1[Produtos],K92,Tabela1[Quantidade]) -> 3 | M92: =SUMIF(Tabela1[Produtos],K92,Tabela1[Valor gasto]) -> 190 | N92: =SUMIF(Tabela1[Produtos],K92,Tabela1[Valor venddo]) -> 310.58 | O92: =SUMIF(Tabela1[Produtos],K92,Tabela1[Valor do lucro]) -> 120.58
A93: 826 | B93: Bateria Litio 2032 Unitário Cr2032 1 unidades | C93: 71 | D93: 71 | E93: 186.92 | F93: 115.92 | G93: vendido | H93: Shopee | K93: copo rico | L93: =SUMIF(Tabela1[Produtos],K93,Tabela1[Quantidade]) -> 2 | M93: =SUMIF(Tabela1[Produtos],K93,Tabela1[Valor gasto]) -> 220 | N93: =SUMIF(Tabela1[Produtos],K93,Tabela1[Valor venddo]) -> 300 | O93: =SUMIF(Tabela1[Produtos],K93,Tabela1[Valor do lucro]) -> 80
A94: 264 | B94: Bateria Litio 2032 Unitário Cr2032 1 unidades | C94: 21 | D94: 1 | E94: 21 | F94: 41.92 | G94: vendido | H94: Shopee | K94: Corrente bike | L94: =SUMIF(Tabela1[Produtos],K94,Tabela1[Quantidade]) -> 8 | M94: =SUMIF(Tabela1[Produtos],K94,Tabela1[Valor gasto]) -> 235 | N94: =SUMIF(Tabela1[Produtos],K94,Tabela1[Valor venddo]) -> 450 | O94: =SUMIF(Tabela1[Produtos],K94,Tabela1[Valor do lucro]) -> 215
A95: 906 | B95: Bateria Litio 2032 Unitário Cr2032 1 unidades | C95: 11 | D95: 11 | E95: 19.0896 | F95: =E95-D95 -> 8.0896 | G95: vendido | H95: Shopee | K95: cortador de vidro | L95: =SUMIF(Tabela1[Produtos],K95,Tabela1[Quantidade]) -> 1 | M95: =SUMIF(Tabela1[Produtos],K95,Tabela1[Valor gasto]) -> 10 | N95: =SUMIF(Tabela1[Produtos],K95,Tabela1[Valor venddo]) -> 20 | O95: =SUMIF(Tabela1[Produtos],K95,Tabela1[Valor do lucro]) -> 10
A96: 760 | B96: Bateria Litio 2032 Unitário Cr2032 1 unidades | C96: 6 | D96: 4.2 | E96: 13.63 | F96: 9.43 | G96: vendido | H96: Shopee | K96: despertador | L96: =SUMIF(Tabela1[Produtos],K96,Tabela1[Quantidade]) -> 1 | M96: =SUMIF(Tabela1[Produtos],K96,Tabela1[Valor gasto]) -> 12 | N96: =SUMIF(Tabela1[Produtos],K96,Tabela1[Valor venddo]) -> 50 | O96: =SUMIF(Tabela1[Produtos],K96,Tabela1[Valor do lucro]) -> 38
A97: 294 | B97: Bateria Litio 2032 Unitário Cr2032 1 unidades | C97: 4 | D97: 4 | E97: 10.8 | F97: 6.8 | G97: Vendido | H97: Shopee | K97: Digital plataforma de pesagem balança eletrônica Digital jóias escalas | L97: =SUMIF(Tabela1[Produtos],K97,Tabela1[Quantidade]) -> 2 | M97: =SUMIF(Tabela1[Produtos],K97,Tabela1[Valor gasto]) -> 53 | N97: =SUMIF(Tabela1[Produtos],K97,Tabela1[Valor venddo]) -> 90.61 | O97: =SUMIF(Tabela1[Produtos],K97,Tabela1[Valor do lucro]) -> 37.61
A98: 40 | B98: Bateria Litio 2032 Unitário Cr2032 1 unidades | C98: 1 | D98: =E98-F98 -> 37 | E98: 79.57 | F98: 42.57 | G98: vendido | H98: shopee | K98: Eken-câmera de ação original h9/h9r remota + SD 128gb - PRETO | L98: =SUMIF(Tabela1[Produtos],K98,Tabela1[Quantidade]) -> 1 | M98: =SUMIF(Tabela1[Produtos],K98,Tabela1[Valor gasto]) -> 260 | N98: =SUMIF(Tabela1[Produtos],K98,Tabela1[Valor venddo]) -> 480.17 | O98: =SUMIF(Tabela1[Produtos],K98,Tabela1[Valor do lucro]) -> 220.17
A99: 347 | B99: Bateria Litio 2032 Unitário Cr2032 1 unidades | C99: 1 | D99: 25 | E99: 58.27 | F99: =E99-D99 -> 33.27 | G99: vendido | H99: bsb | K99: ESPELHO RETROVISOR PARA BIKE | L99: =SUMIF(Tabela1[Produtos],K99,Tabela1[Quantidade]) -> 118 | M99: =SUMIF(Tabela1[Produtos],K99,Tabela1[Valor gasto]) -> 184 | N99: =SUMIF(Tabela1[Produtos],K99,Tabela1[Valor venddo]) -> 1316.79 | O99: =SUMIF(Tabela1[Produtos],K99,Tabela1[Valor do lucro]) -> 1426.94
A100: 440 | B100: Bateria Litio 2032 Unitário Cr2032 1 unidades | C100: 1 | D100: 7 | E100: 20.35 | F100: =E100-D100 -> 13.35 | G100: vendido | H100: bsb | K100: Esponja Limpeza Facial Esfoliante Formato Polvo De Silicone | L100: =SUMIF(Tabela1[Produtos],K100,Tabela1[Quantidade]) -> 1 | M100: =SUMIF(Tabela1[Produtos],K100,Tabela1[Valor gasto]) -> 1 | N100: =SUMIF(Tabela1[Produtos],K100,Tabela1[Valor venddo]) -> 5.1332 | O100: =SUMIF(Tabela1[Produtos],K100,Tabela1[Valor do lucro]) -> 4.1332
...

Sheet Planilha2
A1: Produtos fisicos | B1: Valor gasto | C1: Valor vendido | D1: lucro | E1: Qunt
A2: Produtos fisicos | B2: 16749.433 | C2: 35538.48 | D2: 18789.047 | E2: 478
A3: Produtos online | B3: 22706.675 | C3: 57741.757 | D3: 33144.37 | E3: 2526
A6: Produto | B6: Qunt | C6: Valor unitario | D6: Valor gasto | E6: Valor vendido | F6: lucro | G6: %
A7: Globo de luz de discoteca rotativo para festas | B7: 275 | C7: 35 | D7: 8159 | E7: 19927.57 | F7: =E7-D7 -> 11768.57 | G7: =(F7/E7) -> 0.59056725
A8: Super Mini Taser Defense Choque Ideal Para | B8: 268 | C8: 50 | D8: 4190 | E8: 10769.46 | F8: =E8-D8 -> 6579.46 | G8: =(F8/E8) -> 0.61093685
A9: Mini Máquina De Costura Manual Portátil | B9: 365 | C9: 6 | D9: 1755 | E9: 5194.9948 | F9: =E9-D9 -> 3439.9948 | G9: =(F9/E9) -> 0.66217483
A10: Suporte Anti-Perda Para Fone De Ouvido Sem Fio | B10: 375 | C10: 1 | D10: 498.85 | E10: 1475.1182 | F10: =E10-D10 -> 976.2682 | G10: =(F10/E10) -> 0.66182371
A11: Bateria Litio 2032 Unitário Cr2032 1 unidades | B11: 447 | C11: =4/5 -> 0.8 | D11: 242.1 | E11: 1134.5396 | F11: =E11-D11 -> 892.4396 | G11: =(F11/E11) -> 0.78660948
A12: ESPELHO RETROVISOR PARA BIKE | B12: 116 | C12: 2 | D12: 138 | E12: 949.73 | F12: =E12-D12 -> 811.73 | G12: =(F12/E12) -> 0.85469555
A13: Kit Reparo Para Pneu Sem Câmara | B13: 202 | C13: 10 | D13: 1037 | E13: 2531.2212 | F13: =E13-D13 -> 1494.2212 | G13: =(F13/E13) -> 0.59031633
F14: =E14-D14 -> 0 | G14: =(F14/E14) -> #DIV/0!
F15: =E15-D15 -> 0 | G15: =(F15/E15) -> #DIV/0!
F16: =E16-D16 -> 0 | G16: =(F16/E16) -> #DIV/0!
A22: Produto | B22: Qunt | C22: Valor gasto | D22: Valor vendido | E22: lucro
A23: ESPELHO RETROVISOR PARA BIKE | B23: =SUM(B24:B33) -> 0 | C23: =SUM(C24:C33) -> 0 | D23: =SUM(D24:D33) -> 0 | E23: =SUM(E24:E33) -> 0
