Workbook

Sheet Gastos
A1: Gastos | B1: Janeiro | C1: Fevereiro | D1: Março | E1: Abril | F1: Maio | G1: Junho | H1: Julho | I1: Agosto | J1: Setembro | K1: Outubro | L1: Novembro | M1: Dezembro
A2: Cartao Nu | B2: 769 | C2: 580 | D2: 696.12 | E2: 1562.09 | F2: 1541.83 | G2: 2329.07 | H2: 472.09 | I2: 320.77 | J2: 320.77 | K2: 320.77 | L2: 320.77 | M2: 302.9
A3: Cartao Inter | F3: 993.48 | G3: =353+226 -> 579
A4: Aparelho | B4: - | C4: 70 | D4: 60 | E4: 70 | F4: 70 | G4: 70 | H4: 70 | I4: 70 | J4: 70 | K4: 70 | L4: 70 | M4: 70
A5: IPVA | B5: - | C5: 95.99 | D5: 95.99 | E5: 95.99 | F5: 95.99 | G5: - | H5: - | I5: - | J5: - | K5: - | L5: - | M5: -
A6: Agua | B6: 59 | C6: 59 | D6: 59 | E6: 59 | F6: 59 | G6: 59 | H6: 59 | I6: 59 | J6: 59 | K6: 59 | L6: 59 | M6: 59
A7: Equi. Carro | B7: - | C7: 16.21 | D7: - | E7: - | F7: 72.85 | G7: - | H7: - | I7: - | J7: - | K7: - | L7: - | M7: -
A8: Outros Gastos | B8: - | C8: - | G8: 50 | H8: 50 | I8: 50 | J8: 50 | K8: 50 | L8: 50 | M8: 50
A9: Total Gasto | B9: =SUM(B2:B8) -> 828 | C9: =SUM(C2:C8) -> 821.2 | D9: =SUM(D2:D8) -> 911.11 | E9: =SUM(E5:E8) -> 154.99 | F9: =SUM(F2:F8) -> 2833.15 | G9: =SUM(G2:G8) -> 3087.07 | H9: =SUM(H2:H8) -> 651.09 | I9: =SUM(I2:I8) -> 499.77 | J9: =SUM(J2:J8) -> 499.77 | K9: =SUM(K2:K8) -> 499.77 | L9: =SUM(L2:L8) -> 499.77 | M9: =SUM(M2:M8) -> 481.9
A10: Renda | B10: Janeiro | C10: Fevereiro | D10: Março | E10: Abril | F10: Maio | G10: Junho | H10: Julho | I10: Agosto | J10: Setembro | K10: Outubro | L10: Novembro | M10: Dezembro
A11: Salario | B11: 443 | C11: 365 | D11: 812 | E11: 815 | F11: 815 | G11: 914 | H11: 914 | I11: 914 | J11: 914 | K11: 914 | L11: 914 | M11: 914
A12: Tenebrio | B12: =Vendas!#REF! -> #REF! | C12: 310 | F12: 400 | G12: 400
A13: Vendas | B13: =B53 -> #REF! | C13: =C53 -> #REF! | D13: ='Relatorios 2019'!G1 -> 738.4 | E13: ='Relatorios 2019'!G43 -> 1199.51 | F13: ='Relatorios 2019'!G111 -> 2048.2 | G13: =G53 -> #REF! | H13: =H53 -> #REF! | I13: =I53 -> 3756.8 | J13: =J53 -> 4003.9 | K13: =K53 -> 0 | L13: =L53 -> 0 | M13: =M53 -> 0
A14: APP | B14: =Vendas!#REF! -> #REF! | C14: 0 | D14: 0 | E14: 0 | F14: 0 | G14: 0 | H14: 0 | I14: 0 | J14: 0 | K14: 0 | L14: 0 | M14: 0
A15: Total Ganho | B15: =SUM(B11:B14) -> #REF! | C15: =SUM(C11:C14) -> #REF! | D15: =SUM(D11:D14) -> 1550.4 | E15: =SUM(E11:E14) -> 2014.51 | F15: =SUM(F11:F14) -> 3263.2 | G15: =SUM(G11:G14) -> #REF! | H15: =SUM(H11:H14) -> #REF! | I15: =SUM(I11:I14) -> 4670.8 | ... M15: =SUM(M11:M14) -> 914
B16: =B15-2000 -> #REF! | C16: =C15-2000 -> #REF! | D16: =D15-2000 -> -449.6 | E16: =E15-2000 -> 14.51 | F16: =F15-2000 -> 1263.2 | G16: =G15-2000 -> #REF! | H16: =H15-2000 -> #REF! | I16: =I15-2000 -> 2670.8 | ... M16: =M15-2000 -> -1086
A17: Sobrando | B17: =SUM(B15-B9) -> #REF! | C17: =SUM(C15-C9) -> #REF! | D17: =SUM(D15-D9) -> 639.29 | E17: =SUM(E15-E9) -> 1859.52 | F17: =SUM(F15-F9) -> 430.05 | G17: =SUM(G15-G9) -> #REF! | H17: =SUM(H15-H9) -> #REF! | I17: =SUM(I15-I9) -> 4171.03 | ... M17: =SUM(M15-M9) -> 432.1
A45: Gastos | B45: Janeiro | C45: Fevereiro | D45: Março | E45: Abril | F45: Maio | G45: Junho | H45: Julho | I45: Agosto | J45: Setembro | K45: Outubro | L45: Novembro | M45: Dezembro
A46: Cartao | B46: 0 | C46: 0 | D46: =SUM(Vendas!E6:E47) -> 976.6 | E46: ='Relatorios 2019'!E43 -> 1575.99 | F46: ='Relatorios 2019'!E111 -> 2043.1 | G46: ='Relatorios 2019'!E187 -> 2947.32 | H46: ='Relatorios 2019'!E323 -> 3060.23 | I46: ='Relatorios 2019'!E476 -> 2057.59 | J46: ='Relatorios 2019'!E568 -> 2319.62
A49: Total Gasto | B49: =SUM(B46:B48) -> 0 | C49: =SUM(C46:C48) -> 0 | D49: =SUM(D46:D48) -> 976.6 | E49: =SUM(E46:E48) -> 1575.99 | F49: =SUM(F46:F48) -> 2043.1 | G49: =SUM(G46:G48) -> 2947.32 | H49: =SUM(H46:H48) -> 3060.23 | I49: =SUM(I46:I48) -> 2057.59 | ... M49: =SUM(M46:M48) -> 0
A50: Renda | B50: Janeiro | C50: Fevereiro | D50: Março | E50: Abril | F50: Maio | G50: Junho | H50: Julho | I50: Agosto | J50: Setembro | K50: Outubro | L50: Novembro | M50: Dezembro
A51: Vendas | B51: =Vendas!#REF! -> #REF! | C51: =Vendas!#REF! -> #REF! | D51: =Vendas!#REF! -> #REF! | E51: ='Relatorios 2019'!F43 -> 2775.5 | F51: ='Relatorios 2019'!F111 -> 3243 | G51: =Vendas!#REF! -> #REF! | H51: =Vendas!#REF! -> #REF! | I51: ='Relatorios 2019'!F476 -> 3756.8 | J51: ='Relatorios 2019'!F568 -> 4003.9
A53: Total Ganho | B53: =SUM(B51:B52) -> #REF! | C53: =SUM(C51:C52) -> #REF! | D53: =SUM(D51:D52) -> #REF! | E53: =SUM(E51:E52) -> 2775.5 | F53: =SUM(F51:F52) -> 3243 | G53: =SUM(G51:G52) -> #REF! | H53: =SUM(H51:H52) -> #REF! | I53: =SUM(I51:I52) -> 3756.8 | ... M53: =SUM(M51:M52) -> 0
A54: Lucro | B54: =SUM(B53-B49) -> #REF! | C54: =SUM(C53-C49) -> #REF! | D54: =Vendas!#REF! -> #REF! | E54: ='Relatorios 2019'!G43 -> 1199.51 | F54: ='Relatorios 2019'!G111 -> 2048.2 | G54: =SUM(G53-G49) -> #REF! | H54: =SUM(H53-H49) -> #REF! | I54: =SUM(I53-I49) -> 1699.21 | J54: =SUM(J53-J49) -> 1684.28 | K54: =SUM(K53-K49) -> 0 | L54: =SUM(L53-L49) -> 0 | M54: =SUM(M53-M49) -> 0
D55: =
B155: 35 | F155: 60
B167: 25 | F167: 50
B168: 40 | F168: 60
B170: 5 | F170: 10
B171: 3 | F171: 5
B172: 2.5
B175: 19 | F175: 45
B176: 10 | F176: 25
B177: 2 | F177: 4
B178: 10 | F178: 15
B179: 18 | F179: 35
B180: 18 | F180: 22
F181: 20
B182: 5 | F182: 10
B183: 18 | F183: 35
B185: 25 | F185: 50
F186: 15
B187: 65 | F187: 110
B188: 20 | F188: 35
B189: 4.5 | F189: 7
B190: 4.5
B193: 110 | F193: 160
A194: Umidificador
A196: Umidificador | B196: 22 | F196: 35
R248: Umidificador Atacado
R249: Umidificador Atacado
R250: Umidificador Atacado

Sheet Relatorios 2019
A1: Março | E1: =SUM(E2:E41) -> 923.6 | F1: =SUM(F2:F41) -> 1662 | G1: 738.4 | H1: =COUNTIF(H2:H41,"Vendido") -> 40 | I1: =(F1-E1)/F1 -> 0.444284
B2: Arame de solda | D2: Carlos | E2: 6 | F2: 12 | G2: =F2-E2 -> 6 | H2: Vendido
B3: Arame de solda | D3: Gian | E3: 6 | F3: 12 | G3: =F3-E3 -> 6 | H3: Vendido
B4: Barbeador 7x1 | D4: Danni | E4: 65 | F4: 115 | G4: =F4-E4 -> 50 | H4: Vendido
B5: Barbeador 7x1 | D5: Tio Teinha | E5: 65 | F5: 115 | G5: =F5-E5 -> 50 | H5: Vendido
B6: Cable cb-11 | D6: Mateus | E6: 3 | F6: 5 | G6: =F6-E6 -> 2 | H6: Vendido
B7: Cabo kingo | D7: Amiga Higor | E7: 6.8 | F7: 25 | G7: =F7-E7 -> 18.2 | H7: Vendido
B8: Cabo kingo | D8: irmão higor | E8: 6.8 | F8: 7 | G8: =F8-E8 -> 0.2 | H8: Vendido
A9: 1 | B9: Case HD | D9: Moto casa | E9: 16 | F9: 30 | G9: =F9-E9 -> 14 | H9: Vendido
A10: 2 | B10: Compressor veicular | D10: Segurança | E10: 29 | F10: 50 | G10: =F10-E10 -> 21 | H10: Vendido
A11: 3 | B11: Cortador de cabelo básico | D11: Cliente besouro Bike | E11: 17 | F11: 35 | G11: =F11-E11 -> 18 | H11: Vendido
A12: 4 | B12: Ferro de solda 40w | D12: Gian | E12: 13 | F12: 20 | G12: =F12-E12 -> 7 | H12: Vendido
A13: 5 | B13: Ferro de solda 60w | D13: Carlos | E13: 10 | F13: 20 | G13: =F13-E13 -> 10 | H13: Vendido
A14: 6 | B14: Fita isolante | D14: Carlos | E14: 6 | F14: 6 | G14: =F14-E14 -> 0 | H14: Vendido
A15: 7 | B15: Fita isolante | D15: Gian | E15: 6 | F15: 18 | G15: =F15-E15 -> 12 | H15: Vendido
A16: 8 | B16: Fone completo | D16: Senhor sobradinho | E16: 39 | F16: 80 | G16: =F16-E16 -> 41 | H16: Vendido
A17: 9 | B17: Fone lelong | D17: Mateus | E17: 9 | F17: 20 | G17: =F17-E17 -> 11 | H17: Vendido
A18: 10 | B18: Fone Sony | D18: ETB | E18: 25 | F18: 50 | G18: =F18-E18 -> 25 | H18: Vendido
A19: 11 | B19: Fone Sony | D19: Metro Taguatinga | E19: 25 | F19: 50 | G19: =F19-E19 -> 25 | H19: Vendido
A20: 12 | B20: Mouse game | D20: Ceilândia | E20: 22 | F20: 35 | G20: =F20-E20 -> 13 | H20: Vendido
A21: 13 | B21: Mouse game | D21: Mateus | E21: 2 | H21: Vendido
A22: 14 | B22: Multímetro Digital Dt-830b | D22: Carlos | E22: 16 | F22: 25 | G22: =F22-E22 -> 9 | H22: Vendido
A23: 15 | B23: Multímetro Digital Dt-830b | D23: Feira Tagua | E23: 16 | F23: 25 | G23: =F23-E23 -> 9 | H23: Vendido
A24: 16 | B24: Multímetro Digital Dt-830b | D24: Henrique | E24: 16 | F24: 25 | G24: =F24-E24 -> 9 | H24: Vendido
A25: 17 | B25: Multímetro Digital Dt-830b | D25: Senhor sobradinho | E25: 16 | F25: 20 | G25: =F25-E25 -> 4 | H25: Vendido
A26: 18 | B26: Multímetro Md-180l | D26: a125- | E26: 30 | F26: 50 | G26: =F26-E26 -> 20 | H26: Vendido
A27: 19 | B27: Multímetro Md-180l | D27: ETB | E27: 30 | F27: 55 | G27: =F27-E27 -> 25 | H27: Vendido
A28: 20 | B28: Multímetro Md-180l | D28: Riacho | E28: 30 | F28: 60 | G28: =F28-E28 -> 30 | H28: Vendido
A29: 21 | B29: Powebank PN-951 10000mAh | D29: Danni | E29: 28 | F29: 65 | G29: =F29-E29 -> 37 | H29: Vendido
A30: 22 | B30: Powebank PN-951 10000mAh | D30: Fabrício | E30: 28 | F30: 57 | G30: =F30-E30 -> 29 | H30: Vendido
A31: 23 | B31: Powebank PN-951 10000mAh | D31: Renata | E31: 28 | F31: 30 | G31: =F31-E31 -> 2 | H31: Vendido
A32: 24 | B32: Smartwatch A1 | D32: Riacho olx | E32: 55 | F32: 100 | G32: =F32-E32 -> 45 | H32: Vendido
A33: 25 | B33: Smartwatch Dz09 | D33: André | E33: 55 | F33: 100 | G33: =F33-E33 -> 45 | H33: Vendido
... A38: 30 | B38: Suporte de solda | D38: Carlos | E38: 10 | F38: 20 | G38: =F38-E38 -> 10 | H38: Vendido
A39: 31 | B39: Switch 24 portas | D39: olx | F39: 30 | G39: 30 | H39: Vendido
A40: 32 | B40: Tenebrio | D40: Cliente besouro Bike | E40: 0 | F40: 10 | G40: 10 | H40: Vendido
A41: 33 | B41: Xtrape carregador turbo | D41: Mateus | E41: 8 | F41: 10 | G41: =F41-E41 -> 2 | H41: Vendido
A43: Abril | E43: =SUM(E44:E110) -> 1575.99 | F43: =SUM(F44:F110) -> 2775.5 | G43: 1199.51 | H43: =COUNTIF(H44:H110,"Vendido") -> 50 | I43: =(F43-E43)/F43 -> 0.43217799
A44: 1 | B44: Barbeador 7x1 | D44: Maria olx | E44: 65 | F44: 100 | G44: =F44-E44 -> 35 | H44: Vendido
A45: 2 | B45: Barbeador 7x1 | D45: Jean moto | E45: 65 | F45: 115 | G45: =F45-E45 -> 50 | H45: Vendido
A46: 3 | B46: Barbeador 7x1 | D46: Peixes | E46: 65 | F46: 120 | G46: =F46-E46 -> 55 | H46: Vendido
A47: 4 | B47: Case HD inova | D47: Cliente case 2 | E47: 14 | F47: 30 | G47: =F47-E47 -> 16 | H47: Vendido
A48: 5 | B48: Compressor veicular | D48: Carlos | E48: 29 | F48: 50 | G48: =F48-E48 -> 21 | H48: Vendido
A49: 6 | B49: Compressor veicular | D49: Metro - shopping | E49: 29 | F49: 50 | G49: =F49-E49 -> 21 | H49: Vendido
A50: 7 | B50: Depilador Finishing | D50: JK | E50: 35 | F50: 70 | G50: =F50-E50 -> 35 | H50: Vendido
A51: 8 | B51: Depilador Finishing | D51: Cliente nara | E51: 35 | F51: 60 | G51: =F51-E51 -> 25 | H51: Vendido
A52: 9 | B52: Depilador Finishing | D52: Cida GAMA | E52: 35 | F52: 70 | G52: =F52-E52 -> 35 | H52: Vendido
A53: 10 | B53: Depilador Finishing | D53: Valeria | E53: 35 | F53: 60 | G53: =F53-E53 -> 25 | H53: Vendido
A54: 11 | B54: Dock Station para HD Sata e Ide KP-HD005 - Knup | D54: Taguatinga - loja | E54: 100 | F54: 78 | G54: =F54-E54 -> -22 | H54: Vendido
A55: 12 | B55: Fone M-05 | D55: Bianca | E55: 28 | F55: 50 | G55: =F55-E55 -> 22 | H55: Vendido
... A72: 29 | B72: Multímetro Digital DT-830b | D72: Vicente pires | E72: 14 | F72: 25 | G72: =F72-E72 -> 11 | H72: Vendido
A73: 30 | B73: Multímetro Digital DT-830b | E73: 14 | F73: 20 | G73: =F73-E73 -> 6 | H73: Vendido
A74: 31 | B74: Multímetro MD-180l | E74: 30 | F74: 50 | G74: =F74-E74 -> 20 | H74: Vendido
A75: 32 | B75: Multímetro MD-180l | D75: 202 | E75: 30 | F75: 65 | G75: =F75-E75 -> 35 | H75: Vendido
A76: 33 | B76: Organizador 7000 | D76: Moto
A77: 34 | B77: Organizador 7000 | D77: Jussara
A78: 35 | B78: Organizador 7000 | D78: 408
A79: 36 | B79: Organizador 7000 | D79: floricultora
A80: 37 | B80: Organizador 7000 | D80: Maria Heloise
A81: 38 | B81: Organizador 7000 | D81: Gama
A82: 39 | B82: Organizador 7000 | D82: Carlos
A83: 40 | B83: Organizador 7000 | D83: Maria Heloise
A84: 41 | B84: Organizador 7000 | D84: Maria Heloise
A85: 42 | B85: Pop metal | D85: Amigas do Higor
A86: 43 | B86: Pop metal
A87: 44 | B87: Pop socket 3D | D87: Higor
A88: 45 | B88: Pop socket 3D | D88: Higor
A89: 46 | B89: Pop socket 3D | D89: Higor
A90: 47 | B90: Pop socket 3D | D90: Higor
A91: 48 | B91: Pop socket 3D | D91: Amigas do Higor
A92: 49 | B92: Pop socket 3D | D92: Amigas do Higor
A93: 50 | B93: Pop socket 3D | D93: Amigas do Higor | E93: 1.4 | F93: 5 | G93: =F93-E93 -> 3.6 | H93: Vendido
A94: 51 | B94: Pop socket 3D | D94: Amigas do Higor | E94: 1.4 | F94: 5 | G94: =F94-E94 -> 3.6 | H94: Vendido
A95: 52 | B95: Pop socket 3D | D95: Amigas do Higor | E95: 1.4 | F95: 5 | G95: =F95-E95 -> 3.6 | H95: Vendido
A96: 53 | B96: Pop socket 3D | E96: 1.4 | F96: 5 | G96: =F96-E96 -> 3.6 | H96: Vendido
A97: 54 | B97: Pop socket 3D | E97: 1.4 | F97: 5 | G97: =F97-E97 -> 3.6 | H97: Vendido
A98: 55 | B98: Smartwatch A1 | D98: Goiano | E98: 55 | F98: 100 | G98: =F98-E98 -> 45 | H98: Vendido
A99: 56 | B99: Smartwatch Dz09 | D99: Fabrício | E99: 55 | F99: 100 | G99: =F99-E99 -> 45 | H99: Vendido
A100: 57 | B100: Smartwatch F1 Plus | D100: Higor | E100: 55 | F100: 100 | G100: =F100-E100 -> 45 | H100: Vendido
A101: 58 | B101: Smartwatch F1 Plus | D101: Ana p7 | E101: 60 | F101: 100 | G101: =F101-E101 -> 40 | H101: Vendido
A102: 59 | B102: Smartwatch F1 Plus | D102: Ana p7 | E102: 60 | F102: 100 | G102: =F102-E102 -> 40 | H102: Vendido
A103: 60 | B103: Smartwatch F1 Plus | D103: Bianca | E103: 60 | F103: 100 | G103: =F103-E103 -> 40 | H103: Vendido
A104: 61 | B104: Smartwatch F1 Plus | D104: Gama | E104: 60 | F104: 140 | G104: =F104-E104 -> 80 | H104: Vendido
A105: 62 | B105: Smartwatch F1 Plus | D105: Karen | E105: 60 | F105: 100 | G105: =F105-E105 -> 40 | H105: Vendido
A106: 63 | B106: Smartwatch F1 Plus | D106: Wesley p7 | E106: 60 | F106: 100 | G106: =F106-E106 -> 40 | H106: Vendido
A107: 64 | B107: Smartwatch F1 Plus | D107: Professor academia | E107: 60 | F107: 100 | G107: =F107-E107 -> 40 | H107: Vendido
A108: 65 | B108: Smartwatch F1 Plus | D108: Menina Fit time | E108: 60 | F108: 100 | G108: =F108-E108 -> 40 | H108: Vendido
A109: 66 | B109: Switch 24 portas | E109: 0 | F109: 20 | G109: 20 | H109: Vendido
A110: 67 | B110: Umidificador lua tek lk-109 | D110: 302 | E110: 24 | F110: 30 | G110: =F110-E110 -> 6 | H110: Vendido
A111: Maio | E111: =SUM(E112:E186) -> 2043.1 | F111: =SUM(F112:F186) -> 3243 | G111: 2048.2 | H111: =COUNTIF(H112:H186,"Vendido") -> 75 | I111: =SUM(F111-E111)/F111 -> 0.36999692
A112: 1 | B112: Lanterna Lampião 6x1 | D112: Joao Pedro | E112: 16 | F112: 30 | G112: =F112-E112 -> 14 | H112: Vendido | I112: =SUM(F112-E112)/F112 -> 0.46666667 | K112: 43613
A113: 2 | B113: Lanterna Lampião 6x1 | D113: Riacho Tony | E113: 16 | F113: 30 | G113: =F113-E113 -> 14 | H113: Vendido | I113: =SUM(F113-E113)/F113 -> 0.46666667 | K113: 43586
A114: 3 | B114: Lanterna Lampião 6x1 | D114: Riacho Tony | E114: 16 | F114: 30 | G114: =F114-E114 -> 14 | H114: Vendido | I114: =SUM(F114-E114)/F114 -> 0.46666667 | K114: 43586
A115: 4 | B115: Lanterna Lampião 6x1 | D115: Riacho Tony | E115: 16 | F115: 30 | G115: =F115-E115 -> 14 | H115: Vendido | I115: =SUM(F115-E115)/F115 -> 0.46666667 | K115: 43586 | S115: Smartwatch m4
A116: 5 | B116: Suporte de celular | D116: Riacho Tony | E116: 10 | F116: 15 | G116: =F116-E116 -> 5 | H116: Vendido | I116: =SUM(F116-E116)/F116 -> 0.33333333 | K116: 43586
A117: 6 | B117: Lanterna Lampião 6x1 | D117: Olx Valdir | E117: 16 | F117: 30 | G117: =F117-E117 -> 14 | H117: Vendido | I117: =SUM(F117-E117)/F117 -> 0.46666667 | K117: 43587
A118: 7 | B118: Lanterna Lampião 6x1 | D118: Olx Valdir | E118: 16 | F118: 30 | G118: =F118-E118 -> 14 | H118: Vendido | I118: =SUM(F118-E118)/F118 -> 0.46666667 | K118: 43587
A119: 8 | B119: case de HD | D119: 92664554 | E119: 16 | F119: 30 | G119: =F119-E119 -> 14 | H119: Vendido | I119: =SUM(F119-E119)/F119 -> 0.46666667 | K119: 43588
A120: 9 | B120: fone Sony | D120: 92664554 | E120: 25 | F120: 50 | G120: =F120-E120 -> 25 | H120: Vendido | I120: =SUM(F120-E120)/F120 -> 0.5 | K120: 43588
A121: 10 | B121: Jogo de chave 40 pçs MZA | D121: Senhor sábado | E121: 22 | F121: 50 | G121: =F121-E121 -> 28 | H121: Vendido | I121: =SUM(F121-E121)/F121 -> 0.56 | K121: 43588
...

Sheet Vendas
A1: Mes | B1: Nome | C1: cliente | D1: Valor vendido | E1: Valor de custo | F1: Lucro | G1: Situaçao
A2: 1 | B2: Tenebrios | D2: 10 | E2: 0 | F2: =D2-E2 -> 10 | G2: Concluido
A3: 1 | B3: Pc | D3: 300 | E3: 0 | F3: =D3-E3 -> 300 | G3: Concluido
A4: 2 | B4: TenebrioMulher passarinho | D4: 15 | E4: 0 | F4: =D4-E4 -> 15 | G4: Concluido
A5: 2 | B5: TenebrioMulher passarinho | D5: 30 | E5: 0 | F5: =D5-E5 -> 30 | G5: Concluido
A6: 3 | B6: Tenebrios 100 larvas | C6: Cliente besouro bike | D6: 10 | E6: 0 | F6: =D6-E6 -> 10 | G6: Concluido
A7: 3 | B7: Cortador de cabelo basico | C7: Cliente besouro bike | D7: 35 | E7: 17 | F7: =D7-E7 -> 18 | G7: Concluido
A8: 3 | B8: Smartwatch Academia | C8: Andre | D8: 100 | E8: 55 | F8: =D8-E8 -> 45 | G8: Concluido
A9: 3 | B9: Smartwatch | C9: Danni | D9: 105 | E9: 55 | F9: =D9-E9 -> 50 | G9: Concluido
A10: 3 | B10: Barbeador | C10: Tio Teinha | D10: 115 | E10: 65 | F10: =D10-E10 -> 50 | G10: Concluido
A11: 3 | B11: Multimetro Azul | C11: a125- | D11: 50 | E11: 30 | F11: =D11-E11 -> 20 | G11: Concluido
A12: 3 | B12: Suporte celular | C12: Mateus | D12: 10 | E12: 10 | F12: =D12-E12 -> 0 | G12: Concluido
A13: 3 | B13: Barbeador | C13: Danni | D13: 115 | E13: 65 | F13: =D13-E13 -> 50 | G13: Concluido
A14: 3 | B14: Powebank | C14: Danni | D14: 65 | E14: 28 | F14: =D14-E14 -> 37 | G14: Concluido
A15: 3 | B15: Mouse game 2 | C15: Mateus | D15: 5 | E15: 2 | F15: =D15-E15 -> 3 | G15: Concluido
A16: 3 | B16: Powebank | C16: Renada | D16: 30 | E16: 28 | F16: =D16-E16 -> 2 | G16: Concluido
A17: 3 | B17: cable cb-11 | C17: Mateus | D17: 5 | E17: 3 | F17: =D17-E17 -> 2 | G17: Concluido
... A34: 3 | B34: Cabo kingo | C34: Amiga higor | D34: 25 | E34: 6.8 | F34: =D34-E34 -> 18.2 | G34: Concluido
A35: 3 | B35: Processador | C35: olx | D35: 20 | F35: =D35-E35 -> 20 | G35: Concluido
A36: 3 | B36: fone sony | C36: ETB | D36: 50 | E36: 25 | F36: =D36-E36 -> 25 | G36: Concluido
A37: 3 | B37: Multimetro Azul | C37: ETB | D37: 55 | E37: 30 | F37: =D37-E37 -> 25 | G37: Concluido
A38: 3 | B38: fone sony | C38: Metro Taguatinga | D38: 50 | E38: 25 | F38: =D38-E38 -> 25 | G38: Concluido
A39: 3 | B39: Powebank | C39: Fabricio | D39: 57 | E39: 28 | F39: =D39-E39 -> 29 | G39: Concluido
A40: 3 | B40: Switch 24 portas | C40: olx | D40: 30 | F40: =D40-E40 -> 30 | G40: Concluido
A41: 3 | B41: Multimetro Azul | C41: Riacho | D41: 60 | E41: 30 | F41: =D41-E41 -> 30 | G41: Concluido
A42: 3 | B42: Fone completo | C42: Senhor sobradinho | D42: 80 | E42: 39 | F42: =D42-E42 -> 41 | G42: Concluido
A43: 3 | B43: Smartwatch prata | C43: Riacho olx | D43: 100 | E43: 55 | F43: =D43-E43 -> 45 | G43: Concluido
A44: 3 | B44: Relógio F1 plus | C44: Danni | D44: 110 | E44: 55 | F44: =D44-E44 -> 55 | G44: Concluido
A45: 3 | B45: Impressora | C45: olx | D45: 80 | E45: 55 | F45: =D45-E45 -> 25 | G45: Concluido
A46: 3 | B46: Smartwatch | C46: Andre | D46: 100 | E46: 55 | F46: =D46-E46 -> 45 | G46: Concluido
A47: 3 | B47: Compressor de Ar | C47: Segurança | D47: 50 | E47: 29 | F47: =D47-E47 -> 21 | G47: Concluido
A48: 4 | B48: Barbeador 7x1 | C48: Maria olx | D48: 100 | E48: 65 | F48: =D48-E48 -> 35 | G48: Concluido
A49: 4 | B49: Barbeador 7x1 | C49: Jean moto | D49: 115 | E49: 65 | F49: =D49-E49 -> 50 | G49: Concluido
A50: 4 | B50: Barbeador 7x1 | C50: Peixes | D50: 120 | E50: 65 | F50: =D50-E50 -> 55 | G50: Concluido
A51: 4 | B51: Case HD inova | C51: Cliente case 2 | D51: 30 | E51: 14 | F51: =D51-E51 -> 16 | G51: Concluido
A52: 4 | B52: Compressor veicular | C52: Carlos | D52: 50 | E52: 29 | F52: =D52-E52 -> 21 | G52: Concluido
... A76: 4 | B76: Multímetro Digital DT-830b | C76: Vicente pires | D76: 25 | E76: 14 | F76: =D76-E76 -> 11 | G76: Concluido
A77: 4 | B77: Multímetro Digital DT-830b | D77: 20 | E77: 14 | F77: =D77-E77 -> 6 | G77: Concluido
A78: 4 | B78: Multímetro MD-180l | D78: 50 | E78: 30 | F78: =D78-E78 -> 20 | G78: Concluido
A79: 4 | B79: Multímetro MD-180l | C79: 202 | D79: 65 | E79: 30 | F79: =D79-E79 -> 35 | G79: Concluido
A80: 4 | B80: Organizador 7000 | C80: Moto | D80: 40 | E80: 20 | F80: =D80-E80 -> 20 | G80: Concluido
A81: 4 | B81: Organizador 7000 | C81: Jussara | D81: 40 | E81: 20 | F81: =D81-E81 -> 20 | G81: Concluido
A82: 4 | B82: Organizador 7000 | C82: 408 | D82: 40 | E82: 20 | F82: =D82-E82 -> 20 | G82: Concluido
A83: 4 | B83: Organizador 7000 | C83: floricultora | D83: 30 | E83: 20 | F83: =D83-E83 -> 10 | G83: Concluido
A84: 4 | B84: Organizador 7000 | C84: Maria Heloise | D84: 20 | E84: 20 | F84: =D84-E84 -> 0 | G84: Concluido
A85: 4 | B85: Organizador 7000 | C85: Gama | D85: 60 | E85: 20 | F85: =D85-E85 -> 40 | G85: Concluido
A86: 4 | B86: Organizador 7000 | C86: Carlos | D86: 40 | E86: 20 | F86: =D86-E86 -> 20 | G86: Concluido
A87: 4 | B87: Organizador 7000 | C87: Maria Heloise | D87: 40 | E87: 20 | F87: =D87-E87 -> 20 | G87: Concluido
A88: 4 | B88: Organizador 7000 | C88: Maria Heloise | D88: 40 | E88: 20 | F88: =D88-E88 -> 20 | G88: Concluido
A89: 4 | B89: Pop metal | C89: Amigas do Higor | D89: 5 | E89: 2 | F89: =D89-E89 -> 3 | G89: Concluido
A90: 4 | B90: Pop metal | D90: 5 | E90: 2 | F90: =D90-E90 -> 3 | G90: Concluido
A91: 4 | B91: Pop socket 3D | C91: Higor | D91: 5 | E91: 1.4 | F91: =D91-E91 -> 3.6 | G91: Concluido
A92: 4 | B92: Pop socket 3D | C92: Higor | D92: 5 | E92: 1.4 | F92: =D92-E92 -> 3.6 | G92: Concluido
A93: 4 | B93: Pop socket 3D | C93: Higor | D93: 5 | E93: 1.4 | F93: =D93-E93 -> 3.6 | G93: Concluido
A94: 4 | B94: Pop socket 3D | C94: Higor | D94: 5 | E94: 1.4 | F94: =D94-E94 -> 3.6 | G94: Concluido
A95: 4 | B95: Pop socket 3D | C95: Amigas do Higor | D95: 5 | E95: 1.4 | F95: =D95-E95 -> 3.6 | G95: Concluido
A96: 4 | B96: Pop socket 3D | C96: Amigas do Higor | D96: 5 | E96: 1.4 | F96: =D96-E96 -> 3.6 | G96: Concluido
A97: 4 | B97: Pop socket 3D | C97: Amigas do Higor | D97: 5 | E97: 1.4 | F97: =D97-E97 -> 3.6 | G97: Concluido
A98: 4 | B98: Pop socket 3D | C98: Amigas do Higor | D98: 5 | E98: 1.4 | F98: =D98-E98 -> 3.6 | G98: Concluido
A99: 4 | B99: Pop socket 3D | C99: Amigas do Higor | D99: 5 | E99: 1.4 | F99: =D99-E99 -> 3.6 | G99: Concluido
A100: 4 | B100: Pop socket 3D | D100: 5 | E100: 1.4 | F100: =D100-E100 -> 3.6 | G100: Concluido
A101: 4 | B101: Pop socket 3D | D101: 5 | E101: 1.4 | F101: =D101-E101 -> 3.6 | G101: Concluido
A102: 4 | B102: Smartwatch A1 | C102: Goiano | D102: 100 | E102: 55 | F102: =D102-E102 -> 45 | G102: Concluido
A103: 4 | B103: Smartwatch Dz09 | C103: Fabrício | D103: 100 | E103: 55 | F103: =D103-E103 -> 45 | G103: Concluido
A104: 4 | B104: Smartwatch F1 Plus | C104: Higor | D104: 100 | E104: 55 | F104: =D104-E104 -> 45 | G104: Concluido
A105: 4 | B105: Smartwatch F1 Plus | C105: Ana p7 | D105: 100 | E105: 60 | F105: =D105-E105 -> 40 | G105: Concluido
A106: 4 | B106: Smartwatch F1 Plus | C106: Ana p7 | D106: 100 | E106: 60 | F106: =D106-E106 -> 40 | G106: Concluido
A107: 4 | B107: Smartwatch F1 Plus | C107: Bianca | D107: 100 | E107: 60 | F107: =D107-E107 -> 40 | G107: Concluido
A108: 4 | B108: Smartwatch F1 Plus | C108: Gama | D108: 140 | E108: 60 | F108: =D108-E108 -> 80 | G108: Concluido
A109: 4 | B109: Smartwatch F1 Plus | C109: Karen | D109: 100 | E109: 60 | F109: =D109-E109 -> 40 | G109: Concluido
A110: 4 | B110: Smartwatch F1 Plus | C110: Wesley p7 | D110: 100 | E110: 60 | F110: =D110-E110 -> 40 | G110: Concluido
A111: 4 | B111: Smartwatch F1 Plus | C111: Professor academia | D111: 100 | E111: 60 | F111: =D111-E111 -> 40 | G111: Concluido
A112: 4 | B112: Smartwatch F1 Plus | C112: Menina Fit time | D112: 100 | E112: 60 | F112: =D112-E112 -> 40 | G112: Concluido
A113: 4 | B113: Switch 24 portas | D113: 20 | E113: 0 | F113: =D113-E113 -> 20 | G113: Concluido
A114: 4 | B114: Umidificador Atacado | C114: 302 | D114: 30 | E114: 24 | F114: =D114-E114 -> 6 | G114: Concluido
A115: 5 | B115: Lanterna Lampião 6x1 | C115: Joao pedro | D115: 30 | E115: 16 | F115: =D115-E115 -> 14 | G115: Concluido
A116: 5 | B116: Lanterna Lampião 6x1 | C116: Riacho tony | D116: 30 | E116: 16 | F116: =D116-E116 -> 14 | G116: Concluido
A117: 5 | B117: Lanterna Lampião 6x1 | C117: Riacho tony | D117: 30 | E117: 16 | F117: =D117-E117 -> 14 | G117: Concluido
A118: 5 | B118: Lanterna Lampião 6x1 | C118: Riacho tony | D118: 30 | E118: 16 | F118: =D118-E118 -> 14 | G118: Concluido
A119: 5 | B119: Suporte de celular | C119: Riacho tony | D119: 15 | E119: 10 | F119: =D119-E119 -> 5 | G119: Concluido
A120: 5 | B120: Lanterna Lampião 6x1 | C120: Olx Valdir | D120: 30 | E120: 16 | F120: =D120-E120 -> 14 | G120: Concluido
A121: 5 | B121: Lanterna Lampião 6x1 | C121: Olx Valdir | D121: 30 | E121: 16 | F121: =D121-E121 -> 14 | G121: Concluido
A122: 5 | B122: case de HD | C122: 92664554 | D122: 30 | E122: 16 | F122: =D122-E122 -> 14 | G122: Concluido
A123: 5 | B123: fone Sony | C123: 92664554 | D123: 50 | E123: 25 | F123: =D123-E123 -> 25 | G123: Concluido
A124: 5 | B124: Jogo de chave 40 pçs MZA | C124: Senhor sábado | D124: 50 | E124: 22 | F124: =D124-E124 -> 28 | G124: Concluido
A125: 5 | B125: Lanterna Lampião 6x1 | C125: 92664554 | D125: 35 | E125: 16 | F125: =D125-E125 -> 19 | G125: Concluido
A126: 5 | B126: Bloqueador de Bicicleta - Alta Proteção - BL01 - LuaTek | C126: Menino bike | D126: 30 | E126: 11.8 | F126: =D126-E126 -> 18.2 | G126: Concluido
A127: 5 | B127: Depilador Finishing | D127: 65 | E127: 35 | F127: =D127-E127 -> 30 | G127: Concluido
A128: 5 | B128: Compressor veicular | C128: Cliente top 200 | D128: 50 | E128: 27 | F128: =D128-E128 -> 23 | G128: Concluido
A129: 5 | B129: Depilador Finishing | C129: Cliente top 200 | D129: 60 | E129: 35 | F129: =D129-E129 -> 25 | G129: Concluido
A130: 5 | B130: Jogo de chave 40 pçs MZA | C130: Guará 1 | D130: 60 | E130: 22 | F130: =D130-E130 -> 38 | G130: Concluido
A131: 5 | B131: Jogo de chave 40 pçs MZA | C131: Senhor da Van | D131: 50 | E131: 22 | F131: =D131-E131 -> 28 | G131: Concluido
A132: 5 | B132: Lanterna Lampião 6x1 | C132: Cliente top 200 | D132: 30 | E132: 16 | F132: =D132-E132 -> 14 | G132: Concluido
A133: 5 | B133: Power Bank inova POW-8012 | C133: Cliente top 200 | D133: 50 | E133: 28 | F133: =D133-E133 -> 22 | G133: Concluido
A134: 5 | B134: Morsa jf-8001 | C134: Menino analf ceilandia | D134: 22 | E134: 11 | F134: =D134-E134 -> 11 | G134: Concluido
A135: 5 | B135: Smartwatch F1 Plus | C135: Ana Portaria P7 | D135: 105 | E135: 60 | F135: =D135-E135 -> 45 | G135: Concluido
A136: 5 | B136: Smartwatch M3 | C136: Vitoria Amiga ana | D136: 100 | E136: 60 | F136: =D136-E136 -> 40 | G136: Concluido
A137: 5 | B137: Morsa jf-8001 | C137: 115 Microondas | D137: 25 | E137: 11 | F137: =D137-E137 -> 14 | G137: Concluido
A138: 5 | B138: Dock Station para HD Sata e Ide KP-HD005 - Knup | C138: Clinica geral w3 | D138: 110 | E138: 78 | F138: =D138-E138 -> 32 | G138: Concluido
A139: 5 | B139: Dock Station para HD Sata e Ide KP-HD005 - Knup | C139: Clinica geral w3 | D139: 110 | E139: 78 | F139: =D139-E139 -> 32 | G139: Concluido
...

Sheet Controlde de entrega
A1: Produtos | B1: Cliente | C1: S | D1: T | E1: Q | F1: Q | G1: S | H1: S | I1: D | J1: Quat | K1: Frete | L1: V.V | M1: V.P | N1: Lucro | O1: Horario | P1: Lugar | Q1: Situação
C18: =COUNTA(C2:C17) -> 0 | D18: =COUNTA(D2:D17) -> 0 | E18: =COUNTA(E2:E17) -> 0 | F18: =COUNTA(F2:F17) -> 0 | G18: =COUNTA(G2:G17) -> 0 | H18: =COUNTA(H2:H17) -> 0 | I18: =COUNTA(I2:I17) -> 0 | J18: =SUM(J2:J17) -> 0 | L18: =SUM(L2:L17) -> 0 | M18: =SUM(M2:M17) -> 0 | N18: =SUM(N2:N17) -> 0
